Workbook

Sheet Valuation Summary
A1: Eli Lilly Valuation
A2: Valuation Date | B2: 45747
A4: Multiples Valuation | D4: Free Cash Flow Valuation | G4: Market Conditions at Valuation Date
B6: Price Per | E6: Price Per
B7: Share | E7: Share | G7: Price Per Share | I7: 825.91
A8: LTM EBITDA | B8: ='Multiples Valuation'!I42 -> 143.59047 | D8: Base Case | E8: ='Free Cash Flow Valuation'!G52 -> 828.44993
A9: NTM EBITDA | B9: ='Multiples Valuation'!J42 -> 201.33899 | D9: Higher Growth by 0.5% | E9: ='Free Cash Flow Valuation'!R50 -> 1002.3837 | G9: Conclusion
A10: NTM EPS | B10: ='Multiples Valuation'!I32 -> 204.60999 | D10: Lower Growth by 0.5% | E10: ='Free Cash Flow Valuation'!P50 -> 709.11312
D11: Higher WACC by 0.5% | E11: ='Free Cash Flow Valuation'!Q51 -> 693.64483 | G11: Significantly Undervalued
A12: Low | B12: =MIN($B$8:$B$10) -> 143.59047 | D12: Lower WACC by 0.5% | E12: ='Free Cash Flow Valuation'!Q49 -> 1024.8969 | G12: Slightly Undervalued
A13: High | B13: =MAX($B$8:$B$10) -> 204.60999 | G13: Fairly Priced | I13: X | J13: Based on FCF valuation
A14: Mean | B14: =AVERAGE($B$8:$B$10) -> 183.17982 | D14: Low | E14: =MIN($E$8:$E$12) -> 693.64483 | G14: Slightly Overvalued
A15: Median | B15: =MEDIAN($B$8:$B$10) -> 201.33899 | D15: High | E15: =MAX($E$8:$E$12) -> 1024.8969 | G15: Significantly Overvalued | I15: X | J15: Based on comparable multiples
D16: Mean | E16: =AVERAGE($E$8:$E$12) -> 851.6977
D17: Median | E17: =MEDIAN($E$8:$E$12) -> 828.44993

Sheet Multiples Valuation
A1: Multiples Valuation | P1: Eli Lilly and Company (NYSE:LLY) | S1: LLY
P2: 825.91
A3: 1. Comparable Firm Values (exclude your target firm) | P3: {=INDIRECT("'"&S1&"'!C9")} -> 898
C4: @3/31/2025 | E4: [C] * [D] | H4: [F]-[G] | I4: [E]+[H]
C5: Price Per | D5: Shares | E5: Market | F5: Total | G5: Cash and | H5: Net | I5: Enterprise
A6: Firm | B6: Ticker | C6: Share | D6: Out | E6: Cap | F6: Debt | G6: ST Invest | H6: Debt | I6: Value
A7: Johnson & Johnson (NYSE:JNJ) | B7: JNJ | C7: 165.84 | D7: {=INDIRECT("'"&B7&"'!C9")} -> 2409.8 | E7: =C7*D7 -> 399641.23 | F7: =VLOOKUP($A7,Screening!$A$8:$S$149,15,FALSE) -> 37834 | G7: =VLOOKUP($A7,Screening!$A$8:$S$149,14,FALSE) -> 24522 | H7: =F7-G7 -> 13312 | I7: =E7+H7 -> 412953.23
A8: Merck & Co., Inc. (NYSE:MRK) | B8: MRK | C8: 89.76 | D8: {=INDIRECT("'"&B8&"'!C9")} -> 2516.4 | E8: =C8*D8 -> 225872.06 | F8: =VLOOKUP($A8,Screening!$A$8:$S$149,15,FALSE) -> 38270 | G8: =VLOOKUP($A8,Screening!$A$8:$S$149,14,FALSE) -> 13689 | H8: =F8-G8 -> 24581 | I8: =E8+H8 -> 250453.06
A9: Pfizer Inc. (NYSE:PFE) | B9: PFE | C9: 25.34 | D9: {=INDIRECT("'"&B9&"'!C9")} -> 5671.5 | E9: =C9*D9 -> 143715.81 | F9: =VLOOKUP($A9,Screening!$A$8:$S$149,15,FALSE) -> 67418 | G9: =VLOOKUP($A9,Screening!$A$8:$S$149,14,FALSE) -> 20477 | H9: =F9-G9 -> 46941 | I9: =E9+H9 -> 190656.81
A10: Bristol-Myers Squibb Company (NYSE:BMY) | B10: BMY | C10: 60.99 | D10: {=INDIRECT("'"&B10&"'!C9")} -> 2034.8 | E10: =C10*D10 -> 124102.45 | F10: =VLOOKUP($A10,Screening!$A$8:$S$149,15,FALSE) -> 51257 | G10: =VLOOKUP($A10,Screening!$A$8:$S$149,14,FALSE) -> 10859 | H10: =F10-G10 -> 40398 | I10: =E10+H10 -> 164500.45
A11: Zoetis Inc. (NYSE:ZTS) | B11: ZTS | C11: 164.65 | D11: 448.47307 | E11: =C11*D11 -> 73841.091 | F11: =VLOOKUP($A11,Screening!$A$8:$S$149,15,FALSE) -> 6829 | G11: =VLOOKUP($A11,Screening!$A$8:$S$149,14,FALSE) -> 1987 | H11: =F11-G11 -> 4842 | I11: =E11+H11 -> 78683.091
A12: Viatris Inc. (NasdaqGS:VTRS) | B12: VTRS | C12: 8.71 | D12: {=INDIRECT("'"&B12&"'!C9")} -> 1193.7 | E12: =C12*D12 -> 10397.127 | F12: =VLOOKUP($A12,Screening!$A$8:$S$149,15,FALSE) -> 14305.9 | G12: =VLOOKUP($A12,Screening!$A$8:$S$149,14,FALSE) -> 1089.9 | H12: =F12-G12 -> 13216 | I12: =E12+H12 -> 23613.127
A13: Organon & Co. (NYSE:OGN) | B13: OGN | C13: 14.89 | D13: {=INDIRECT("'"&B13&"'!C9")} -> 258 | E13: =C13*D13 -> 3841.62 | F13: =VLOOKUP($A13,Screening!$A$8:$S$149,15,FALSE) -> 9036 | G13: =VLOOKUP($A13,Screening!$A$8:$S$149,14,FALSE) -> 675 | H13: =F13-G13 -> 8361 | I13: =E13+H13 -> 12202.62
A14: Jazz Pharmaceuticals plc (NasdaqGS:JAZZ) | B14: JAZZ | C14: 124.15 | D14: 60.631 | E14: =C14*D14 -> 7527.3387 | F14: =VLOOKUP($A14,Screening!$A$8:$S$149,15,FALSE) -> 6166.9 | G14: =VLOOKUP($A14,Screening!$A$8:$S$149,14,FALSE) -> 2993.8 | H14: =F14-G14 -> 3173.1 | I14: =E14+H14 -> 10700.439
A17: 2. Trailing and Forward Metrics (exclude your target firm)
C18: LTM | D18: NTM | E18: NTM
A19: Firm | B19: Ticker | C19: EBITDA | D19: EBITDA | E19: EPS
A20: =A7 -> Johnson & Johnson (NYSE:JNJ) | B20: =B7 -> JNJ | C20: =VLOOKUP($A20,Screening!$A$8:$S$149,5,FALSE) -> 29940 | D20: =VLOOKUP($A20,Screening!$A$8:$S$149,10,FALSE) -> 33182.8 | E20: =VLOOKUP($A20,Screening!$A$8:$S$149,13,FALSE) -> 10.6
A21: =A8 -> Merck & Co., Inc. (NYSE:MRK) | B21: =B8 -> MRK | C21: =VLOOKUP($A21,Screening!$A$8:$S$149,5,FALSE) -> 29134 | D21: =VLOOKUP($A21,Screening!$A$8:$S$149,10,FALSE) -> 30606.3 | E21: =VLOOKUP($A21,Screening!$A$8:$S$149,13,FALSE) -> 8.98
A22: =A9 -> Pfizer Inc. (NYSE:PFE) | B22: =B9 -> PFE | C22: =VLOOKUP($A22,Screening!$A$8:$S$149,5,FALSE) -> 23322 | D22: =VLOOKUP($A22,Screening!$A$8:$S$149,10,FALSE) -> 26638.8 | E22: =VLOOKUP($A22,Screening!$A$8:$S$149,13,FALSE) -> 2.95
A23: =A10 -> Bristol-Myers Squibb Company (NYSE:BMY) | B23: =B10 -> BMY | C23: =VLOOKUP($A23,Screening!$A$8:$S$149,5,FALSE) -> 19407 | D23: =VLOOKUP($A23,Screening!$A$8:$S$149,10,FALSE) -> 17661.4 | E23: =VLOOKUP($A23,Screening!$A$8:$S$149,13,FALSE) -> 6.74
A24: =A11 -> Zoetis Inc. (NYSE:ZTS) | B24: =B11 -> ZTS | C24: =VLOOKUP($A24,Screening!$A$8:$S$149,5,FALSE) -> 3829 | D24: =VLOOKUP($A24,Screening!$A$8:$S$149,10,FALSE) -> 4194.1 | E24: =VLOOKUP($A24,Screening!$A$8:$S$149,13,FALSE) -> 6.07
A25: =A12 -> Viatris Inc. (NasdaqGS:VTRS) | B25: =B12 -> VTRS | C25: =VLOOKUP($A25,Screening!$A$8:$S$149,5,FALSE) -> 4483.2 | D25: =VLOOKUP($A25,Screening!$A$8:$S$149,10,FALSE) -> 4019.4 | E25: =VLOOKUP($A25,Screening!$A$8:$S$149,13,FALSE) -> 2.2
A26: =A13 -> Organon & Co. (NYSE:OGN) | B26: =B13 -> OGN | C26: =VLOOKUP($A26,Screening!$A$8:$S$149,5,FALSE) -> 1765 | D26: =VLOOKUP($A26,Screening!$A$8:$S$149,10,FALSE) -> 1965.1 | E26: =VLOOKUP($A26,Screening!$A$8:$S$149,13,FALSE) -> 3.85
A27: =A14 -> Jazz Pharmaceuticals plc (NasdaqGS:JAZZ) | B27: =B14 -> JAZZ | C27: =VLOOKUP($A27,Screening!$A$8:$S$149,5,FALSE) -> 1521.7 | D27: =VLOOKUP($A27,Screening!$A$8:$S$149,10,FALSE) -> 1970.5 | E27: =VLOOKUP($A27,Screening!$A$8:$S$149,13,FALSE) -> 23.4 | G27: 4. Target Firm Valuation
I28: NTM
A29: 3. Trailing and Forward Multiples (leave negative multiples blank) | I29: EPS
C30: Ent Val / | D30: Ent Val / | E30: Share Price / | G30: Earnings-Per-Share | I30: =VLOOKUP(P1,Screening!$A$8:$S$149,13,FALSE) -> 23.2
C31: LTM | D31: NTM | E31: NTM | G31: Multpile from Comps | I31: =E42 -> 8.819396
A32: Firm | B32: Ticker | C32: EBITDA | D32: EBITDA | E32: EPS | G32: Estimated Price per Share | I32: =I30*I31 -> 204.60999
A33: =A7 -> Johnson & Johnson (NYSE:JNJ) | B33: =B7 -> JNJ | C33: =$I7/C20 -> 13.792693 | D33: =$I7/D20 -> 12.444798 | E33: =$C7/E20 -> 15.645283
A34: =A8 -> Merck & Co., Inc. (NYSE:MRK) | B34: =B8 -> MRK | C34: =$I8/C21 -> 8.5965904 | D34: =$I8/D21 -> 8.1830559 | E34: =$C8/E21 -> 9.9955457 | I34: LTM | J34: NTM
A35: =A9 -> Pfizer Inc. (NYSE:PFE) | B35: =B9 -> PFE | C35: =$I9/C22 -> 8.1749768 | D35: =$I9/D22 -> 7.1571096 | E35: =$C9/E22 -> 8.5898305 | I35: EBITDA | J35: EBITDA
A36: =A10 -> Bristol-Myers Squibb Company (NYSE:BMY) | B36: =B10 -> BMY | C36: =$I10/C23 -> 8.4763463 | D36: =$I10/D23 -> 9.314123 | E36: =$C10/E23 -> 9.0489614 | G36: EBITDA | I36: =VLOOKUP($P1,Screening!$A$8:$S$149,5,FALSE) -> 19268.3 | J36: =VLOOKUP($P1,Screening!$A$8:$S$149,10,FALSE) -> 27676.3
A37: =A11 -> Zoetis Inc. (NYSE:ZTS) | B37: =B11 -> ZTS | C37: =$I11/C24 -> 20.549253 | D37: =$I11/D24 -> 18.760423 | E37: =$C11/E24 -> 27.125206 | G37: Multpile from Comps | I37: =C42 -> 8.3256616 | J37: =D42 -> 7.6700827
A38: =A12 -> Viatris Inc. (NasdaqGS:VTRS) | B38: =B12 -> VTRS | C38: =$I12/C25 -> 5.2670251 | D38: =$I12/D25 -> 5.874789 | E38: =$C12/E25 -> 3.9590909 | G38: Estimated Enterprise Value | I38: =I36*I37 -> 160421.34 | J38: =J36*J37 -> 212279.51
A39: =A13 -> Organon & Co. (NYSE:OGN) | B39: =B13 -> OGN | C39: =$I13/C26 -> 6.9136657 | D39: =$I13/D26 -> 6.2096687 | E39: =$C13/E26 -> 3.8675325 | G39: Net Debt | I39: =VLOOKUP($P1,Screening!$A$8:$S$149,15,FALSE)-VLOOKUP($P1,Screening!$A$8:$S$149,14,FALSE) -> 31477.1 | J39: =VLOOKUP($P1,Screening!$A$8:$S$149,15,FALSE)-VLOOKUP($P1,Screening!$A$8:$S$149,14,FALSE) -> 31477.1
A40: =A14 -> Jazz Pharmaceuticals plc (NasdaqGS:JAZZ) | B40: =B14 -> JAZZ | C40: =$I14/C27 -> 7.0318976 | D40: =$I14/D27 -> 5.4303165 | E40: =$C14/E27 -> 5.3055556 | G40: Total Equity (Market Cap) | I40: =I38-I39 -> 128944.24 | J40: =J38-J39 -> 180802.41
G41: Shares Outstanding | I41: =LLY!$C$9 -> 898 | J41: =LLY!$C$9 -> 898
A42: Median | C42: =MEDIAN(C33:C40) -> 8.3256616 | D42: =MEDIAN(D33:D40) -> 7.6700827 | E42: =MEDIAN(E33:E40) -> 8.819396 | G42: Estimated Price Per share | I42: =I40/I41 -> 143.59047 | J42: =J40/J41 -> 201.33899

Sheet CAPM and WACC
A1: CAPM and WACC
A3: 1. Unlevering Betas
D4: From | E4: From
D5: Multiples | E5: Multiples | F5: [D]/[E]
H6: Unlevered
A7: Firm | B7: Ticker | C7: Beta (5Y) | D7: Net Debt | E7: Mkt Cap | F7: D/E | G7: Tax Rate | H7: Beta
A8: ='Multiples Valuation'!A7 -> Johnson & Johnson (NYSE:JNJ) | B8: ='Multiples Valuation'!B7 -> JNJ | C8: =HLOOKUP(B8,'Excess Returns and Beta'!$AB$64:$EN$126,63,FALSE) -> 0.4764287 | D8: ='Multiples Valuation'!H7 -> 13312 | E8: ='Multiples Valuation'!E7 -> 399641.23 | F8: =D8/E8 -> 0.033309876 | G8: {=INDIRECT("'"&B8&"'!D5")} -> 0.1664 | H8: =C8/(1+F8*(1-G8)) -> 0.46355706
A9: ='Multiples Valuation'!A8 -> Merck & Co., Inc. (NYSE:MRK) | B9: ='Multiples Valuation'!B8 -> MRK | C9: =HLOOKUP(B9,'Excess Returns and Beta'!$AB$64:$EN$126,63,FALSE) -> 0.35092769 | D9: ='Multiples Valuation'!H8 -> 24581 | E9: ='Multiples Valuation'!E8 -> 225872.06 | F9: =D9/E9 -> 0.10882709 | G9: {=INDIRECT("'"&B9&"'!D5")} -> 0.1667 | H9: =C9/(1+F9*(1-G9)) -> 0.32174963
A10: ='Multiples Valuation'!A9 -> Pfizer Inc. (NYSE:PFE) | B10: ='Multiples Valuation'!B9 -> PFE | C10: =HLOOKUP(B10,'Excess Returns and Beta'!$AB$64:$EN$126,63,FALSE) -> 0.63078468 | D10: ='Multiples Valuation'!H9 -> 46941 | E10: ='Multiples Valuation'!E9 -> 143715.81 | F10: =D10/E10 -> 0.32662377 | G10: {=INDIRECT("'"&B10&"'!D5")} -> 0.1482 | H10: =C10/(1+F10*(1-G10)) -> 0.49348751
A11: ='Multiples Valuation'!A10 -> Bristol-Myers Squibb Company (NYSE:BMY) | B11: ='Multiples Valuation'!B10 -> BMY | C11: =HLOOKUP(B11,'Excess Returns and Beta'!$AB$64:$EN$126,63,FALSE) -> 0.44306942 | D11: ='Multiples Valuation'!H10 -> 40398 | E11: ='Multiples Valuation'!E10 -> 124102.45 | F11: =D11/E11 -> 0.32552137 | G11: {=INDIRECT("'"&B11&"'!D5")} -> 0.1801 | H11: =C11/(1+F11*(1-G11)) -> 0.34972861
A12: ='Multiples Valuation'!A11 -> Zoetis Inc. (NYSE:ZTS) | B12: ='Multiples Valuation'!B11 -> ZTS | C12: =HLOOKUP(B12,'Excess Returns and Beta'!$AB$64:$EN$126,63,FALSE) -> 0.94650828 | D12: ='Multiples Valuation'!H11 -> 4842 | E12: ='Multiples Valuation'!E11 -> 73841.091 | F12: =D12/E12 -> 0.065573246 | G12: 0.209 | H12: =C12/(1+F12*(1-G12)) -> 0.89983523
A13: ='Multiples Valuation'!A12 -> Viatris Inc. (NasdaqGS:VTRS) | B13: ='Multiples Valuation'!B12 -> VTRS | C13: =HLOOKUP(B13,'Excess Returns and Beta'!$AB$64:$EN$126,63,FALSE) -> 0.81254761 | D13: ='Multiples Valuation'!H12 -> 13216 | E13: ='Multiples Valuation'!E12 -> 10397.127 | F13: =D13/E13 -> 1.2711204 | G13: {=INDIRECT("'"&B13&"'!D5")} -> 0.175 | H13: =C13/(1+F13*(1-G13)) -> 0.39662118
A14: ='Multiples Valuation'!A13 -> Organon & Co. (NYSE:OGN) | B14: ='Multiples Valuation'!B13 -> OGN | C14: =HLOOKUP(B14,'Excess Returns and Beta'!$AB$64:$EN$126,63,FALSE) -> 0.77500293 | D14: ='Multiples Valuation'!H13 -> 8361 | E14: ='Multiples Valuation'!E13 -> 3841.62 | F14: =D14/E14 -> 2.1764256 | G14: {=INDIRECT("'"&B14&"'!D5")} -> 0.2288 | H14: =C14/(1+F14*(1-G14)) -> 0.28934653
A15: ='Multiples Valuation'!A14 -> Jazz Pharmaceuticals plc (NasdaqGS:JAZZ) | B15: ='Multiples Valuation'!B14 -> JAZZ | C15: =HLOOKUP(B15,'Excess Returns and Beta'!$AB$64:$EN$126,63,FALSE) -> 0.44494593 | D15: ='Multiples Valuation'!H14 -> 3173.1 | E15: ='Multiples Valuation'!E14 -> 7527.3387 | F15: =D15/E15 -> 0.42154341 | G15: 0.148 | H15: =C15/(1+F15*(1-G15)) -> 0.32736953
A16: Average | H16: =AVERAGE(H8:H15) -> 0.44271191
A18: 2. Relevering Beta
A19: Comparable Unlevered Beta | B19: =AVERAGE(H8:H15) -> 0.44271191 | C19: average of comparable unlevered betas
A20: Net Debt | B20: ='Multiples Valuation'!I39 -> 31477.1
A21: Market Capitalization | B21: ='Multiples Valuation'!P2*'Multiples Valuation'!P3 -> 741667.18
A22: D/E Ratio | B22: =B20/B21 -> 0.042441004
A23: Tax Rate | B23: {=INDIRECT("'"&'Multiples Valuation'!S1&"'!D5")} -> 0.1603
A24: Estimated Levered Equity Beta | B24: =B19*(1+B22*(1-B23)) -> 0.45848915
A26: 3. CAPM
A27: Risk-Free Rate (10-year Treasury) | B27: 0.04245 | C27: from Federal Reserve Statistical Release (as of valuation date). Assume this is an APR with k=2
A28: Convert to EAR | B28: =(1+B27/2)^2-1 -> 0.042900501
A29: Market Risk Premium | B29: 0.05 | C29: Assumption, typically thought to be between 4% and 6%
A30: Expected Return on Equity | B30: =B28+B24*B29 -> 0.065824958
A32: 4. WACC
A33: Credit Rating | B33: Aa3/A+
A34: Expected Return on Debt | B34: 0.0501 | C34: ICE BofA Single-A US Corporate Index Effective Yield on 3/31
A35: Tax Rate | B35: =B23 -> 0.1603
A37: Expected Return on Equity | B37: =B30 -> 0.065824958 | C37: from CAPM
A39: Net Debt | B39: ='Multiples Valuation'!I39 -> 31477.1 | C39: from Multiples
A40: Market Capitalization | B40: =B21 -> 741667.18 | C40: shares times price per share (or just look it up on the comp search sheet)
A41: Enterprise Value | B41: =B40+B39 -> 773144.28 | C41: Net Debt + Market Capitalization
A43: Net Debt-to-Enterprise Value | B43: =B39/B41 -> 0.0407131
A44: Equity-to-Enterprise Value | B44: =B40/B41 -> 0.9592869
A46: WACC | B46: =B43*B34*(1-B35)+B44*B37 -> 0.064857778

Sheet Free Cash Flow Valuation
A1: FCF Valuation
A3: Key Inputs | N3: Notes | Z3: Data table increments
A4: Long-Term Growth Rate | G4: =L33+Z4 -> 0.038 | Z4: 0
A5: WACC | G5: ='CAPM and WACC'!B46+Z5 -> 0.064857778 | Z5: 0
B7: Historical | G7: Provided | J7: Our projections
B8: 2020A | C8: 2021A | D8: 2022A | E8: 2023A | F8: 2024A | G8: 2025E | H8: 2026E | I8: 2027E | J8: 2028E | K8: 2029E | L8: Terminal
A9: Revenue | B9: 24540 | C9: 28318 | D9: 28541 | E9: 34124 | F9: =VLOOKUP('Multiples Valuation'!$P$1,Screening!$A$8:$S$149,4,FALSE) -> 45042.7 | G9: =LLY!D2 -> 59413.32 | H9: =LLY!E2 -> 71106.58 | I9: =LLY!F2 -> 82961.51 | J9: =I9*(1+J10) -> 86114.047 | K9: =J9*(1+K10) -> 89386.381 | L9: =K9*(1+L10) -> 92783.064
A10: Growth | B10: =B9/22320-1 -> 0.099462366 | C10: =C9/B9-1 -> 0.15395273 | D10: =D9/C9-1 -> 0.0078748499 | E10: =E9/D9-1 -> 0.19561333 | F10: =F9/E9-1 -> 0.31997128 | G10: =G9/F9-1 -> 0.31904437 | H10: =H9/G9-1 -> 0.1968121 | I10: =I9/H9-1 -> 0.16672058 | J10: 0.038 | K10: 0.038 | L10: 0.038
A12: EBITDA | B12: =B15+B26 -> 8955.84 | C12: =C15+C26 -> 10014.682 | D12: =D15+D26 -> 10370.21 | E12: =E15+E26 -> 12359.3 | F12: =VLOOKUP('Multiples Valuation'!$P$1,Screening!$A$8:$S$149,5,FALSE) -> 19268.3 | G12: =LLY!D3 -> 27690.85 | H12: =LLY!E3 -> 34459.71 | I12: =LLY!F3 -> 41098.96 | J12: =J13*J9 -> 35306.759 | K12: =K13*K9 -> 36648.416 | L12: =L13*L9 -> 38041.056 | N12: 25 - '27 significant positive impact of Mounjaro, Zepbound, and incretins
A13: as % of Revenue | B13: =B12/B9 -> 0.36494866 | C13: =C12/C9 -> 0.35365075 | D13: =D12/D9 -> 0.36334431 | E13: =E12/E9 -> 0.3621879 | F13: =F12/F9 -> 0.42777853 | G13: =G12/G9 -> 0.46607141 | H13: =H12/H9 -> 0.48462055 | I13: =I12/I9 -> 0.49539793 | J13: 0.41 | K13: 0.41 | L13: 0.41 | N13: Tapered terminal margin down to '20 - '27 average
A15: EBIT | B15: 7631.94 | C15: 8467.082 | D15: 8847.71 | E15: 10832 | F15: =VLOOKUP('Multiples Valuation'!$P$1,Screening!$A$8:$S$149,6,FALSE) -> 17501.7 | G15: =LLY!D3-LLY!D4 -> 25918.98 | H15: =LLY!E3-LLY!E4 -> 32457 | I15: =LLY!F3-LLY!F4 -> 38721.6 | J15: =J16*J9 -> 31862.198 | K15: =K16*K9 -> 33072.961 | L15: =L16*L9 -> 34329.734 | N15: 25 - '27 significant positive impact of Mounjaro, Zepbound, and incretins
A16: as % of Revenue | B16: =B15/B9 -> 0.311 | C16: =C15/C9 -> 0.299 | D16: =D15/D9 -> 0.31 | E16: =E15/E9 -> 0.31743055 | F16: =F15/F9 -> 0.38855797 | G16: =G15/G9 -> 0.43624864 | H16: =H15/H9 -> 0.45645565 | I16: =I15/I9 -> 0.46674175 | J16: 0.37 | K16: 0.37 | L16: 0.37 | N16: Tapered terminal margin down to '20 - '27 average
A18: Tax Rate | B18: 0.142 | C18: 0.123 | D18: 0.103 | E18: 0.201 | F18: 0.169 | G18: =LLY!D5 -> 0.1603 | H18: =LLY!E5 -> 0.1621 | I18: =LLY!F5 -> 0.1631 | J18: 0.162 | K18: 0.162 | L18: 0.162
A19: Unlevered Income Taxes | G19: =G15*G18 -> 4154.8125 | H19: =H15*H18 -> 5261.2797 | I19: =I15*I18 -> 6315.493 | J19: =J15*J18 -> 5161.676 | K19: =K15*K18 -> 5357.8197 | L19: =L15*L18 -> 5561.4168
A21: After-Tax EBIT | G21: =(1-G18)*G15 -> 21764.168 | H21: =(1-H18)*H15 -> 27195.72 | I21: =(1-I18)*I15 -> 32406.107 | J21: =(1-J18)*J15 -> 26700.522 | K21: =(1-K18)*K15 -> 27715.141 | L21: =(1-L18)*L15 -> 28768.317
A23: Capital Expenditures | B23: 1387.9 | C23: 1309.8 | D23: 1854.3 | E23: 3448 | F23: 5058 | G23: =LLY!D6 -> 5067.81 | H23: =LLY!E6 -> 5235.77 | I23: =LLY!F6 -> 4892.61 | J23: =J9*J24 -> 6889.1238 | K23: =K9*K24 -> 7150.9105 | L23: =L9*L24 -> 7422.6451
A24: as % of Revenue | B24: =B23/B9 -> 0.056556642 | C24: =C23/C9 -> 0.046253266 | D24: =D23/D9 -> 0.064969693 | E24: =E23/E9 -> 0.10104325 | F24: =F23/F9 -> 0.11229345 | G24: =G23/G9 -> 0.085297539 | H24: =H23/H9 -> 0.073632707 | I24: =I23/I9 -> 0.058974457 | J24: 0.08 | K24: 0.08 | L24: 0.08
A26: Depreciation & Amortization | B26: 1323.9 | C26: 1547.6 | D26: 1522.5 | E26: 1527.3 | F26: 1766.6 | G26: =LLY!D4 -> 1771.87 | H26: =LLY!E4 -> 2002.71 | I26: =LLY!F4 -> 2377.36 | J26: =J12-J15 -> 3444.5619 | K26: =K12-K15 -> 3575.4552 | L26: =L12-L15 -> 3711.3225
A27: as % of Capital Expenditures | B27: =B26/B23 -> 0.95388717 | C27: =C26/C23 -> 1.1815544 | D27: =D26/D23 -> 0.82106455 | E27: =E26/E23 -> 0.44295244 | F27: =F26/F23 -> 0.34926849 | G27: =G26/G23 -> 0.34963229 | H27: =H26/H23 -> 0.38250534 | I27: =I26/I23 -> 0.48590834 | ... L27: =L26/L23 -> 0.5
A29: Change in Net Working Capital | G29: =LLY!D7-LLY!C7 -> 1136.9 | H29: =LLY!E7-LLY!D7 -> 1500 | I29: =LLY!F7-LLY!E7 -> 1000 | J29: =J30*(J9-I9) -> 315.25374 | K29: =K30*(K9-J9) -> 327.23338 | L29: =L30*(L9-K9) -> 339.66825
A30: as % of Revenue growth | G30: =G29/(G9-LLY!C2) -> 0.079112801 | H30: =H29/(H9-G9) -> 0.12827903 | I30: =I29/(I9-H9) -> 0.084353092 | J30: 0.1 | K30: 0.1 | L30: 0.1
A32: Unlevered Free Cash Flow | G32: =G21-G23+G26-G29 -> 17331.328 | H32: =H21-H23+H26-H29 -> 22462.66 | I32: =I21-I23+I26-I29 -> 28890.857 | J32: =J21-J23+J26-J29 -> 22940.706 | K32: =K21-K23+K26-K29 -> 23812.453 | L32: =L21-L23+L26-L29 -> 24717.326
A33: Growth | H33: =H32/G32-1 -> 0.29607269 | I33: =I32/H32-1 -> 0.28617255 | J33: =J32/I32-1 -> -0.20595274 | K33: =K32/J32-1 -> 0.038 | L33: =L32/K32-1 -> 0.038
A35: Portion of Year | G35: 0.75 | H35: 1 | I35: 1 | J35: 1 | K35: 1
A36: Time | G36: =G35 -> 0.75 | H36: =G36+1 -> 1.75 | I36: =H36+1 -> 2.75 | J36: =I36+1 -> 3.75 | K36: =J36+1 -> 4.75
A37: PV Factor | G37: =(1+$G$5)^-G36 -> 0.95396248 | H37: =(1+$G$5)^-H36 -> 0.89585905 | I37: =(1+$G$5)^-I36 -> 0.84129456 | J37: =(1+$G$5)^-J36 -> 0.79005345 | K37: =(1+$G$5)^-K36 -> 0.7419333
A39: PV of Free Cash Flow | G39: =G32*G35*G37 -> 12400.077 | H39: =H32*H35*H37 -> 20123.378 | I39: =I32*I35*I37 -> 24305.721 | J39: =J32*J35*J37 -> 18124.384 | K39: =K32*K35*K37 -> 17667.252
A41: First Stage PV | G41: =SUM(G39:K39) -> 92620.811
A43: Second Stage FV at 2029 | G43: =L32/(G5-G4) -> 920304.2 | H43: Implied Terminal Forward EBITDA multiple ----> | N43: second stage value as of 2029 divided by Terminal Year EBITDA
A44: Second Stage PV | G44: =G43*K37 -> 682804.33 | H44: Uses same PV factor as the 2029 FCF
A46: Enterprise Value | G46: =G44+G41 -> 775425.14 | N46: Sensitivity to growth rate and WACC
A47: Excess Cash | G47: =VLOOKUP('Multiples Valuation'!$P$1,Screening!$A$8:$S$149,14,FALSE) -> 3433.5 | P47: Growth rate sensitivity
A48: Firm Value | G48: =G46+G47 -> 778858.64 | O48: =G52 -> 828.44993 | P48: -0.005 | Q48: 0 | R48: 0.005
A49: Total Debt | G49: =VLOOKUP('Multiples Valuation'!$P$1,Screening!$A$8:$S$149,15,FALSE) -> 34910.6 | N49: WACC Sensitivity | O49: -0.005 | P49: 847.03091 | Q49: 1024.8969 | R49: 1308.2727
A50: Total Equity | G50: =G48-G49 -> 743948.04 | O50: 0 | P50: 709.11312 | Q50: 828.44993 | R50: 1002.3837
A51: Shares Outstanding | G51: ='Multiples Valuation'!I41 -> 898 | O51: 0.005 | P51: 608.59924 | Q51: 693.64483 | R51: 810.35558
A52: Price Per Share | G52: =G50/G51 -> 828.44993

Sheet JNJ
C1: 2024 (Historical) | D1: 2025 | E1: 2026 | F1: 2027
A2: Revenue | B2: millions of USD | C2: 88821 | D2: 90259.52 | E2: 94012.03 | F2: 98044.27
A3: EBITDA | B3: millions of USD | D3: 33274.21 | E3: 34681.25 | F3: 37635.96
A4: Depreciation & Amortization | B4: millions of USD | D4: 7548.93 | E4: 7744.91 | F4: 8105.09
A5: Income Tax Rate | B5: percentage | D5: 0.1664 | E5: 0.1675 | F5: 0.1676
A6: Capital Expenditures | B6: millions of USD | D6: 3918.09 | E6: 4071.27 | F6: 4078.21
A7: Level of Net Working Capital | B7: millions of USD | C7: 5572 | D7: 5820 | E7: 6090 | F7: 6200
A9: Shares Outstanding | B9: millions of shares | C9: 2409.8

Sheet MRK
C1: 2024 (Historical) | D1: 2025 | E1: 2026 | F1: 2027
A2: Revenue | B2: millions of USD | C2: 64168 | D2: 65084.56 | E2: 69327.83 | F2: 72952.46
A3: EBITDA | B3: millions of USD | D3: 30535.91 | E3: 33166.32 | F3: 35762.91
A4: Depreciation & Amortization | B4: millions of USD | D4: 3060.47 | E4: 3069.27 | F4: 3073.42
A5: Income Tax Rate | B5: percentage | D5: 0.1667 | E5: 0.1679 | F5: 0.1679
A6: Capital Expenditures | B6: millions of USD | D6: 3277.8 | E6: 3566.17 | F6: 3466.75
A7: Level of Net Working Capital | B7: millions of USD | C7: 10362 | D7: 11000 | E7: 11500 | F7: 12000
A9: Shares Outstanding | B9: millions of shares | C9: 2516.4

Sheet PFE
C1: 2024 (Historical) | D1: 2025 | E1: 2026 | F1: 2027
A2: Revenue | B2: millions of USD | C2: 63627 | D2: 62900.36 | E2: 62889.41 | F2: 61712.85
A3: EBITDA | B3: millions of USD | D3: 26581.67 | E3: 26735.33 | F3: 26148.63
A4: Depreciation & Amortization | B4: millions of USD | D4: 7189.01 | E4: 7028.68 | F4: 6944.95
A5: Income Tax Rate | B5: percentage | D5: 0.1482 | E5: 0.1494 | F5: 0.1494
A6: Capital Expenditures | B6: millions of USD | D6: 2907.74 | E6: 2724.11 | F6: 2625.51
A7: Level of Net Working Capital | B7: millions of USD | C7: 7363 | D7: 7800 | E7: 8200 | F7: 8700
A9: Shares Outstanding | B9: millions of shares | C9: 5671.5

Sheet BMY
C1: 2024 (Historical) | D1: 2025 | E1: 2026 | F1: 2027
A2: Revenue | B2: millions of USD | C2: 48300 | D2: 45803.74 | E2: 43015.2 | F2: 42813.06
A3: EBITDA | B3: millions of USD | D3: 17563.89 | E3: 15383.14 | F3: 15586.14
A4: Depreciation & Amortization | B4: millions of USD | D4: 6162.06 | E4: 5122.49 | F4: 4709.72
A5: Income Tax Rate | B5: percentage | D5: 0.1801 | E5: 0.1751 | F5: 0.1754
A6: Capital Expenditures | B6: millions of USD | D6: 1138.68 | E6: 1104.42 | F6: 1086.14
A7: Level of Net Working Capital | B7: millions of USD | C7: 6006 | D7: 6000 | E7: 6500 | F7: 7000
A9: Shares Outstanding | B9: millions of shares | C9: 2034.8

Sheet VTRS
C1: 2024 (Historical) | D1: 2025 | E1: 2026 | F1: 2027
A2: Revenue | B2: millions of USD | C2: 14739 | D2: 13793.55 | E2: 13958.57 | F2: 14104.99
A3: EBITDA | B3: millions of USD | D3: 4023.64 | E3: 4183.27 | F3: 4401.5
A4: Depreciation & Amortization | B4: millions of USD | D4: 342.02 | E4: 333.12 | F4: 253.16
A5: Income Tax Rate | B5: percentage | D5: 0.175 | E5: 0.1888 | F5: 0.1833
A6: Capital Expenditures | B6: millions of USD | D6: 377.2 | E6: 410.62 | F6: 391.46
A7: Level of Net Working Capital | B7: millions of USD | C7: 3738.4 | D7: 3750 | E7: 3800 | F7: 3850
A9: Shares Outstanding | B9: millions of shares | C9: 1193.7

Sheet OGN
C1: 2024 (Historical) | D1: 2025 | E1: 2026 | F1: 2027
A2: Revenue | B2: millions of USD | C2: 6403 | D2: 6286.58 | E2: 6366.46 | F2: 6341.67
A3: EBITDA | B3: millions of USD | D3: 1967.16 | E3: 2007.33 | F3: 2077.81
A4: Depreciation & Amortization | B4: millions of USD | D4: 187.75 | E4: 196.25 | F4: 222.33
A5: Income Tax Rate | B5: percentage | D5: 0.2288 | E5: 0.235 | F5: 0.2317
A6: Capital Expenditures | B6: millions of USD | D6: 192 | E6: 207 | F6: 185.33
A7: Level of Net Working Capital | B7: millions of USD | C7: 1630 | D7: 1675 | E7: 1725 | F7: 1800
A9: Shares Outstanding | B9: millions of shares | C9: 258

Sheet PRGO
C1: 2024 (Historical) | D1: 2025 | E1: 2026 | F1: 2027
A2: Revenue | B2: millions of USD | C2: 4373.4 | D2: 4436.44 | E2: 4537.89 | F2: 4661.4
A3: EBITDA | B3: millions of USD | D3: 764.92 | E3: 824.87 | F3: 890.36
A4: Depreciation & Amortization | B4: millions of USD | D4: 325.5 | E4: 334.27 | F4: 343.77
A5: Income Tax Rate | B5: percentage | D5: 0.201 | E5: 0.205 | F5: 0.205
A6: Capital Expenditures | B6: millions of USD | D6: 144 | E6: 147 | F6: 149
A7: Level of Net Working Capital | B7: millions of USD | C7: 1437.7 | D7: 1600 | E7: 1700 | F7: 1725
A9: Shares Outstanding | B9: millions of shares | C9: 136.5

Sheet LLY
C1: 2024 (Historical) | D1: 2025 | E1: 2026 | F1: 2027
A2: Revenue | B2: millions of USD | C2: 45042.7 | D2: 59413.32 | E2: 71106.58 | F2: 82961.51
A3: EBITDA | B3: millions of USD | D3: 27690.85 | E3: 34459.71 | F3: 41098.96
A4: Depreciation & Amortization | B4: millions of USD | D4: 1771.87 | E4: 2002.71 | F4: 2377.36
A5: Income Tax Rate | B5: percentage | D5: 0.1603 | E5: 0.1621 | F5: 0.1631
A6: Capital Expenditures | B6: millions of USD | D6: 5067.81 | E6: 5235.77 | F6: 4892.61
A7: Level of Net Working Capital | B7: millions of USD | C7: 4363.1 | D7: 5500 | E7: 7000 | F7: 8000
A9: Shares Outstanding | B9: millions of shares | C9: 898

Sheet Tax Rates
A6: Capital IQ Company Screening Report > Taxes
A8: Company Name | B8: Exchange:Ticker | C8: Effective Tax Rate - Capital IQ [NTM] (%)
A9: Corcept Therapeutics Incorporated (NasdaqCM:CORT) | B9: NasdaqCM:CORT | C9: 17.3
A10: Journey Medical Corporation (NasdaqCM:DERM) | B10: NasdaqCM:DERM | C10: 21
A11: ANI Pharmaceuticals, Inc. (NasdaqGM:ANIP) | B11: NasdaqGM:ANIP | C11: 24.6
A12: Avadel Pharmaceuticals plc (NasdaqGM:AVDL) | B12: NasdaqGM:AVDL | C12: 9.25
A13: biote Corp. (NasdaqGM:BTMD) | B13: NasdaqGM:BTMD | C13: 23.6
A14: CorMedix Inc. (NasdaqGM:CRMD) | B14: NasdaqGM:CRMD | C14: 2
A15: Eton Pharmaceuticals, Inc. (NasdaqGM:ETON) | B15: NasdaqGM:ETON | C15: 10
A16: Harmony Biosciences Holdings, Inc. (NasdaqGM:HRMY) | B16: NasdaqGM:HRMY | C16: 23.7
A17: Harrow, Inc. (NasdaqGM:HROW) | B17: NasdaqGM:HROW | C17: 15
A18: Ligand Pharmaceuticals Incorporated (NasdaqGM:LGND) | B18: NasdaqGM:LGND | C18: 19.6
A19: Supernus Pharmaceuticals, Inc. (NasdaqGM:SUPN) | B19: NasdaqGM:SUPN | C19: 20.5
A20: Amphastar Pharmaceuticals, Inc. (NasdaqGS:AMPH) | B20: NasdaqGS:AMPH | C20: 20.4
... A33: Zoetis Inc. (NYSE:ZTS) | B33: NYSE:ZTS | C33: 20.9

Sheet Decimal Format
A1: YEAR | B1: MONTH | C1: SPY | D1: TBILL | E1: ACRS | F1: ADIL | G1: ALMS | H1: ALTS | I1: AMLX | J1: AMPH | K1: AMRX | L1: ANEB | M1: ANIP | N1: ANRO | O1: ANTX | P1: AQST | Q1: ARTL | R1: ARVN | S1: ASBP | T1: ASRT | U1: ATHA | V1: AVDL | W1: AVIR | X1: AXSM | Y1: AYTU | Z1: BFRI | AA1: BIOA | AB1: BMY | AC1: BTMD | AD1: CALC | AE1: CARA | AF1: CGTX | AG1: CING | AH1: CLSD | AI1: CNSP | AJ1: CNTX | AK1: COCP | AL1: COLL | AM1: CORT | AN1: CPHI | AO1: CPIX | AP1: CRMD | AQ1: CTNM | AR1: CTXR | AS1: CVKD | AT1: DARE | AU1: DERM | AV1: DRRX | AW1: ELAN | AX1: ELVN | AY1: ENVB | AZ1: EOLS | BA1: ESPR | BB1: ETON | BC1: EVOK | BD1: EWTX | BE1: EYEN | BF1: EYPT | BG1: FULC | BH1: GHRS | BI1: GRCE | BJ1: HEPA | BK1: HOTH | BL1: HRMY | BM1: HROW | BN1: IBO | BO1: IGC | BP1: IKNA | BQ1: INVA | BR1: IRD | BS1: ITCI | BT1: ITRM | BU1: IXHL | BV1: JAGX | BW1: JAZZ | BX1: JNJ | BY1: JUNS | BZ1: KPRX | CA1: LEXX | CB1: LGND | CC1: LLY | CD1: LPCN | CE1: LQDA | CF1: LYRA | CG1: MAZE | CH1: MBX | CI1: MIRA | CJ1: MRK | CK1: NBY | CL1: NKTR | CM1: NMRA | CN1: NRXP | CO1: NTRB | CP1: NUVB | CQ1: OCUL | CR1: OGN | CS1: OMER | CT1: OPTN | CU1: ORMP | CV1: PAHC | CW1: PBH | CX1: PCRX | CY1: PCSA | CZ1: PFE | DA1: PHAT | DB1: PLRX | DC1: PRGO | DD1: PRPH | DE1: PTPI | DF1: PULM | DG1: RANI | DH1: RAPP | DI1: RLMD | DJ1: RVPH | DK1: SAVA | DL1: SCLX | DM1: SCPH | DN1: SCYX | DO1: SEPN | DP1: SIGA | DQ1: SNES | DR1: SNOA | DS1: SUPN | DT1: SXTP | DU1: TARS | DV1: TELO | DW1: TERN | DX1: THRD | DY1: TLPH | DZ1: TLRY | EA1: TNFA | EB1: TRAW | EC1: TRVI | ED1: TTNP | EE1: TXMD | EF1: VERU | EG1: VRCA | EH1: VRPX | EI1: VTRS | EJ1: VTYX | EK1: VYNE | EL1: XERS | EM1: YCBD | EN1: ZTS | EO1: ZVRA
A2: 2020 | B2: 3 | C2: -0.12464237 | D2: 0.0020473632 | E2: -0.087719298 | F2: -0.097222222 | H2: -0.36 | J2: -0.035737492 | K2: -0.096103896 | M2: -0.15142679 | P2: -0.41286863 | Q2: -0.10280374 | R2: -0.14491831 | T2: -0.39814815 | V2: -0.20520521 | X2: -0.24576923 | Y2: 1.8301887 | AB2: -0.056215219 | AE2: -0.12109115 | AH2: -0.24107143 | AI2: -0.43548387 | AK2: -0.46616541 | AL2: -0.31242105 | AM2: -0.057844691 | AN2: -0.12280702 | AO2: -0.099255583 | AP2: -0.30961538 | AR2: -0.15730337 | AT2: -0.22018349 | AV2: -0.12429379 | AW2: -0.18284672 | AY2: -0.163034 | AZ2: -0.51688009 | BA2: -0.3755199 | BB2: -0.24074074 | BC2: -0.056910569 | BE2: -0.41025641 | BF2: -0.20930233 | BG2: -0.36892178 | BJ2: -0.50558659 | BK2: -0.27021226 | BM2: -0.30797101 | BO2: 0.11363636 | BQ2: -0.12694878 | BR2: -0.22746781 | BS2: -0.27156398 | BT2: 0.12916667 | BV2: -0.15789474 | BW2: -0.1295165 | BX2: -0.024910801 | BZ2: -0.095652174 | CA2: -0.12121212 | CB2: -0.22307692 | CC2: 0.099818252 | CD2: -0.034205231 | CE2: 0.14043584 | CJ2: 0.012951052 | CK2: 0.052631579 | CL2: -0.14223931 | CN2: 0.011267606 | CO2: 0.50000583 | CQ2: 0.052072264 | CS2: 0.12258606 | CT2: -0.25785124 | CU2: -0.25490196 | CV2: -0.038269983 | CW2: -0.018201285 | CX2: -0.22706316 | CY2: 0.025641026 | CZ2: -0.023339184 | DA2: -0.28516058 | DC2: -0.051291715 | DD2: -0.025728383 | DF2: -0.36875 | DI2: -0.30073801 | DJ2: -0.0037878788 | DK2: -0.26737968 | DM2: -0.16384181 | DN2: -0.1673774 | DP2: -0.04400049 | DQ2: -0.37650602 | DR2: -0.070208729 | DS2: 0 | DY2: -0.10606061 | DZ2: -0.52321552 | EA2: -0.23201439 | EB2: -0.30232558 | EC2: -0.36608863 | ED2: -0.11538462 | EE2: -0.37278107 | EF2: -0.20823245 | EG2: -0.079191238 | EK2: -0.091525424 | EL2: -0.45224719 | EM2: -0.088235294 | EN2: -0.11664052 | EO2: -0.25742574
A3: 2020 | B3: 4 | C3: 0.12698322 | D3: -0.00019324052 | E3: 0.27884615 | F3: 0.13846154 | H3: 0.16517857 | J3: 0.14218329 | K3: 0.043103448 | M3: -0.017918508 | P3: 0.96803653 | Q3: 0.22916667 | R3: 0.30272953 | T3: 0.35384615 | V3: 0.30730479 | X3: 0.61533231 | Y3: 0.093333333 | AB3: 0.099850495 | AE3: 0.12187737 | AH3: 0.16470588 | AI3: 0.36666667 | AK3: 0.32394366 | AL3: 0.26638089 | AM3: 0.064760303 | AN3: -0.04 | AO3: 0.090909091 | AP3: 0.15598886 | AR3: 0.53166667 | AT3: 0.30588235 | AV3: 0.37419355 | AW3: 0.10361769 | AY3: -0.052083333 | AZ3: 0.0024096386 | BA3: 0.25594672 | BB3: 0.26341463 | BC3: 0.14655172 | BE3: 0.59130435 | BF3: -0.049019608 | BG3: 0.056951424 | BJ3: 0.056497175 | BK3: 0.16013072 | BM3: 0.17539267 | BO3: 0.10204082 | BQ3: 0.20578231 | BR3: 0.055555556 | BS3: 0.14964216 | BT3: 0.29151292 | BV3: -0.05 | BW3: 0.10537397 | BX3: 0.14420735 | BZ3: 0.0019230769 | CA3: 0 | CB3: 0.35547305 | CC3: 0.11476347 | CD3: 0.15416667 | CE3: 0.057324841 | CJ3: 0.031192157 | CK3: 0.53333333 | CL3: 0.075630252 | CN3: 0.10027855 | CO3: -0.2 | CQ3: 0.16363636 | CS3: 0.24308153 | CT3: -0.10022272 | CU3: 0.016447368 | CV3: 0.10508994 | CW3: 0.10932388 | CX3: 0.23143454 | CY3: -0.25 | CZ3: 0.1752481 | DA3: 0.31061193 | DC3: 0.10833905 | DD3: -0.11642349 | DF3: 0.36633663 | DI3: 0.23013779 | DJ3: 0.0085551331 | DK3: 0.85766423 | DM3: 0.27567568 | DN3: 0.23559539 | DP3: 0.23641026 | DQ3: 0.038647343 | DR3: 0.036734694 | DS3: 0.30072262 | DY3: 0.36440678 | DZ3: 0.17005814 | EA3: 0.6206089 | EB3: 0.033333333 | EC3: -0.12765957 | ED3: 0.13043478 | EE3: 0.49056604 | EF3: -0.012232416 | EG3: 0.10430009 | EK3: -0.32089552 | EL3: 0.38461538 | EM3: 0.035483871 | EN3: 0.10045752 | EO3: 0.33333333
A4: 2020 | B4: 5 | C4: 0.047645592 | D4: -0.00017111862 | E4: 0.060150376 | F4: 0.094594595 | H4: 0.21072797 | J4: 0.099705015 | K4: 0.3415978 | M4: -0.22369408 | P4: 0.12993039 | Q4: 0.084745763 | R4: -0.36628571 | T4: 0.125 | V4: -0.22157996 | X4: -0.18994002 | Y4: -0.091463415 | AB4: -0.017923128 | AE4: 0.070850202 | AH4: -0.060606061 | AI4: -0.073170732 | AK4: 0.031914894 | AL4: 0.066247582 | AM4: 0.19589258 | AN4: -0.0625 | AO4: -0.16414141 | AP4: 0.065060241 | AR4: -0.055495103 | AT4: -0.054054054 | AV4: 0.098591549 | AW4: -0.13354917 | AX4: 0.91371429 | AY4: 0.45054945 | AZ4: 0.098557692 | BA4: 0.069949495 | BB4: -0.11196911 | BC4: 0.85714286 | BE4: -0.21038251 | BF4: -0.11340206 | BG4: 0.57765452 | BJ4: -0.010695187 | BK4: -0.18591549 | BM4: 0.20489978 | BO4: 0.074074074 | BQ4: -0.014809591 | BR4: 0.32105263 | BS4: 0.18166384 | BT4: 0.20285714 | BV4: 0.059210526 | BW4: 0.082267574 | BX4: -0.0016618646 | BZ4: -0.021113244 | CA4: 0.034482759 | CB4: 0.030435224 | CC4: -0.0063077818 | CD4: 0.64981949 | CE4: 0.85542169 | CJ4: 0.017394236 | CK4: -0.076086957 | CL4: 0.13020833 | CN4: -0.065654008 | CO4: -0.14583738 | CQ4: 0.22222222 | CS4: -0.10469314 | CT4: 0.069306931 | CU4: 0.01618123 | CV4: -0.0190965 | CW4: 0.037109855 | CX4: 0.064422378 | CY4: 0.066666667 | CZ4: 0.0058041867 | DA4: 0.24940898 | DC4: 0.031779238 | DD4: -0.04790174 | DF4: 0.2173913 | DI4: 0.14895138 | DJ4: -0.0065975495 | DK4: -0.71971185 | DM4: -0.11758475 | DN4: -0.21865285 | DP4: 0.013542099 | DQ4: -0.11162791 | DR4: 0.90944882 | DS4: 0.030769231 | DY4: -0.13664596 | DZ4: 0.22360248 | EA4: -0.01734104 | EB4: 0.35483871 | EC4: -0.045296167 | ED4: 0.076923077 | EE4: -0.28481013 | EF4: 0.15479876 | EG4: -0.048881524 | EK4: 0.31318681 | EL4: 0.9037037 | EM4: 0.52647975 | EN4: 0.077952343 | EO4: -0.37333333
A5: 2020 | B5: 6 | C5: 0.017760594 | D5: 0 | E5: 0.14893617 | F5: -0.14197531 | H5: 0.012658228 | J5: 0.20493562 | K5: -0.022587269 | M5: 0.04121056 | P5: -0.0020533881 | Q5: -0.0546875 | R5: 0.0081154193 | T5: -0.13131313 | V5: 0 | X5: 0.068849052 | Y5: -0.046979866 | AB5: -0.015406399 | AE5: 0.077504726 | AH5: 0.010752688 | AI5: -0.19548872 | AK5: 0.56701031 | AL5: -0.20634921 | AM5: 0.11096433 | AN5: 0.48888889 | AO5: 0.0060422961 | AP5: 0.42533937 | AR5: 0.30184332 | AT5: -0.058095238 | AV5: -0.0085470085 | AW5: 0.0018682858 | AX5: -0.17497761 | AY5: 0.17424242 | AZ5: 0.15973742 | BA5: 0.21099835 | BB5: 0.18478261 | BC5: 0.43319838 | BE5: -0.017301038 | BF5: -0.11627907 | BG5: -0.081366148 | BJ5: 0.54594595 | BK5: -0.10726644 | BM5: -0.036968577 | BO5: 0.034482759 | BQ5: 0.00071581961 | BR5: 0.1314741 | BS5: 0.22940613 | BT5: -0.71733967 | BV5: 0.0041407867 | BW5: -0.075259806 | BX5: -0.054587914 | BZ5: -0.056862745 | CA5: -0.015666667 | CB5: 0.10121099 | CC5: 0.073422731 | CD5: 0.3785558 | CE5: -0.088744589 | CJ5: -0.034337446 | CK5: 0.35294118 | CL5: 0.067281106 | CN5: -0.05166185 | CO5: 0 | CQ5: 0.18323864 | CS5: -0.010752688 | CT5: 0.72222222 | CU5: 0.12420382 | CV5: 0.0073585706 | CW5: -0.10995261 | CX5: 0.19385666 | CY5: 0.125 | CZ5: -0.14375603 | DA5: -0.22161779 | DC5: 0.0091291706 | DD5: -0.094316634 | DF5: 0.023809524 | DI5: -0.071769342 | DJ5: 0.019924099 | DK5: 0.43925234 | DM5: -0.11644658 | DN5: -0.0039787798 | DP5: -0.013361161 | DQ5: 0.047120419 | DR5: -0.26597938 | DS5: -0.015339967 | DY5: -0.1294964 | DZ5: -0.27817259 | EA5: 0.023529412 | EB5: 0.35714286 | EC5: 1.4014599 | ED5: 0.10714286 | EE5: 0.10619469 | EF5: -0.10455764 | EG5: -0.040940767 | EK5: -0.27615063 | EL5: -0.48249027 | EM5: 0.29931973 | EN5: -0.016858777 | EO5: 0.52659574
A6: 2020 | B6: 7 | C6: 0.05889233 | D6: 0.00010958391 | E6: 0.32716049 | F6: 0.15827338 | H6: 0.23125 | J6: -0.10863758 | K6: -0.090336134 | M6: -0.084415584 | P6: 0.082304527 | Q6: -0.049586777 | R6: -0.060822898 | T6: 0.047209302 | V6: -0.030940594 | X6: -0.13308216 | Y6: -0.021126761 | AB6: 0.0052111106 | AE6: -0.038596491 | AH6: -0.12765957 | AI6: -0.13084112 | AK6: 0.11184211 | AL6: -0.098285714 | AM6: -0.11117717 | AN6: -0.28358209 | AO6: 0 | AP6: -0.29365079 | AR6: 0.14159292 | AT6: 0.1223458 | AV6: -0.15517241 | AW6: 0.1016317 | AX6: -0.26927253 | AY6: 0.19354839 | AZ6: -0.38490566 | BA6: -0.26661469 | BB6: 0.22568807 | BC6: 0.042372881 | BE6: 0.23943662 | BF6: -0.065789474 | BG6: -0.13231274 | BJ6: 0.41258741 | BK6: 0.058139535 | BM6: 0.051823417 | BO6: 0.016666667 | BQ6: -0.03111588 | BR6: -0.063380282 | BS6: -0.2276977 | BT6: -0.12605042 | BV6: 0.34804124 | BW6: -0.018941454 | BX6: 0.03647841 | BZ6: -0.15176715 | CA6: 0.34050119 | CB6: 0.047653107 | CC6: -0.084602135 | CD6: 0.22222222 | CE6: -0.3432304 | CF6: 0.18165785 | CJ6: 0.037629918 | CK6: 0.069565217 | CL6: -0.043177893 | CN6: 0.020952381 | CO6: -0.12194706 | CQ6: -0.058823529 | CS6: -0.12839674 | CT6: -0.31518817 | CU6: 0.039660057 | CV6: -0.1170508 | CW6: -0.0098509052 | CX6: 0.0026681913 | CY6: -0.055555556 | CZ6: 0.18830114 | DA6: 0.010635065 | DC6: -0.040707536 | DD6: 0.18746538 | DF6: -0.23255814 | DI6: -0.18726257 | DJ6: -0.0046511628 | DK6: 0.029220779 | DM6: 0.019021739 | DN6: -0.13715047 | DP6: 0.086291995 | DQ6: -0.1 | DR6: 0.28932584 | DS6: -0.062526316 | DY6: -0.099173554 | DZ6: 0.037974684 | EA6: 0.49137931 | EB6: 1.0175439 | EC6: -0.24468085 | ED6: -0.061290323 | EE6: 0.48 | EF6: -0.15269461 | EG6: -0.40417802 | EK6: -0.069364162 | EL6: 0.07518797 | EM6: 0.72774869 | EN6: 0.10837896 | EO6: 0.44947735
A7: 2020 | B7: 8 | C7: 0.069796715 | D7: 0 | E7: 0.14418605 | F7: -0.14285714 | H7: 0.7715736 | J7: 0.017982018 | K7: -0.050808314 | M7: 0.059101655 | P7: 0.49429658 | Q7: -0.16521739 | R7: -0.17619048 | T7: -0.1005996 | V7: -0.066411239 | X7: 0.027758306 | Y7: -0.23741007 | AB7: 0.06034649 | AE7: -0.057177616 | AH7: 0.048780488 | AI7: 0.15591398 | AK7: -0.37278107 | AL7: 0.20785805 | AM7: -0.15050167 | AN7: -0.18708333 | AO7: -0.033033033 | AP7: 0.049438202 | AR7: -0.27906977 | AT7: -0.027027027 | AV7: -0.11479592 | AW7: 0.22979264 | AX7: 0.15106488 | AY7: -0.31345946 | AZ7: 0.18404908 | BA7: -0.040659049 | BB7: 0.17365269 | BC7: 0.21138211 | BE7: -0.0028409091 | BF7: -0.24633803 | BG7: -0.54190296 | BJ7: -0.18069307 | BK7: -0.029304029 | BM7: 0.25729927 | BO7: 0.96721311 | BQ7: -0.13547434 | BR7: -0.14285714 | BS7: -0.080958386 | BT7: -0.25 | BV7: -0.38819211 | BW7: 0.24147806 | BX7: 0.059470549 | BZ7: -0.0049019608 | CA7: -0.12625153 | CB7: -0.12954429 | CC7: -0.0077861482 | CD7: -0.038961039 | CE7: -0.074141049 | CF7: -0.024626866 | CJ7: 0.062687631 | CK7: -0.26317073 | CL7: -0.12725632 | CN7: -0.0018656716 | CO7: 0.11110679 | CQ7: 0.10969388 | CS7: -0.068589244 | CT7: -0.10696762 | CU7: -0.049046322 | CV7: -0.07480313 | CW7: -0.020435601 | CX7: 0.18836723 | CY7: -0.076470588 | CZ7: -0.017932638 | DA7: 0.10523151 | DB7: 0.079862602 | DC7: -0.0093434772 | DD7: 0.60822338 | DF7: -0.18939394 | DI7: -0.01897168 | DJ7: -0.0046728972 | DK7: -0.0094637224 | DM7: 0.14133333 | DN7: -0.12808642 | DP7: 0.082549016 | DQ7: -0.20555556 | DR7: -0.19716776 | DS7: -0.012351224 | DY7: 0.14678899 | DZ7: -0.090785908 | EA7: -0.51445087 | EB7: -0.79069565 | EC7: -0.18913481 | ED7: -0.20687285 | EE7: -0.21081081 | EF7: -0.021201413 | EG7: 0.40091463 | EK7: -0.049689441 | EL7: 0.6451049 | EM7: -0.25151515 | EN7: 0.055510982 | EO7: 0.75456731
A8: 2020 | B8: 9 | C8: -0.037398487 | D8: -0.00021914381 | E8: 0.044715447 | F8: 0.61594203 | H8: -0.32091691 | J8: -0.079980373 | K8: -0.055961071 | M8: -0.10044643 | P8: -0.38231552 | Q8: 0.033958333 | R8: -0.09017341 | T8: -0.17814815 | V8: -0.31053352 | X8: -0.02809985 | Y8: 0.12264151 | AB8: -0.030706317 | AE8: -0.17903226 | AH8: -0.10465116 | AI8: -0.18139535 | AK8: -0.12301887 | AL8: 0.092339979 | AM8: 0.37047244 | AN8: -0.065094823 | AO8: -0.0031055901 | AP8: 0.29122056 | AR8: 0.11827957 | AT8: -0.075277778 | AV8: -0.014409222 | AW8: -0.038885065 | AX8: -0.12478485 | AY8: 0.08652862 | AZ8: 0.012953368 | BA8: 0.029639889 | BB8: 0.0076530612 | BC8: 0.049217002 | BE8: -0.11111111 | BF8: -0.031769763 | BG8: 0.090784044 | BJ8: -0.060422961 | BK8: -0.25660377 | BM8: -0.18867925 | BO8: -0.13333333 | BQ8: -0.10760034 | BR8: -0.087719298 | BS8: 0.40834248 | BT8: 0.34615385 | BV8: -0.27625 | BW8: 0.061016445 | BX8: -0.029529 | BZ8: -0.034482759 | CA8: -0.22659548 | CB8: -0.065490196 | CC8: -0.0024932063 | CD8: -0.047297297 | CE8: -0.0390625 | CF8: -0.14460597 | CJ8: -0.020157279 | CK8: -0.1945272 | CL8: -0.14219235 | CN8: 0.0028037383 | CO8: -0.39499551 | CQ8: -0.12528736 | CS8: -0.15439331 | CT8: -0.14285714 | CU8: -0.252149 | CV8: -0.18446669 | CW8: -0.00027449904 | CX8: -0.038387716 | CY8: 0.2611465 | CZ8: -0.028841595 | DA8: -0.0024483134 | DB8: -0.099403579 | DC8: -0.12218051 | DD8: 0.25815274 | DF8: 0.11214953 | DI8: 0.054372197 | DJ8: 0.0093896714 | DK8: 2.6656051 | DM8: -0.1296729 | DN8: -0.21946903 | DP8: -0.011515739 | DQ8: 0.31468531 | DR8: 0.13568521 | DS8: -0.052296498 | DY8: 0.136 | DZ8: -0.27719821 | EA8: -0.10714286 | EB8: 0.16327378 | EC8: 0 | ED8: -0.28336222 | EE8: 0.082191781 | EF8: -0.054151625 | EG8: -0.1577802 | EK8: 0.08496732 | EL8: 0.26036132 | EM8: -0.1902834 | EN8: 0.032917484 | EO8: -0.22660638
A9: 2020 | B9: 10 | C9: -0.024933396 | D9: 0.00010959592 | E9: 0.49416342 | F9: -0.21973094 | H9: -0.2278481 | J9: 0.0448 | K9: 0.072164948 | M9: -0.096419709 | P9: -0.0030895984 | Q9: -0.53878702 | R9: -0.11435832 | T9: -0.068649542 | V9: 0 | X9: -0.069333333 | Y9: -0.20142857 | AB9: -0.023227534 | AE9: 0.042043222 | AH9: -0.12337662 | AI9: -0.044545455 | AK9: -0.10251721 | AL9: -0.14361191 | AM9: -0.035909221 | AN9: 0.06441886 | AO9: -0.080996885 | AP9: -0.16252073 | AR9: -0.057211538 | AT9: -0.036647642 | AV9: 0.055555556 | AW9: 0.11027569 | AX9: -0.22271386 | AY9: -0.15217391 | AZ9: -0.22506394 | BA9: -0.1937046 | BB9: -0.07721519 | BC9: -0.18550107 | BE9: 0.057692308 | BF9: -0.27793862 | BG9: 0.24337957 | BJ9: -0.13504823 | BK9: -0.15228426 | BL9: 0.14749263 | BM9: -0.14847943 | BO9: 0.057692308 | BQ9: 0.034449761 | BR9: 0.033653846 | BS9: -0.03858145 | BT9: -0.54857143 | BV9: -0.31295337 | BW9: 0.010589803 | BX9: -0.079056739 | BZ9: -0.10204082 | CA9: -0.32990654 | CB9: -0.13501888 | CC9: -0.11863259 | CD9: -0.14893617 | CE9: -0.06097561 | CF9: -0.04293381 | CJ9: -0.0933098 | CK9: -0.16767123 | CL9: -0.045207957 | CN9: 0.0050046598 | CO9: 1.2313874 | CP9: -0.09894624 | CQ9: 0.24835742 | CS9: 0.0034636319 | CT9: -0.17948718 | CU9: -0.030651341 | CV9: -0.055175651 | CW9: -0.093080725 | CX9: -0.13007319 | CY9: -0.58484848 | CZ9: -0.033242243 | DA9: 0.073356968 | DB9: -0.045474614 | DC9: -0.044435496 | DD9: 1.092481 | DF9: -0.058823529 | DI9: -0.17783094 | DJ9: 0.0093023256 | DK9: -0.28670721 | DM9: 0.15704698 | DN9: -0.0090702948 | DP9: -0.069863698 | DQ9: -0.25 | DR9: -0.11469534 | DS9: -0.11900192 | DY9: 0.20422535 | DZ9: 0.17731959 | EA9: -0.17777778 | EB9: -0.071428571 | EC9: -0.20099256 | ED9: -0.15175333 | EE9: -0.2278481 | EF9: -0.038167939 | EG9: -0.042635659 | EK9: -0.036144578 | EL9: -0.20236088 | EM9: 0.025 | EN9: -0.040040544 | EO9: 0.0097431355
A10: 2020 | B10: 11 | C10: 0.10877691 | D10: -0.00010958391 | E10: -0.13020833 | F10: 0.33908046 | H10: 0.16666667 | J10: -0.093415008 | K10: -0.050480769 | M10: 0.15967046 | P10: 0.45867769 | Q10: 0.34185234 | R10: 0.15734099 | T10: -0.32258065 | U10: 0.37873754 | V10: 0.42460317 | X10: 0.093198613 | Y10: -0.069977902 | AB10: 0.067578819 | AD10: 0.96732523 | AE10: 0.10633484 | AH10: 0.48888889 | AI10: 0.3320647 | AK10: 1.5889968 | AL10: 0.037016265 | AM10: 0.34922527 | AN10: 0.11898017 | AO10: 0.0033898305 | AP10: 0.78217822 | AR10: 0.050484447 | AT10: 0.53830163 | AV10: 0.024930748 | AW10: -0.013544018 | AX10: 0.61353574 | AY10: 0.35897436 | AZ10: 0.2310231 | BA10: -0.055055055 | BB10: 0.089163237 | BC10: -0.18324607 | BE10: 0.063636364 | BF10: 0.45682972 | BG10: 0.15922921 | BJ10: -0.37918216 | BK10: 0.02994012 | BL10: 0.11182519 | BM10: 0.20798319 | BO10: 1.0818182 | BQ10: -0.032839963 | BR10: -0.28372093 | BS10: -0.041751115 | BT10: 0.54388186 | BV10: 0.75917547 | BW10: -0.02352533 | BX10: 0.062618388 | BZ10: -0.059659091 | CA10: 0.16317992 | CB10: 0.023286841 | CC10: 0.12229168 | CD10: 0.33333333 | CE10: -0.3961039 | CF10: 0.16074766 | CJ10: 0.068874952 | CK10: 0.020408163 | CL10: 0.034722222 | CN10: 0.0080028191 | CO10: -0.20666782 | CP10: -0.0049554014 | CQ10: 0.84210526 | CS10: 0.14299803 | CT10: 0.265625 | CU10: 0.68379447 | CV10: 0.15606781 | CW10: 0.076899788 | CX10: 0.1585086 | CY10: 0.54501217 | CZ10: 0.1499524 | DA10: 0.087906504 | DB10: 0.27289547 | DC10: 0.10431831 | DD10: 0.44752416 | DF10: 0.23214286 | DI10: 0.14969285 | DJ10: 0.010138249 | DK10: -0.059683313 | DM10: 0.069605568 | DN10: 0.52173913 | DP10: 0.084509744 | DQ10: 0.14184397 | DR10: -0.090418354 | DS10: 0.16013072 | DY10: -0.12280702 | DZ10: 0.58318739 | EA10: 0.1027027 | EB10: 0.11538462 | EC10: -0.052795031 | ED10: 0.21168924 | EE10: 0.098360656 | EF10: 0.20634921 | EG10: 0.23481781 | EK10: 0.0625 | EL10: -0.078224101 | EM10: 0.46829268 | EN10: 0.011542146 | EO10: 0.77192982
A11: 2020 | B11: 12 | C11: 0.037065957 | D11: 3.5711031e-05 | E11: 0.93712575 | F11: -0.27038627 | H11: 0.14519906 | J11: 0.13231982 | K11: 0.15696203 | M11: -0.01759134 | P11: -0.24220963 | Q11: 0.18834446 | R11: 2.5095041 | T11: -0.14857143 | U11: 0.37550201 | V11: -0.069637883 | W11: 0.25390156 | X11: 0.12387916 | Y11: -0.32337633 | AB11: 0.0019235528 | AD11: 0.1208961 | AE11: 0.03135651 | AH11: 0.36318408 | AI11: -0.20535714 | AK11: -0.37037037 | AL11: 0.083288264 | AM11: 0.15547703 | AN11: 0.026006904 | AO11: -0.0033783784 | AP11: -0.17444444 | AR11: -0.0097087379 | AT11: -0.094594595 | AV11: 0.11891892 | AW11: 0.0026152337 | AX11: -0.13563309 | AY11: -0.06918239 | AZ11: -0.09919571 | BA11: -0.081920904 | BB11: 0.023929471 | BC11: -0.17307692 | BE11: 0.72649573 | BF11: 0.20733945 | BG11: 0.024496938 | BJ11: 0.31137725 | BK11: 0.37790698 | BL11: -0.16416185 | BM11: 0.19304348 | BO11: -0.31877729 | BQ11: 0.18507891 | BR11: 0.053571429 | BS11: 0.34517766 | BT11: 0.35146215 | BV11: 1.3292369 | BW11: 0.17297989 | BX11: 0.087780205 | BZ11: 0.48942598 | CA11: 0.19568345 | CB11: 0.17873652 | CC11: 0.1592175 | CD11: -0.15 | CE11: 0.05734767 | CF11: -0.082125604 | CJ11: 0.02577325 | CK11: 0.12419355 | CL11: 0.037217816 | CN11: 1.2447102 | CO11: 0.40056831 | CP11: 0.16533865 | CQ11: 0.18285714 | CS11: 0.23252804 | CT11: 0.022222222 | CU11: -0.0046948357 | CV11: 0.028056124 | CW11: -0.019679505 | CX11: -0.01237828 | CY11: 0.038582677 | CZ11: -0.039152496 | DA11: -0.2241943 | DB11: -0.1744186 | DC11: -0.072585844 | DD11: -0.12404449 | DF11: -0.13768116 | DI11: -0.098143982 | DJ11: -0.20209854 | DK11: -0.11658031 | DM11: -0.42624729 | DN11: 0.15037594 | DP11: 0.049060875 | DQ11: 0.071428571 | DR11: 0.077151335 | DS11: 0.18122066 | DU11: 0.70997104 | DY11: -0.17333333 | DZ11: -0.086283186 | EA11: -0.024509804 | EB11: 0.6062069 | EC11: -0.20655738 | ED11: -0.35490196 | EE11: -0.097014925 | EF11: 1.8453947 | EG11: 0.2579235 | EK11: -0.070588235 | EL11: 0.12844037 | EM11: -0.019933555 | EN11: 0.031924199 | EO11: -0.30693069
A12: 2021 | B12: 1 | C12: -0.010190496 | D12: 0 | E12: 2.2071097 | F12: 0.26470588 | H12: 0.84253579 | J12: -0.095972153 | K12: 0.052516411 | M12: -0.017217631 | P12: -0.011214953 | Q12: 0.31178082 | R12: -0.11173908 | T12: 0.76314318 | U12: -0.37751825 | V12: 0.092814371 | W12: 0.74724749 | X12: -0.16423223 | Y12: 0.19397993 | AB12: -0.0096722765 | AD12: 0.05616816 | AE12: 0.23595506 | AH12: 0.14233577 | AI12: -0.033707865 | AK12: 0.26470588 | AL12: 0.20519221 | AM12: 0.080275229 | AN12: 0.59376402 | AO12: 0.074576271 | AP12: 0.17765814 | AR12: 0.19607843 | AT12: 0.68656716 | AV12: -0.0048309179 | AW12: -0.053472449 | AX12: -0.40952381 | AY12: 1.5 | AZ12: 1.0119048 | BA12: 0.21115385 | BB12: 0.097170972 | BC12: 0 | BE12: -0.0082508251 | BF12: 0.70212766 | BG12: -0.055508113 | BJ12: -0.059360731 | BK12: -0.10970464 | BL12: -0.00802213 | BM12: 0.31195335 | BO12: 0.019230769 | BQ12: -0.030669895 | BR12: 0.798151 | BS12: 0.011006289 | BT12: 0.42568251 | BV12: 2.4601227 | BW12: -0.057861254 | BX12: 0.036535806 | BZ12: 0.27991886 | CA12: -0.38093328 | CB12: 0.86375063 | CC12: 0.2317583 | CD12: 0.30147059 | CE12: -0.071186441 | CF12: -0.072807018 | CJ12: -0.057824221 | CK12: 0.276901 | CL12: 0.15882353 | CN12: 1.407377 | CO12: 0.2 | CP12: -0.12393162 | CQ12: -0.12318841 | CS12: 0.36226811 | CT12: -0.038647343 | CU12: 0.71226415 | CV12: 0.067973621 | CW12: 0.14711787 | CX12: 0.10427807 | CY12: -0.044730857 | CZ12: -0.014116417 | DA12: 0.1589404 | DB12: 0.08318662 | DC12: -0.045169715 | DD12: 0.102397 | DF12: 0.18487395 | DI12: 0.019020892 | DJ12: -0.071469411 | DK12: 1.9061584 | DM12: 0.19848771 | DN12: -0.023529412 | DP12: -0.11142019 | DQ12: 0.031884058 | DR12: 0.12672176 | DS12: 0.16812401 | DU12: -0.087829664 | DY12: 0.77419355 | DZ12: 1.1912833 | EA12: 0.32663317 | EB12: 0.43838557 | EC12: 0.23140496 | ED12: -0.039513678 | EE12: 0.36363636 | EF12: 0.019653179 | EG12: 0.020851434 | EI12: -0.093385924 | EK12: 0.25316456 | EL12: 0.032520325 | EM12: 0.18644068 | EN12: -0.066542347 | EO12: -0.46160714
A13: 2021 | B13: 2 | C13: 0.02780559 | D13: -0.00010959201 | E13: 0.07373494 | F13: 0.16744186 | H13: -0.061043285 | J13: -0.035753575 | K13: 0.12058212 | M13: 0.019621584 | P13: -0.1342155 | Q13: 0.92147034 | R13: 0.037910923 | T13: 0.35289453 | U13: 0.034709193 | V13: 0.10136986 | W13: 0.032328767 | X13: -0.010721104 | Y13: 0.074229692 | AB13: -0.0016287353 | AD13: -0.34486134 | AE13: -0.018716578 | AH13: 0.057507987 | AI13: 0.52906977 | AK13: -0.087209302 | AL13: -0.022783761 | AM13: -0.11004954 | AN13: 0.24883885 | AO13: 0.072555205 | AP13: 0.71428571 | AR13: 0.66393443 | AT13: -0.17256637 | AV13: 0.077669903 | AW13: 0.13193248 | AX13: -0.033026114 | AY13: -0.075675676 | AZ13: 0.79142012 | BA13: -0.13020006 | BB13: -0.1132287 | BC13: 0.14341085 | BE13: -0.013311148 | BF13: -0.034821429 | BG13: 0.14014467 | BJ13: -0.087378641 | BK13: 0.11374408 | BL13: -0.010875627 | BM13: -0.14777778 | BO13: 0.10691824 | BQ13: -0.048293089 | BR13: -0.090831191 | BS13: 0.10202177 | BT13: 0.16312057 | BV13: -0.25531915 | BW13: 0.080643087 | BX13: -0.022566288 | BZ13: -0.12202853 | CA13: 0.29157667 | CB13: -0.20032371 | CC13: -0.010676379 | CD13: -0.10169492 | CE13: 0.02189781 | CF13: 0.4115421 | CJ13: -0.057739027 | CK13: 0.26966292 | CL13: 0.15177665 | CN13: -0.34439905 | CO13: 0.72222006 | CP13: -0.021463415 | CQ13: 0.01046832 | CS13: 0.024665982 | CT13: -0.025125628 | CU13: 0.22727273 | CV13: 0.040018047 | CW13: 0.04275 | CX13: 0.11228814 | CY13: 0.81269841 | CZ13: -0.067130054 | DA13: 0.14415584 | DB13: 0.34457538 | DC13: -0.054800643 | DD13: -0.24308621 | DE13: -0.0089285714 | DF13: 0.092198582 | DI13: 0.020195838 | DJ13: 0.13423645 | DK13: 1.4510595 | DM13: 0.16403785 | DN13: 0.041499331 | DP13: -0.021666951 | DQ13: 0.0056179775 | DR13: -0.015892421 | DS13: -0.08574345 | DU13: -0.038461538 | DY13: -0.14545455 | DZ13: 0.34585635 | EA13: 0.26136364 | EB13: 0.86567164 | EC13: -0.053691275 | ED13: 0.047468354 | EE13: -0.078787879 | EF13: 0.56689342 | EG13: 0.16680851 | EI13: -0.12595841 | EK13: -0.058080808 | EL13: 0.072834646 | EM13: 0.068571429 | EN13: 0.0064180878 | EO13: 0.5721393
A14: 2021 | B14: 3 | C14: 0.045404985 | D14: -0.00010837252 | E14: 0.13105925 | F14: -0.035856574 | H14: -0.0047281324 | J14: 0.045065602 | K14: 0.24860853 | M14: 0.2419244 | P14: 0.13537118 | Q14: -0.11413043 | R14: -0.15581098 | T14: -0.19988277 | U14: -0.16591115 | V14: 0.12437811 | W14: -0.18059979 | X14: -0.15944181 | Y14: -0.0091264668 | AB14: 0.037340338 | AD14: -0.72360558 | AE14: 0.18310627 | AH14: -0.25377644 | AI14: -0.091254753 | AK14: -0.11464968 | AL14: 0.0046629928 | AM14: -0.054075547 | AN14: -0.053307788 | AO14: -0.10882353 | AP14: -0.334 | AR14: -0.12315271 | AT14: -0.096256684 | AV14: -0.10810811 | AW14: -0.10377358 | AX14: -0.32962669 | AY14: -0.10233918 | AZ14: 0.072667217 | BA14: 0.024096386 | BB14: -0.074589128 | BC14: -0.37966102 | BE14: -0.13827993 | BF14: -0.06012951 | BG14: -0.065820777 | BJ14: -0.021276596 | BK14: -0.16170213 | BL14: -0.068508599 | BM14: -0.11994785 | BO14: 0.017045455 | BQ14: 0.045494313 | BR14: -0.45240339 | BS14: -0.042337003 | BT14: -0.1402439 | BV14: -0.14285714 | BW14: -0.021840038 | BX14: 0.037170256 | BZ14: -0.10108303 | CA14: -0.06187291 | CB14: 0.028538659 | CC14: -0.088193811 | CD14: -0.050314465 | CE14: -0.039285714 | CF14: -0.22319035 | CJ14: 0.070803077 | CK14: -0.19469027 | CL14: -0.11855443 | CN14: -0.080238899 | CO14: -0.27258092 | CP14: 0.041874377 | CQ14: -0.10523446 | CS14: -0.10732197 | CT14: -0.048969072 | CU14: 0.14029181 | CV14: 0.13732889 | CW14: 0.056820906 | CX14: -0.046394558 | CY14: -0.045534151 | CZ14: 0.081814411 | DA14: -0.14733258 | DB14: 0.18857661 | DC14: 0.0085458953 | DD14: -0.03458792 | DE14: 0.12012012 | DF14: -0.13636364 | DI14: 0.056088782 | DJ14: -0.37676439 | DK14: -0.074722108 | DM14: -0.098915989 | DN14: 0.020565553 | DP14: 0.028488316 | DQ14: -0.072625698 | DR14: -0.077018634 | DS14: -0.025679196 | DU14: -0.11089655 | DY14: -0.095744681 | DZ14: -0.066912972 | EA14: -0.033033033 | EB14: -0.20088 | EC14: -0.039007092 | ED14: -0.099697885 | EE14: -0.11842105 | EF14: -0.22033285 | EG14: 0.10503282 | EI14: -0.059254084 | EK14: -0.082439678 | EL14: -0.17247706 | EM14: 0.10695187 | EN14: 0.014429012 | EO14: -0.029535865
A15: 2021 | B15: 4 | C15: 0.052910546 | D15: 0 | E15: -0.053571429 | F15: -0.090909091 | H15: -0.17814727 | J15: -0.050218341 | K15: -0.18127786 | M15: -0.079136691 | P15: -0.21730769 | Q15: -0.19018405 | R15: 0.042965204 | T15: -0.19399267 | U15: 0.069565217 | V15: -0.17035398 | W15: -0.59983806 | X15: 0.067820558 | Y15: -0.12894737 | AB15: -0.011247681 | AD15: -0.14594595 | AE15: -0.40350069 | AH15: 0.24291498 | AI15: -0.16317992 | AK15: -0.15107914 | AL15: -0.05907173 | AM15: -0.042034468 | AN15: -0.083333333 | AO15: -0.11881188 | AP15: -0.13513514 | AR15: 0.23595506 | AT15: -0.10650888 | AV15: -0.04040404 | AW15: 0.076740238 | AX15: -0.12322275 | AY15: -0.2247557 | AZ15: -0.2986913 | BA15: -0.039215686 | BB15: 0.18579235 | BC15: -0.1147541 | BE15: 0.035225049 | BF15: 0.052165354 | BG15: -0.044991511 | BJ15: -0.059782609 | BK15: -0.23350254 | BL15: -0.11319613 | BM15: 0.1362963 | BO15: -0.10614525 | BQ15: -0.041841004 | BR15: -0.12392427 | BS15: 0.014736222 | BT15: -0.12765957 | BV15: -0.16111111 | BW15: 0.00018251506 | BX15: -0.0098573808 | BZ15: -0.15060241 | CA15: -0.098039216 | CB15: -0.043030502 | CC15: -0.021678322 | CD15: -0.066225166 | CE15: 0.055762082 | CF15: -0.13114754 | CJ15: -0.033597081 | CK15: -0.10043956 | CL15: -0.0195 | CN15: 0.092603049 | CO15: -0.20177253 | CP15: 0.070813397 | CQ15: 0.12004875 | CS15: -0.0078651685 | CT15: -0.032520325 | CU15: 0.049212598 | CV15: 0.004917189 | CW15: -0.011796733 | CX15: -0.09858753 | CY15: -0.24954128 | CZ15: 0.06679622 | DA15: 0.025559105 | DB15: -0.1482329 | DC15: 0.028663279 | DD15: -0.2792511 | DE15: -0.13672922 | DF15: -0.28571429 | DI15: 0.095143425 | DJ15: 0.0052264808 | DK15: 0.041156841 | DM15: -0.027067669 | DN15: -0.047858942 | DP15: 0.10306596 | DQ15: -0.060240964 | DR15: 0.043068641 | DS15: 0.1631016 | DU15: -0.04685076 | DW15: 0 | DY15: -0.23529412 | DZ15: -0.19313682 | EA15: -0.33229814 | EB15: -0.27970768 | EC15: -0.15498155 | ED15: -0.15436242 | EE15: -0.097014925 | EF15: -0.17958237 | EG15: -0.12871287 | EH15: -0.15711253 | EI15: -0.047965435 | EK15: -0.27830533 | EL15: -0.15077605 | EM15: -0.070048309 | EN15: 0.10037054 | EO15: 0.057608696
A16: 2021 | B16: 5 | C16: 0.0065660538 | D16: -0.0001096159 | E16: -0.067505241 | F16: 0.12272727 | H16: -0.0043352601 | J16: 0.087356322 | K16: 0.02722323 | M16: 0.032151442 | P16: -0.088452088 | Q16: -0.060606061 | R16: 0.055120395 | T16: -0.17742229 | U16: 0.013211382 | V16: 0.025333333 | W16: -0.17361392 | X16: 0.0041349653 | Y16: -0.2326284 | AB16: 0.052868541 | AD16: -0.16033755 | AE16: 0.049420849 | AH16: -0.16449511 | AI16: -0.075 | AK16: -0.042372881 | AL16: 0.071300448 | AM16: -0.052215884 | AN16: -0.23376623 | AO16: 0.10486891 | AP16: -0.16319444 | AR16: 0.036363636 | AT16: -0.15231788 | AV16: -0.13157895 | AW16: 0.13465784 | AX16: -0.017567568 | AY16: -0.06302521 | AZ16: 0.18770582 | BA16: -0.26122449 | BB16: -0.18663594 | BC16: -0.24074074 | BD16: 0.0080307263 | BE16: -0.096408318 | BF16: -0.080449018 | BG16: -0.20622222 | BJ16: -0.01734104 | BK16: -0.039735099 | BL16: 0.090784983 | BM16: 0.19947849 | BO16: -0.1125 | BP16: -0.26440539 | BQ16: 0.17467249 | BR16: -0.10805501 | BS16: 0.1446413 | BT16: 0.17886179 | BV16: 0.059602649 | BW16: 0.083515815 | BX16: 0.046531127 | BZ16: 0.037825059 | CA16: 0.20158103 | CB16: -0.19322777 | CC16: 0.097614088 | CD16: -0.13475177 | CE16: 0.059859155 | CF16: -0.28699106 | CJ16: 0.018656876 | CK16: -0.13681896 | CL16: -0.078531362 | CN16: -0.43152455 | CO16: 0 | CP16: 0.27077748 | CQ16: -0.2078346 | CS16: -0.1398641 | CT16: -0.10644258 | CU16: 0.080675422 | CV16: 0.14967486 | CW16: 0.14485767 | CX16: -0.039727762 | CY16: -0.24816626 | CZ16: 0.012041959 | DA16: -0.082294912 | DB16: -0.10268657 | DC16: 0.1083359 | DD16: -0.054262074 | DE16: -0.059006211 | DF16: -0.020526316 | DI16: -0.10295643 | DJ16: -0.13344887 | DK16: 0.15213675 | DL16: -0.0040241449 | DM16: -0.1251932 | DN16: 0.26719577 | DP16: -0.016735043 | DQ16: 0.038461538 | DR16: -0.014193548 | DS16: -0.019704433 | DU16: 0.084635417 | DW16: -0.22227273 | DY16: 0.069230769 | DZ16: -0.091057797 | EA16: 0.01627907 | EB16: -0.38012509 | EC16: -0.069868996 | ED16: -0.031746032 | EE16: 0 | EF16: -0.0011312217 | EG16: -0.1469697 | EH16: 0.085642317 | EI16: 0.15410661 | EK16: -0.20040486 | EL16: -0.18537859 | EM16: -0.21298701 | EN16: 0.021094728 | EO16: 0.052415211
A17: 2021 | B17: 6 | C17: 0.022472573 | D17: -0.00021925584 | E17: -0.21043165 | F17: 0.032388664 | H17: 0.13207547 | J17: 0.065539112 | K17: -0.09540636 | M17: 0.020378457 | P17: 0.070080863 | Q17: -0.040322581 | R17: 0.058564751 | T17: -0.13812155 | U17: -0.48645938 | V17: -0.12483745 | W17: 0.051909892 | X17: 0.11118432 | Y17: -0.013779528 | AB17: 0.016736768 | AC17: -0.012755102 | AD17: 0.36432161 | AE17: 0.050036792 | AH17: 0.89863548 | AI17: 0.059459459 | AK17: 0.10619469 | AL17: -0.01046463 | AM17: 0.018518519 | AN17: 0.22576271 | AO17: -0.03559322 | AP17: -0.051175657 | AR17: 0.52631579 | AT17: 0.4765625 | AV17: -0.012121212 | AW17: -0.035853252 | AX17: 0.086657497 | AY17: 0.067264574 | AZ17: 0.16913124 | BA17: 0.062280261 | BB17: -0.12747875 | BC17: 0.11382114 | BD17: -0.26117077 | BE17: 0.037656904 | BF17: -0.085452696 | BG17: 0.17357223 | BJ17: 0.16470588 | BK17: 0.10344828 | BL17: -0.11670839 | BM17: 0.0097826087 | BO17: 0.15492958 | BP17: -0.22 | BQ17: -0.0029739777 | BR17: 0.16299559 | BS17: 0.035777721 | BT17: 0.59310345 | BV17: -0.0125 | BW17: -0.0027508 | BX17: -0.026647486 | BZ17: -0.17084282 | CA17: 0.15131579 | CB17: 0.11461342 | CC17: 0.14909357 | CD17: 0.14754098 | CE17: -0.049833887 | CF17: 0.1183844 | CJ17: 0.08321408 | CK17: -0.04981602 | CL17: -0.050359712 | CN17: -0.47181818 | CO17: -0.30277767 | CP17: -0.34528833 | CQ17: -0.026098901 | CS17: -0.023041475 | CT17: -0.02507837 | CU17: 0.16145833 | CV17: 0.028842023 | CW17: 0.044716262 | CX17: 0.00016482611 | CY17: 0.33170732 | CZ17: 0.011102778 | DA17: -0.042432815 | DB17: -0.031270792 | DC17: -0.0012485501 | DD17: 0.29166949 | DE17: 0.0330033 | DF17: 0.11767867 | DI17: -0.074588031 | DJ17: -0.028 | DK17: 0.58456973 | DL17: 0.002020202 | DM17: 0.0795053 | DN17: -0.23173278 | DP17: -0.10921229 | DQ17: -0.0061728395 | DR17: -0.039267016 | DS17: 0.031490787 | DU17: -0.1302521 | DW17: -0.28345996 | DY17: -0.0071942446 | DZ17: 0.084583083 | EA17: 0.4416476 | EB17: 0.035874439 | EC17: 0.056338028 | ED17: 0.06557377 | EE17: -0.016528926 | EF17: -0.086070215 | EG17: 0.0035523979 | EH17: 0.055684455 | EI17: -0.062340635 | EK17: -0.11139241 | EL17: 0.30448718 | EM17: -0.04290429 | EN17: 0.054788646 | EO17: 0.25195312
A18: 2021 | B18: 7 | C18: 0.024412456 | D18: -0.00010841992 | E18: -0.14977221 | F18: -0.043137255 | H18: -0.065384615 | J18: 0.039186508 | K18: -0.037109375 | L18: 0.064281525 | M18: -0.031954351 | P18: -0.1813602 | Q18: -0.16 | R18: 0.31298701 | T18: -0.19230769 | U18: -0.061523438 | V18: 0.15453195 | W18: 0.16573557 | X18: -0.27972132 | Y18: -0.20758483 | AB18: 0.023192278 | AC18: -0.0015503876 | AD18: -0.23388582 | AE18: -0.1611773 | AH18: 0.01026694 | AI18: -0.12244898 | AK18: -0.072 | AL18: 0.052876481 | AM18: -0.055909091 | AN18: 0.12002212 | AO18: 0.14235501 | AP18: -0.15306122 | AR18: -0.45689655 | AT18: -0.18518519 | AV18: -0.13496933 | AW18: 0.051311617 | AX18: -0.31772152 | AY18: -0.19747899 | AZ18: -0.14466403 | BA18: -0.27234043 | BB18: -0.16558442 | BC18: -0.18248175 | BD18: -0.17909048 | BE18: -0.14717742 | BF18: -0.085650723 | BG18: -0.30248092 | BJ18: -0.22222222 | BK18: -0.19375 | BL18: -0.073326249 | BM18: -0.039827772 | BO18: 0.079268293 | BP18: -0.29415954 | BQ18: 0.057419836 | BR18: -0.20454545 | BS18: -0.15899069 | BT18: -0.66281385 | BV18: -0.11392405 | BW18: -0.045710426 | BX18: 0.045283478 | BZ18: -0.30769231 | CA18: -0.11 | CB18: -0.13476637 | CC18: 0.060909706 | CD18: -0.057142857 | CE18: -0.1958042 | CF18: -0.19800747 | CJ18: -0.011571932 | CK18: 0.021000894 | CL18: -0.07983683 | CN18: 0.30636833 | CO18: -0.28286864 | CP18: -0.071965628 | CQ18: -0.2235543 | CR18: -0.041307607 | CS18: -0.022911051 | CT18: -0.08681672 | CU18: 0.060538117 | CV18: -0.1803986 | CW18: 0.0086372361 | CX18: -0.028510218 | CY18: -0.26984127 | CZ18: 0.10317225 | DA18: -0.051698671 | DB18: -0.30631868 | DC18: 0.047546133 | DD18: 0.15485587 | DE18: -0.028753994 | DF18: -0.18769231 | DI18: -0.18775383 | DJ18: -0.27983539 | DK18: -0.18621255 | DL18: 0.0040322581 | DM18: -0.10310966 | DN18: -0.05298913 | DP18: 0.014325026 | DQ18: -0.055900621 | DR18: -0.085831063 | DS18: -0.14485222 | DU18: -0.22118703 | DW18: -0.38825449 | DY18: -0.14492754 | DZ18: -0.19192478 | EA18: -0.21428571 | EB18: -0.28282828 | EC18: -0.15555556 | ED18: -0.13846154 | EE18: -0.15966387 | EF18: -0.14869888 | EG18: -0.053097345 | EH18: -0.021978022 | EI18: -0.015390664 | EK18: -0.23076923 | EL18: -0.24570025 | EM18: -0.11034483 | EN18: 0.089038581 | EO18: -0.21294852
A19: 2021 | B19: 8 | C19: 0.029760085 | D19: -0.00010966385 | E19: 0.085733423 | F19: 0.68032787 | H19: -0.1042524 | J19: -0.061575179 | K19: 0.14401623 | L19: -0.070042985 | M19: -0.1061008 | P19: 0.40923077 | Q19: -0.088735494 | R19: -0.14727992 | T19: -0.15079365 | U19: 0.10197711 | V19: 0.066924067 | W19: 0.18690096 | X19: -0.47149619 | Y19: -0.042821159 | AB19: -0.01488195 | AC19: 0 | AD19: 0.052884615 | AE19: 0.31829574 | AH19: 0.4004065 | AI19: -0.011627907 | AK19: 0.0086206897 | AL19: -0.17517075 | AM19: 0.024554646 | AN19: -0.15333333 | AO19: -0.11384615 | AP19: 0.11187608 | AR19: 0.19047619 | AT19: 0.13636364 | AV19: -0.014184397 | AW19: -0.084727173 | AX19: -0.11131725 | AY19: 0.041884817 | AZ19: -0.020332717 | BA19: -0.1539961 | BB19: 0.025291829 | BC19: 0.044642857 | BD19: -0.095374072 | BE19: 0.30023641 | BF19: 0.33090024 | BG19: 3.0629275 | BH19: 0.11015228 | BJ19: 0.045454545 | BK19: 0.054263566 | BL19: 0.2954893 | BM19: 0.18834081 | BO19: -0.079096045 | BP19: 0.29868819 | BQ19: 0.076163611 | BR19: 0.05952381 | BS19: -0.032915817 | BT19: -0.13981256 | BV19: -0.14285714 | BW19: -0.22304153 | BX19: 0.011401303 | BZ19: -0.26984127 | CA19: -0.0016051364 | CB19: 0.16553608 | CC19: 0.064161706 | CD19: -0.0075757576 | CE19: 0.16086957 | CF19: 0.10869565 | CJ19: -0.0075448073 | CK19: -0.017943107 | CL19: -0.019632679 | CN19: 0.034255599 | CO19: 0.11110679 | CP19: 0.068287037 | CQ19: -0.040871935 | CR19: 0.17806495 | CS19: 0.12413793 | CT19: 0.024647887 | CU19: 0.38689218 | CV19: 0.031260319 | CW19: 0.092102759 | CX19: 0.0057675997 | CY19: 0.090301003 | CZ19: 0.076148526 | DA19: 0.10872274 | DB19: -0.097029703 | DC19: -0.14740836 | DD19: -0.25140562 | DE19: -0.25986842 | DF19: -0.029474432 | DI19: -0.080384615 | DJ19: 0.25714286 | DK19: -0.18236732 | DL19: 0.0020080321 | DM19: 0.14416058 | DN19: -0.06456241 | DP19: 0.025109191 | DQ19: 0.13815789 | DR19: -0.05514158 | DS19: 0.045575389 | DU19: 0.17412494 | DW19: 0.79466667 | DY19: -0.050847458 | DZ19: -0.062970568 | EA19: 0.31313131 | EB19: 0.072434608 | EC19: -0.12631579 | ED19: 0 | EE19: -0.205 | EF19: 0.29839884 | EG19: 0.046728972 | EH19: 3.2921348 | EI19: 0.047542593 | EK19: -0.37037037 | EL19: -0.1009772 | EM19: -0.16666667 | EN19: 0.0091758657 | EO19: -0.078295342
A20: 2021 | B20: 9 | C20: -0.046575397 | D20: 0.00010967588 | E20: 0.11042566 | F20: 0.046341463 | H20: 0.047473201 | J20: -0.033062055 | K20: -0.053191489 | L20: -0.02962963 | M20: 0.082096934 | P20: -0.048034934 | Q20: -0.13217697 | R20: -0.046746317 | T20: -0.15327103 | U20: -0.11425873 | V20: 0.18214717 | W20: 0.17967699 | X20: 0.2834891 | Y20: -0.24210526 | AB20: -0.1076866 | AC20: 0.0077639752 | AD20: -0.24200913 | AE20: -0.020912548 | AH20: -0.12917271 | AI20: -0.12352941 | AK20: -0.1025641 | AL20: -0.038480273 | AM20: -0.07518797 | AN20: -0.18562263 | AO20: -0.069444444 | AP20: -0.28018576 | AR20: -0.097777778 | AT20: -0.045714286 | AV20: -0.079136691 | AW20: -0.044637507 | AX20: -0.14822547 | AY20: 0.040201005 | AZ20: -0.28113208 | BA20: -0.074500768 | BB20: -0.043643264 | BC20: 0.11111111 | BD20: 0.047979798 | BE20: -0.10909091 | BF20: -0.047531993 | BG20: -0.05016835 | BH20: 0.0086877 | BJ20: -0.049689441 | BK20: -0.125 | BL20: 0.1310121 | BM20: -0.14245283 | BO20: -0.09202454 | BP20: -0.019425019 | BQ20: 0.095019659 | BR20: 0.15730337 | BS20: 0.12289157 | BT20: -0.16656716 | BV20: -0.36944444 | BW20: -0.011388657 | BX20: -0.067175151 | BZ20: 0.22282609 | CA20: 0.0064308682 | CB20: 0.053061224 | CC20: -0.10546298 | CD20: -0.16793893 | CE20: 0.033707865 | CF20: 0.27787115 | CJ20: -0.0065928456 | CK20: -0.04560309 | CL20: 0.16020672 | CN20: -0.40955414 | CO20: -0.12499563 | CP20: 0.076923077 | CQ20: -0.053030303 | CR20: -0.032458061 | CS20: -0.15398773 | CT20: 0.030927835 | CU20: 0.11686992 | CV20: -0.11321419 | CW20: -0.022303537 | CX20: -0.055489965 | CY20: 0.31441718 | CZ20: -0.066419808 | DA20: -0.098061253 | DB20: -0.074561404 | DC20: 0.16250024 | DD20: -0.029840473 | DE20: -0.11111111 | DF20: -0.024393219 | DG20: -0.03362256 | DI20: 0.096194061 | DJ20: -0.075 | DK20: 0.091996482 | DL20: 0.002004008 | DM20: 0.060606061 | DN20: -0.18711656 | DP20: 0.13170539 | DQ20: -0.12716763 | DR20: -0.11987382 | DS20: -0.031238649 | DU20: -0.18679245 | DW20: -0.22585438 | DY20: -0.089285714 | DZ20: -0.17531045 | EA20: 0.10769231 | EB20: -0.28142589 | EC20: -0.15662651 | ED20: -0.16517857 | EE20: -0.067421384 | EF20: -0.043721973 | EG20: 0.11607143 | EH20: -0.7486911 | EI20: -0.07381495 | EK20: -0.18235294 | EL20: -0.11231884 | EM20: -0.03255814 | EN20: -0.0509387 | EO20: 0.0032258065
A21: 2021 | B21: 10 | C21: 0.070163514 | D21: -0.00010966385 | E21: -0.036111111 | F21: -0.25174825 | H21: -0.10380117 | J21: -0.017359285 | K21: 0.028089888 | L21: 0.015267176 | M21: 0.13893967 | P21: 0.17889908 | Q21: -0.094750158 | R21: 0.053541008 | T21: 0.13686534 | U21: 0.39339019 | V21: -0.0091836735 | W21: -0.66799772 | X21: 0.16808252 | Y21: -0.13541667 | AB21: -0.01301459 | AC21: 0.001540832 | AD21: -0.084337349 | AE21: 0.089320388 | AH21: -0.09 | AI21: -0.073825503 | AK21: -0.15028571 | AL21: -0.0055724417 | AM21: -0.085365854 | AN21: 0.15971352 | AO21: 0.0037313433 | AP21: 0.04516129 | AR21: -0.078817734 | AT21: -0.1257485 | AV21: 0 | AW21: 0.031044214 | AX21: -0.11764706 | AY21: -0.14975845 | AZ21: 0.026246719 | BA21: -0.25809129 | BB21: 0.14285714 | BC21: -0.053846154 | BD21: -0.0060240964 | BE21: -0.22040816 | BF21: 0.10076775 | BG21: -0.21517192 | BH21: 0.14732548 | BJ21: -0.065359477 | BK21: -0.10084034 | BL21: 0.081920167 | BM21: 0.110011 | BO21: -0.054054054 | BP21: -0.1481775 | BQ21: 0.044284859 | BR21: -0.23495146 | BS21: 0.15531116 | BT21: -0.043696275 | BV21: -0.061674009 | BW21: 0.021734122 | BX21: 0.0085451929 | BZ21: -0.15555556 | CA21: -0.011182109 | CB21: 0.047516509 | CC21: 0.10261835 | CD21: -0.04587156 | CE21: 0.35869565 | CF21: -0.19991232 | CJ21: 0.17227987 | CK21: -0.17509728 | CL21: -0.155902 | CN21: 0.092772384 | CO21: -0.28457018 | CP21: -0.077464789 | CQ21: -0.336 | CR21: 0.12076675 | CS21: -0.5453227 | CT21: -0.11666667 | CU21: 0.065059145 | CV21: 0.018569144 | CW21: 0.069149884 | CX21: -0.066428571 | CY21: -0.19253209 | CZ21: 0.016971607 | DA21: -0.26697819 | DB21: -0.056279621 | DC21: -0.046059912 | DD21: 0.1326948 | DE21: -0.13 | DF21: 0.087635954 | DG21: 0.29068462 | DI21: -0.10454025 | DJ21: -0.14004914 | DK21: -0.30525129 | DL21: 0.00205 | DM21: -0.11578947 | DN21: -0.054716981 | DP21: -0.024346961 | DQ21: -0.026490066 | DR21: 0.039426523 | DS21: 0.1192351 | DU21: 0.28816705 | DW21: -0.088291747 | DY21: -0.1372549 | DZ21: -0.08768822 | EA21: 0.33055556 | EB21: -0.096605744 | EC21: -0.16071429 | ED21: -0.080213904 | EE21: -0.018073914 | EF21: -0.042203986 | EG21: 0.0072 | EH21: -0.12916667 | EI21: -0.014764894 | EK21: -0.035971223 | EL21: -0.24081633 | EM21: -0.14903846 | EN21: 0.11493885 | EO21: 0.018220793
A22: 2021 | B22: 11 | C22: -0.0080348836 | D22: -0.00021935175 | E22: -0.26224784 | F22: -0.13395639 | H22: -0.20391517 | J22: 0.047109208 | K22: -0.23861566 | L22: -0.097744361 | M22: 0.10058855 | P22: 0.14785992 | Q22: -0.1196199 | R22: -0.12670363 | T22: 0.37864078 | U22: 0.031369549 | V22: -0.077239959 | W22: -0.30498282 | X22: -0.10285714 | Y22: -0.21285141 | AB22: -0.081678343 | AC22: -0.0020512821 | AD22: -0.15789474 | AE22: -0.21687463 | AH22: -0.32783883 | AI22: -0.1884058 | AK22: 0.0060524546 | AL22: -0.10443199 | AM22: 0.16666667 | AN22: -0.042766713 | AO22: 0.86988848 | AP22: 0.024691358 | AR22: -0.096256684 | AT22: 0.23287671 | AV22: -0.22671875 | AW22: -0.12591241 | AX22: -0.061111111 | AY22: -0.26136364 | AZ22: -0.2915601 | BA22: -0.023489933 | BB22: -0.32291667 | BC22: -0.38219512 | BD22: 0.055757576 | BE22: -0.044502618 | BF22: 0.37750654 | BG22: -0.34507678 | BH22: 0.045831687 | BJ22: -0.13286713 | BK22: -0.23457944 | BL22: -0.17795997 | BM22: -0.0089197225 | BO22: -0.064285714 | BP22: 0.33069767 | BQ22: -0.041833811 | BR22: -0.0076142132 | BS22: -0.060134664 | BT22: -0.080524345 | BV22: -0.38497653 | BW22: -0.098992784 | BX22: -0.036315457 | BZ22: -0.20526316 | CA22: -0.14378029 | CB22: 0.10949705 | CC22: -0.023190258 | CD22: 0.057692308 | CE22: 0.10666667 | CF22: -0.23287671 | CJ22: -0.14923269 | CK22: -0.056603774 | CL22: -0.25725594 | CN22: -0.34057256 | CO22: 0.025555059 | CP22: -0.021810251 | CQ22: 0.030120482 | CR22: -0.19749769 | CS22: 0.14832536 | CT22: -0.4 | CU22: -0.17898334 | CV22: -0.1021978 | CW22: -0.067344557 | CX22: 0.006503443 | CY22: -0.21098266 | CZ22: 0.23932097 | DA22: -0.23756906 | DB22: -0.10985562 | DC22: -0.18693411 | DD22: 0.066211013 | DE22: 0.64367816 | DF22: -0.23333333 | DG22: 0.28869565 | DI22: -0.23902855 | DJ22: 0.037142857 | DK22: 0.24020403 | DL22: 0.0030437603 | DM22: -0.26190476 | DN22: 0.47305389 | DP22: 0.13175923 | DQ22: -0.15646259 | DR22: -0.086206897 | DS22: 0.0040201005 | DU22: -0.041786744 | DW22: -0.20526316 | DY22: -0.25931818 | DZ22: -0.017475728 | EA22: -0.20041754 | EB22: -0.13294798 | EC22: -0.15353191 | ED22: -0.16284884 | EE22: -0.32005495 | EF22: -0.082007344 | EG22: -0.17791898 | EH22: 0.11961722 | EI22: -0.0701704 | EK22: -0.23134328 | EL22: 0.12365591 | EM22: -0.050847458 | EN22: 0.027011941 | EO22: -0.17578947
A23: 2021 | B23: 12 | C23: 0.046288422 | D23: 0 | E23: 0.1359375 | F23: -0.028776978 | H23: -0.16188525 | J23: 0.1906953 | K23: 0.14593301 | L23: 0.025 | M23: 0.12007778 | P23: -0.34067797 | Q23: -0.17619048 | R23: 0.086364238 | T23: 0.53521127 | U23: -0.033382789 | V23: -0.098214286 | W23: 0.10506799 | X23: 0.093804285 | Y23: -0.31122449 | Z23: 0.25542571 | AB23: 0.16259676 | AC23: 0.0071942446 | AD23: -0.28515625 | AE23: -0.075872534 | AF23: -0.2718894 | AH23: -0.2506812 | AI23: -0.37285714 | AJ23: -0.61337209 | AK23: -0.2758467 | AL23: 0.062571104 | AM23: -0.057142857 | AN23: -0.2216129 | AO23: -0.071570577 | AP23: -0.086345382 | AR23: -0.088757396 | AT23: 0.11111111 | AV23: -0.0039401899 | AW23: -0.012526096 | AX23: -0.33431953 | AY23: -0.28461538 | AZ23: 0.17509025 | BA23: -0.42726231 | BB23: 0.1 | BC23: -0.27622056 | BD23: -0.1228473 | BE23: 0.095890411 | BF23: -0.22531646 | BG23: 0.22 | BH23: -0.11862486 | BJ23: -0.080645161 | BK23: -0.19426129 | BL23: 0.25080669 | BM23: -0.136 | BO23: -0.25458015 | BP23: -0.12338343 | BQ23: 0.031698565 | BR23: -0.046035806 | BS23: 0.29298419 | BT23: -0.20203666 | BV23: -0.20610687 | BW23: 0.062818053 | BX23: 0.097095018 | BZ23: 0 | CA23: -0.23962264 | CB23: -0.046072134 | CC23: 0.11361057 | CD23: -0.099 | CE23: 0.17349398 | CF23: -0.22142857 | CJ23: 0.032668938 | CK23: -0.2468 | CL23: 0.19982238 | CN23: -0.28443114 | CO23: 0.57008718 | CP23: -0.052396878 | CQ23: 0.019005848 | CR23: 0.041735485 | CS23: -0.10694444 | CT23: 0.018867925 | CU23: -0.25702393 | CV23: 0.042371495 | CW23: 0.084003575 | CX23: 0.14348157 | CY23: -0.1025641 | CZ23: 0.099013206 | DA23: 0.096432553 | DB23: -0.047954866 | DC23: 0.066754848 | DD23: 0.14171922 | DE23: 0.16433566 | DF23: -0.34392804 | DG23: -0.44838057 | DI23: 0.26147816 | DJ23: -0.20385675 | DK23: -0.18302486 | DL23: -0.0010944185 | DM23: 0.15668203 | DN23: -0.17344173 | DP23: -0.078434318 | DQ23: -0.21064516 | DR23: -0.13962264 | DS23: -0.027027027 | DU23: -0.15413534 | DW23: -0.063576159 | DY23: -0.14053391 | DZ23: -0.30533597 | EA23: -0.20887728 | EB23: -0.15 | EC23: -0.21355319 | ED23: -0.29161747 | EE23: -0.28181818 | EF23: -0.21466667 | EG23: -0.11497585 | EH23: -0.26709402 | EI23: 0.099108037 | EJ23: 0.010687023 | EK23: -0.0097087379 | EL23: 0.40191388 | EM23: -0.35714286 | EN23: 0.099035884 | EO23: 0.11238825
A24: 2022 | B24: 1 | C24: -0.05274139 | D24: 0 | E24: -0.24896836 | F24: -0.22962963 | H24: -0.25672372 | J24: -0.0085873766 | K24: -0.075156576 | L24: 0.074796748 | M24: -0.12282986 | P24: -0.30077121 | Q24: -0.19075145 | R24: -0.12965668 | T24: 0.18807339 | U24: -0.2095165 | V24: -0.2549505 | W24: -0.20134228 | X24: -0.27368978 | Y24: -0.02962963 | Z24: -0.54920213 | AB24: 0.049877965 | AC24: 0.0040816327 | AD24: -0.26229508 | AE24: -0.049261084 | AF24: -0.30379747 | AH24: -0.29090909 | AI24: -0.14436219 | AJ24: -0.23308271 | AK24: -0.13076923 | AL24: -0.044432548 | AM24: -0.052020202 | AN24: -0.15043514 | AO24: -0.28051392 | AP24: -0.07032967 | AR24: -0.019480519 | AT24: -0.215 | AU24: -0.0074349442 | AV24: -0.23227508 | AW24: -0.082452431 | AX24: -0.38222222 | AY24: -0.31580645 | AZ24: 0.13978495 | BA24: -0.142 | BB24: -0.13752914 | BC24: -0.0087272727 | BD24: -0.10994764 | BE24: -0.23 | BF24: -0.23447712 | BG24: -0.31260599 | BH24: -0.27218174 | BJ24: -0.14026316 | BK24: -0.14108198 | BL24: -0.15900563 | BM24: -0.13194444 | BO24: -0.018945212 | BP24: -0.22408293 | BQ24: -0.070724638 | BR24: -0.15013405 | BS24: -0.092663355 | BT24: -0.12557427 | BV24: -0.21769231 | BW24: 0.090345369 | BX24: 0.0071315922 | BZ24: -0.49006623 | CA24: -0.0074441687 | CB24: -0.19312443 | CC24: -0.11161384 | CD24: 0.02915952 | CE24: 0.16221766 | CF24: -0.061926606 | CJ24: 0.063153306 | CK24: -0.2031333 | CL24: -0.176906 | CN24: -0.37866109 | CO24: -0.56646115 | CP24: -0.28235294 | CQ24: -0.18794835 | CR24: 0.047947699 | CS24: -0.066874028 | CT24: 0.41975309 | CU24: -0.37254902 | CV24: -0.054848188 | CW24: -0.069249794 | CX24: 0.043210902 | CY24: -0.24489796 | CZ24: -0.10101622 | DA24: -0.14590747 | DB24: -0.13111111 | DC24: -0.021334673 | DD24: 0.0090651815 | DE24: -0.48048048 | DF24: -0.097577697 | DG24: 0.26788991 | DI24: -0.18375499 | DJ24: -0.41522491 | DK24: 0.012585812 | DL24: 0.0049800797 | DM24: -0.14143426 | DN24: -0.19672131 | DP24: -0.13431449 | DQ24: -0.029423784 | DR24: -0.16885965 | DS24: 0.057956104 | DU24: -0.108 | DW24: -0.11315417 | DY24: -0.14209211 | DZ24: -0.15220484 | EA24: -0.27722772 | EB24: -0.23529412 | EC24: -0.18473536 | ED24: 0.025588235 | EE24: -0.14627286 | EF24: -0.11714771 | EG24: -0.1058952 | EH24: -0.37900875 | EI24: 0.10642755 | EJ24: -0.18126888 | EK24: -0.39088235 | EL24: -0.27986348 | EM24: -0.037037037 | EN24: -0.17996244 | EO24: -0.17221584
A25: 2022 | B25: 2 | C25: -0.029516989 | D25: -0.0002181673 | E25: 0.36446886 | F25: -0.0096153846 | H25: -0.17927632 | J25: 0.20008662 | K25: 0.022573363 | L25: 0.10287443 | M25: -0.073478476 | P25: 0.025735294 | Q25: -0.054047619 | R25: -0.093439642 | T25: -0.11196911 | U25: -0.11067961 | V25: 0.33887043 | W25: -0.11204482 | X25: 0.02441691 | Y25: -0.038167939 | Z25: -0.12979351 | AB25: 0.058253806 | AC25: 0 | AD25: -0.014814815 | AE25: -0.1044905 | AF25: -0.30227273 | AG25: -0.22702703 | AH25: -0.18205128 | AI25: -0.35108153 | AJ25: -0.078431373 | AK25: -0.044247788 | AL25: 0.090756303 | AM25: 0.1875333 | AN25: 0.068292683 | AO25: -0.06547619 | AP25: 0.1536643 | AR25: 0.01986755 | AT25: -0.050955414 | AU25: -0.04494382 | AV25: -0.12379442 | AW25: 0.091013825 | AX25: 0.09352518 | AY25: -0.56859972 | AZ25: 0.23315364 | BA25: -0.046620047 | BB25: 0.016216216 | BC25: 0.16929567 | BD25: -0.13308824 | BE25: -0.090909091 | BF25: 0.06189968 | BG25: -0.095394737 | BH25: -0.028268551 | BJ25: 0.12233446 | BK25: 0.0056457304 | BL25: 0.11433352 | BM25: 0.028 | BO25: 0.10647182 | BP25: -0.37204522 | BQ25: 0.19837804 | BR25: 0.078864353 | BS25: 0.16824595 | BT25: 0.16462347 | BV25: -0.44014258 | BW25: -0.01072637 | BX25: -0.038610046 | BZ25: -0.18831169 | CA25: -0.1125 | CB25: -0.18783599 | CC25: 0.022836026 | CD25: 0.20588235 | CE25: 0.14310954 | CF25: 0.19070905 | CJ25: -0.060138268 | CK25: 0.052649117 | CL25: -0.079136691 | CN25: 0.0067340067 | CO25: -0.10984818 | CP25: -0.1704918 | CQ25: -0.014134276 | CR25: 0.17857396 | CS25: 0.2 | CT25: 0.27391304 | CU25: 0.14955357 | CV25: 0.10362694 | CW25: 0.054561559 | CX25: 0.062450215 | CY25: 0.035135135 | CZ25: -0.10912924 | DA25: 0.079166667 | DB25: -0.23529412 | DC25: -0.06018471 | DD25: -0.085008099 | DE25: -0.20231214 | DF25: -0.21828311 | DG25: -0.19488664 | DI25: 0.11528004 | DJ25: 0.14201183 | DK25: -0.039322034 | DL25: 0.0039643211 | DM25: 0.21809745 | DN25: -0.14693878 | DP25: -0.078339452 | DQ25: -0.19473684 | DR25: -0.16094987 | DS25: 0.035656402 | DU25: -0.12157449 | DW25: -0.47049442 | DY25: -0.060549313 | DZ25: 0.023489933 | EA25: -0.089041096 | EB25: -0.16923077 | EC25: 0.0036067116 | ED25: -0.024949814 | EE25: -0.21186161 | EF25: 0.075 | EG25: 0.023199023 | EH25: 0.018779343 | EI25: -0.2583622 | EJ25: -0.28105781 | EK25: -0.12747465 | EL25: 0.12796209 | EM25: -0.17307692 | EN25: -0.03073212 | EO25: -0.17753121
A26: 2022 | B26: 3 | C26: 0.037555701 | D26: 0.00045368974 | E26: 0.15704698 | F26: -0.024271845 | H26: 0.3987976 | I26: -0.60942249 | J26: 0.29556117 | K26: -0.079470199 | L26: -0.028806584 | M26: -0.2493992 | P26: -0.064516129 | Q26: 0.13264536 | R26: 0.038419997 | T26: 0.24782609 | U26: 0.47379913 | V26: -0.15260546 | W26: 0.13880126 | X26: 0.47242974 | Y26: -0.14285714 | Z26: 0.12881356 | AB26: 0.071354324 | AC26: 0.0040650407 | AD26: -0.07518797 | AE26: 0.17164899 | AF26: -0.10423453 | AG26: 0.37762238 | AH26: 0.43573668 | AI26: -0.12564103 | AJ26: 0.15425532 | AK26: 0.018518519 | AL26: 0.045711351 | AM26: 0.010318528 | AN26: -0.10958904 | AO26: -0.10191083 | AP26: 0.12295082 | AR26: 0.16233766 | AT26: 0 | AU26: -0.052941176 | AV26: 0.010102533 | AW26: -0.081661387 | AX26: 0.23684211 | AY26: 0.20218579 | AZ26: 0.22622951 | BA26: 0.13447433 | BB26: 0.15957447 | BC26: -0.22352941 | BD26: -0.17726887 | BE26: 0.089285714 | BF26: 0.22110553 | BG26: 1.15 | BH26: 0.10848485 | BJ26: 0.17272727 | BK26: 0.21403509 | BL26: 0.21746747 | BM26: -0.1154345 | BO26: -0.10481132 | BP26: -0.0016366612 | BQ26: 0.0072878709 | BR26: -0.052631579 | BS26: 0.10291997 | BT26: -0.11027569 | BV26: 0.55543359 | BW26: 0.13280454 | BX26: 0.076927621 | BZ26: -0.00416 | CA26: -0.070422535 | CB26: 0.11134163 | CC26: 0.14570879 | CD26: 0.11382114 | CE26: 0.10973725 | CF26: -0.17453799 | CJ26: 0.080933548 | CK26: -0.062044951 | CL26: -0.47363281 | CN26: -0.18060201 | CO26: 0.082249266 | CP26: 0.039525692 | CQ26: -0.11290323 | CR26: -0.064292416 | CS26: -0.16527778 | CT26: -0.15699659 | CU26: -0.16019417 | CV26: -0.057982518 | CW26: -0.11070049 | CX26: 0.14439946 | CY26: -0.21409922 | CZ26: 0.10289653 | DA26: -0.24931054 | DB26: -0.21850613 | DC26: 0.08192644 | DD26: 0.10759245 | DE26: 0.13043478 | DF26: 0.10625202 | DG26: -0.19113241 | DI26: 0.31594344 | DJ26: 0.2746114 | DK26: -0.12632322 | DL26: 0.0049358342 | DM26: 0.081904762 | DN26: -0.064593301 | DP26: 0.18166033 | DQ26: -0.045751634 | DR26: 0.26100629 | DS26: 0.011580595 | DU26: -0.045944413 | DW26: -0.10542169 | DY26: -0.36766334 | DZ26: 0.27377049 | EA26: 0.1679198 | EB26: 0.13580247 | EC26: 2.4375 | ED26: -0.062254902 | EE26: 0.58862876 | EF26: -0.13595707 | EG26: -0.03221957 | EH26: 0.023041475 | EI26: -0.011809757 | EJ26: 0.16082121 | EK26: 0.19922524 | EL26: 0.075630252 | EM26: 0.20930233 | EN26: -0.026129777 | EO26: -0.15177066
A27: 2022 | B27: 4 | C27: -0.087769141 | D27: -0.00010844183 | E27: -0.28538283 | F27: -0.29850746 | H27: -0.29226361 | I27: -0.29961089 | J27: -0.011977716 | K27: -0.074340528 | L27: -0.4759887 | M27: 0.04980434 | P27: -0.46360153 | Q27: -0.152 | R27: -0.18320951 | T27: -0.26480836 | U27: -0.23777778 | V27: -0.26793558 | W27: -0.18698061 | X27: -0.2329065 | Y27: -0.40287037 | Z27: 0.11111111 | AB27: 0.030672972 | AC27: 0.004048583 | AD27: -0.1300813 | AE27: -0.28230453 | AF27: 0.0072727273 | AG27: -0.17766497 | AH27: -0.33187773 | AI27: -0.0082111437 | AJ27: -0.33179724 | AK27: -0.14545455 | AL27: -0.20923379 | AM27: -0.044849023 | AN27: -0.28461538 | AO27: -0.16666667 | AP27: -0.37226277 | AR27: -0.43575419 | AT27: -0.24161074 | AU27: -0.20289855 | AV27: -0.32825795 | AW27: -0.029896512 | AX27: -0.28723404 | AY27: -0.18151515 | AZ27: -0.0026737968 | BA27: 0.22413793 | BB27: -0.19036697 | BC27: -0.050505051 | BD27: -0.17731959 | BE27: -0.20655738 | BF27: -0.069958848 | BG27: -0.59323467 | BH27: -0.20393658 | BJ27: -0.28124031 | BK27: -0.24364162 | BL27: -0.074203494 | BM27: -0.0073313783 | BO27: -0.22004426 | BP27: -0.36393443 | BQ27: -0.11834625 | BR27: -0.27777778 | BS27: -0.17290407 | BT27: -0.28507042 | BV27: -0.36810162 | BW27: 0.029228496 | BX27: 0.018224681 | BZ27: -0.14845758 | CA27: -0.15757576 | CB27: -0.1745044 | CC27: 0.020114109 | CD27: -0.35627737 | CE27: -0.24233983 | CF27: 0.40547264 | CJ27: 0.080927372 | CK27: -0.19136011 | CL27: -0.23376623 | CN27: -0.36326531 | CO27: -0.061734892 | CP27: -0.11406844 | CQ27: -0.27878788 | CR27: -0.074434644 | CS27: -0.42262895 | CT27: -0.020242915 | CU27: -0.40578035 | CV27: -0.098244377 | CW27: 0.032489611 | CX27: -0.022929769 | CY27: -0.079734219 | CZ27: -0.052152965 | DA27: -0.049228508 | DB27: -0.16405136 | DC27: -0.10746786 | DD27: 0.060010063 | DE27: -0.27564103 | DF27: -0.25183016 | DG27: -0.094074074 | DI27: -0.069655428 | DJ27: -0.1504065 | DK27: -0.43807216 | DL27: 0 | DM27: -0.125 | DN27: -0.31713555 | DP27: -0.031030131 | DQ27: -0.064246575 | DR27: -0.33665835 | DS27: -0.13675743 | DU27: 0.088585018 | DW27: -0.46127946 | DY27: -0.12539405 | DZ27: -0.35907336 | EA27: -0.19742489 | EB27: -0.24456522 | EC27: 0.22727273 | ED27: -0.27130162 | EE27: -0.46921053 | EF27: 1.426501 | EG27: -0.18988903 | EH27: -0.2027027 | EI27: -0.050555013 | EJ27: 0.070744289 | EK27: -0.35394555 | EL27: -0.046875 | EM27: -0.38461538 | EN27: -0.058503935 | EO27: -0.11133201
A28: 2022 | B28: 5 | C28: 0.0022573655 | D28: 0.00032782562 | E28: 0.038149351 | F28: -0.10638298 | H28: 0.51012146 | I28: -0.012222222 | J28: 0.047082041 | K28: -0.059585492 | L28: -0.2722372 | M28: 0.025076245 | O28: -0.040307102 | P28: -0.29 | Q28: -0.13259958 | R28: -0.24158632 | T28: 0.42654028 | U28: -0.11758989 | V28: -0.558 | W28: 0.34241908 | X28: -0.21259843 | Y28: -0.1538223 | Z28: -0.22432432 | AB28: 0.0023911883 | AC28: -0.34475806 | AD28: -0.088317757 | AE28: -0.04587156 | AF28: -0.054151625 | AG28: -0.32716049 | AH28: -0.1503268 | AI28: -0.10348906 | AJ28: 0.54482759 | AK28: -0.14468085 | AL28: -0.029813665 | AM28: -0.031148303 | AN28: -0.16810036 | AO28: -0.1106383 | AP28: -0.058139535 | AR28: -0.06960396 | AT28: 0.088495575 | AU28: 0.0051948052 | AV28: 0.22222222 | AW28: -0.063611221 | AX28: -0.097014925 | AY28: -0.26804887 | AZ28: 0.15281501 | BA28: 0.0035211268 | BB28: -0.1388102 | BC28: -0.52304965 | BD28: -0.21679198 | BE28: -0.037190083 | BF28: -0.1460177 | BG28: -0.25987526 | BH28: -0.31181319 | BJ28: -0.1586497 | BK28: -0.16431028 | BL28: -0.031971581 | BM28: 0.067946824 | BO28: -0.41305229 | BP28: 0.0051546392 | BQ28: -0.11078546 | BR28: -0.094017094 | BS28: 0.13416321 | BT28: -0.093774626 | BV28: -0.18650882 | BW28: -0.065784546 | BX28: 0.0011113162 | BZ28: -0.16981132 | CA28: -0.26258993 | CB28: -0.042537153 | CC28: 0.076552358 | CD28: -0.080394603 | CE28: -0.25367647 | CF28: -0.053097345 | CJ28: 0.037658985 | CK28: -0.15609349 | CL28: -0.15738499 | CN28: -0.64141026 | CO28: 0.18732473 | CP28: -0.24248927 | CQ28: -0.1232493 | CR28: 0.1835506 | CS28: -0.28530259 | CT28: -0.15082645 | CU28: -0.09922179 | CV28: 0.074486406 | CW28: 0.0212221 | CX28: -0.15180367 | CY28: -0.079422383 | CZ28: 0.089483788 | DA28: -0.44590417 | DB28: -0.039249147 | DC28: 0.16209928 | DD28: 0.26349002 | DE28: -0.13734513 | DF28: 0.057279843 | DG28: -0.067865904 | DI28: -0.25169255 | DJ28: -0.14832536 | DK28: 0.46621945 | DL28: 0.0029469548 | DM28: -0.034205231 | DN28: -0.20973783 | DP28: 0.68980589 | DQ28: -0.2740448 | DR28: 0.29699248 | DS28: -0.0010752688 | DU28: -0.24904424 | DW28: 0.08125 | DY28: -0.09050861 | DZ28: -0.098393574 | EA28: -0.19518717 | EB28: -0.15107914 | EC28: -0.1037037 | ED28: -0.40286944 | EE28: -0.01536936 | EF28: 0.10409556 | EG28: -0.70624049 | EH28: -0.19774011 | EI28: 0.20005752 | EJ28: 0.20509291 | EK28: -0.03 | EL28: -0.094262295 | EM28: 0.07828125 | EN28: -0.035655498 | EO28: 0.035794183
A29: 2022 | B29: 6 | C29: -0.082469432 | D29: 0.00077987071 | E29: 0.091477717 | F29: 0.063492063 | H29: -0.30831099 | I29: 1.1664792 | J29: -0.063274098 | K29: -0.12396694 | L29: 0.92592593 | M29: -0.019173554 | O29: -0.48333333 | P29: -0.35633803 | Q29: -0.042900302 | R29: 0.009594627 | S29: 0.0030150754 | T29: -0.019933555 | U29: -0.66409692 | V29: 0.1040724 | W29: -0.098984772 | X29: 0.532 | Y29: 0.26443101 | Z29: -0.35191638 | AB29: 0.027700012 | AC29: -0.42 | AD29: 0.1173757 | AE29: 0.097355769 | AF29: -0.19465649 | AG29: 0.33944954 | AH29: 0.13076923 | AI29: -0.07651715 | AJ29: -0.053571429 | AK29: 0.019900498 | AL29: 0.13444302 | AM29: 0.14107486 | AN29: -0.075398535 | AO29: -0.0071770335 | AP29: 0.24074074 | AR29: -0.020964137 | AT29: 0 | AU29: -0.033591731 | AV29: -0.13090909 | AW29: -0.17172996 | AX29: 0.0082644628 | AY29: 0.083965604 | AZ29: -0.10077519 | BA29: 0.11578947 | BB29: -0.13815789 | BC29: 0.20446097 | BD29: 0.2736 | BE29: -0.16309013 | BF29: -0.18445596 | BG29: -0.31179775 | BH29: -0.003992016 | BJ29: -0.26611973 | BK29: -0.041609511 | BL29: 0.11857798 | BM29: 0.0069156293 | BO29: 0.22007366 | BP29: 0.13589744 | BQ29: -0.027027027 | BR29: -0.094339623 | BS29: -0.0055749129 | BT29: -0.12956522 | BV29: -0.19275124 | BW29: 0.042290219 | BX29: -0.011251376 | BZ29: 0.069545455 | CA29: 0.45365854 | CB29: 0.0034866719 | CC29: 0.034424376 | CD29: -0.012330456 | CE29: 0.073891626 | CF29: 0.056074766 | CJ29: -0.0012557833 | CK29: 0.2363996 | CL29: 0.091954023 | CN29: 0.072577762 | CO29: -0.12366059 | CP29: -0.082152975 | CQ29: 0.28434505 | CR29: -0.11090599 | CS29: 0.10887097 | CT29: 0.7810219 | CU29: -0.010799136 | CV29: -0.0041660746 | CW29: 0.053385883 | CX29: -0.07826087 | CY29: 0.10196078 | CZ29: -0.011499944 | DA29: 0.17712692 | DB29: 0.42273535 | DC29: 0.024477197 | DD29: 0.40110497 | DE29: -0.13848995 | DF29: -0.15042479 | DG29: -0.093859649 | DI29: 0.01064396 | DJ29: -0.38202247 | DK29: -0.081045752 | DL29: 0.00097943193 | DM29: 0.0041666667 | DN29: -0.11848341 | DP29: 0.058500586 | DQ29: 0.063520871 | DR29: -0.15362319 | DS29: 0.037674919 | DU29: 0.061818182 | DW29: 0.43352601 | DY29: 0.075737561 | DZ29: -0.30512249 | EA29: -0.27906977 | EB29: 0.11864407 | EC29: 0.16115702 | ED29: 0.34262374 | EE29: 0.0020140987 | EF29: -0.12673879 | EG29: -0.0051813472 | EH29: 0.18309859 | EI29: -0.14669665 | EJ29: -0.30154198 | EK29: -0.045409917 | EL29: -0.30316742 | EM29: -0.36212143 | EN29: 0.0056160482 | EO29: -0.036717063
A30: 2022 | B30: 7 | C30: 0.092087608 | D30: 0.00035947045 | E30: 0.10386819 | F30: -0.51492537 | H30: 0.069767442 | I30: 0.40134995 | J30: 0.074734119 | K30: 0.11320755 | L30: -0.42596154 | M30: 0.15436468 | O30: 0.10451613 | P30: 0.28477649 | Q30: 0.07354798 | R30: 0.26181991 | S30: 0.004509018 | T30: 0.3220339 | U30: 0.14098361 | V30: 0.93852459 | W30: 0.15492958 | X30: 0.0075718016 | Y30: -0.24637681 | Z30: -0.2311828 | AB30: -0.041817347 | AC30: -0.045092838 | AD30: -0.11926606 | AE30: -0.04271632 | AF30: -0.1042654 | AG30: -0.15753425 | AH30: 0.047619048 | AI30: -0.21535714 | AJ30: -0.10853774 | AK30: -0.020731707 | AL30: -0.029909707 | AM30: 0.20521447 | AN30: -0.013979497 | AO30: 0.093975904 | AP30: 0.33084577 | AR30: -0.029347826 | AT30: -0.097560976 | AU30: -0.0026737968 | AV30: 0.025104603 | AW30: 0.032093734 | AX30: -0.040983607 | AY30: -0.40270649 | AZ30: 0.062931034 | BA30: -0.092767296 | BB30: 0.022900763 | BC30: -0.058641975 | BD30: 0.21482412 | BE30: -0.12820513 | BF30: 0.16010165 | BG30: 0.2 | BH30: 0.11823647 | BJ30: -0.056768559 | BK30: -0.026717557 | BL30: 0.040188641 | BM30: -0.076923077 | BO30: -0.0028301887 | BP30: 0.14221219 | BQ30: -0.028455285 | BR30: -0.026041667 | BS30: -0.051857043 | BT30: 0.098901099 | BV30: -0.12619048 | BW30: 0.00032049228 | BX30: -0.016843778 | BZ30: -0.68742031 | CA30: -0.093959732 | CB30: 0.03149518 | CC30: 0.016839992 | CD30: -0.059300874 | CE30: 0.125 | CF30: 0.14867257 | CJ30: -0.020072763 | CK30: -0.04 | CL30: 0.042105263 | CN30: 0.32166667 | CO30: 0.24573747 | CP30: -0.14814815 | CQ30: 0.11442786 | CR30: -0.060147813 | CS30: 0.81090909 | CT30: -0.010928962 | CU30: 0.91703057 | CV30: 0.023000708 | CW30: 0.025680272 | CX30: -0.029845626 | CY30: 0.10320285 | CZ30: -0.029021992 | DA30: 0.091232227 | DB30: 1.1685393 | DC30: 0.032041086 | DD30: -0.18454259 | DE30: -0.054774946 | DF30: -0.041394336 | DG30: 0.089060987 | DI30: 0.34807794 | DJ30: -0.42190909 | DK30: -0.41927454 | DL30: 0.0078277886 | DM30: 0.024896266 | DN30: 0.24193548 | DP30: 0.48446009 | DQ30: 0.020667425 | DR30: 0.0034246575 | DS30: 0.097856155 | DU30: 0.028767123 | DW30: -0.14112903 | DY30: -0.15677446 | DZ30: 0.16987179 | EA30: 0.85253456 | EB30: -0.0875 | EC30: 0.088967972 | ED30: 1.3622047 | EE30: -0.37386935 | EF30: 0.07079646 | EG30: 0.640625 | EH30: -0.095238095 | EI30: -0.074497732 | EJ30: 0.23548651 | EK30: 0.11108254 | EL30: -0.077922078 | EM30: 0.090640618 | EN30: 0.063974905 | EO30: 0.25560538
A31: 2022 | B31: 8 | C31: -0.0408019 | D31: 0.0019345359 | E31: 0.032446463 | F31: -0.17415385 | H31: 0.076086957 | I31: -0.064838829 | J31: -0.20834448 | K31: -0.38700565 | L31: 0.16247906 | M31: 0.077080292 | O31: 1.0023364 | P31: 0.75790754 | Q31: -0.24532 | R31: -0.20278667 | S31: 0.0059850374 | T31: -0.34615385 | U31: -0.028735632 | V31: 0.4038055 | W31: -0.085365854 | X31: 0.65327805 | Y31: -0.57211538 | Z31: -0.18881119 | AB31: -0.086338542 | AC31: 0.22222222 | AD31: 0.041666667 | AE31: 0.18077803 | AF31: 0.084656085 | AG31: 0.34146341 | AH31: -0.11038961 | AI31: 0.11242604 | AJ31: 0.0053441981 | AK31: -0.001494396 | AL31: 0.022687609 | AM31: -0.099092812 | AN31: -0.077504726 | AO31: 0.035242291 | AP31: -0.34018692 | AR31: 0.37737962 | AT31: -0.027027027 | AU31: -0.091930295 | AV31: 0.48469388 | AW31: -0.25320829 | AX31: 0.0085470085 | AY31: -0.128125 | AZ31: -0.22060016 | BA31: 0.29289428 | BB31: -0.15671642 | BC31: -0.1147541 | BD31: 0.042399173 | BE31: -0.041176471 | BF31: 0.095290252 | BG31: 0.2585034 | BH31: 0.39336918 | BJ31: 0.26425926 | BK31: 0.053921569 | BL31: -0.13443722 | BM31: 0.33779762 | BO31: 0.059602649 | BP31: -0.061264822 | BQ31: -0.082287308 | BR31: 0.21390374 | BS31: -0.071322986 | BT31: -0.2 | BV31: -0.085247178 | BW31: -0.0053825452 | BX31: -0.069288216 | BZ31: 0.32154997 | CA31: 0.096296296 | CB31: 0.0039117679 | CC31: -0.083417243 | CD31: -0.23025879 | CE31: 0.17635066 | CF31: -0.10785824 | CJ31: -0.044548744 | CK31: -0.020833333 | CL31: -0.0050505051 | CN31: -0.18032787 | CO31: -0.12322653 | CP31: 0.014492754 | CQ31: 0.13392857 | CR31: -0.092443132 | CS31: -0.19076305 | CT31: 0.0082872928 | CU31: -0.025056948 | CV31: -0.24322982 | CW31: -0.16133311 | CX31: -0.072135785 | CY31: -0.11290323 | CZ31: -0.10453534 | DA31: -0.072747014 | DB31: 0.1099597 | DC31: -0.10627923 | DD31: 0.17117988 | DE31: -0.17422525 | DF31: 0.0045454545 | DG31: -0.20888889 | DI31: 0.13828125 | DJ31: 2.4439377 | DK31: 0.57562768 | DL31: 0.0038834951 | DM31: 0.18421053 | DN31: 0.095238095 | DP31: -0.1227449 | DQ31: 0.040312094 | DR31: -0.051194539 | DS31: 0.078110236 | DU31: 0.023968043 | DW31: 0.83098592 | DY31: 0.43203883 | DZ31: 0.04109589 | EA31: -0.069651741 | EB31: -0.0078870901 | EC31: 0.039215686 | ED31: 0 | EE31: 0.59069021 | EF31: 0.26446281 | EG31: 0.24444444 | EH31: -0.16447368 | EI31: -0.0028010224 | EJ31: 0.35009927 | EK31: -0.27493636 | EL31: 0.17605634 | EM31: -0.16871485 | EN31: -0.14253641 | EO31: -0.025
A32: 2022 | B32: 9 | C32: -0.092416539 | D32: 0.0020609946 | E32: -0.010685104 | F32: -0.34798808 | H32: -0.27946128 | I32: 0.11529319 | J32: -0.050675676 | K32: -0.069124424 | L32: -0.19308357 | M32: -0.12876118 | O32: 0.014002334 | P32: -0.19031142 | Q32: -0.1038961 | R32: 0.050779405 | S32: 0.005453644 | T32: -0.10980392 | U32: -0.12130178 | V32: -0.24548193 | W32: -0.24133333 | X32: -0.30062696 | Y32: -0.16853933 | Z32: -0.094827586 | AB32: 0.054591391 | AC32: -0.027272727 | AD32: -0.0596 | AE32: -0.093023256 | AF32: -0.073170732 | AG32: -0.35151515 | AH32: -0.17518248 | AI32: -0.26759411 | AJ32: -0.41578947 | AK32: -0.2741332 | AL32: -0.088737201 | AM32: -0.00697134 | AN32: -0.33401639 | AO32: 0.025531915 | AP32: -0.19830028 | AR32: -0.016260163 | AT32: -0.074074074 | AU32: -0.27371498 | AV32: -0.20522337 | AW32: -0.17977528 | AX32: 0.93220339 | AY32: -0.2437276 | AZ32: -0.16233091 | BA32: -0.10187668 | BB32: -0.07079646 | BC32: -0.30740741 | BD32: -0.023809524 | BE32: 0.1993865 | BF32: -0.209 | BG32: 0.093243243 | BH32: -0.25273312 | BJ32: -0.25999707 | BK32: -0.19093023 | BL32: 0.0086540651 | BM32: 0.34260289 | BO32: -0.22982143 | BP32: -0.25263158 | BQ32: -0.11778116 | BR32: -0.11453744 | BS32: -0.074214087 | BT32: -0.38636364 | BV32: -0.33617021 | BW32: -0.14128334 | BX32: 0.012520241 | BZ32: -0.20910494 | CA32: -0.1722973 | CB32: -0.067972724 | CC32: 0.073432471 | CD32: -0.22413793 | CE32: -0.057192374 | CF32: -0.13471503 | CJ32: 0.016910215 | CK32: -0.53191489 | CL32: -0.18781726 | CN32: 0.13846154 | CO32: -0.067532468 | CP32: -0.2 | CQ32: -0.18307087 | CR32: -0.17980836 | CS32: -0.21836228 | CT32: 0.002739726 | CU32: -0.24299065 | CV32: -0.095307604 | CW32: -0.014827995 | CX32: 0.013528963 | CY32: -0.17818182 | CZ32: -0.032500774 | DA32: 0.29742389 | DB32: 0.083506224 | DC32: -0.040297471 | DD32: -0.068538398 | DE32: -0.22196796 | DF32: -0.19230769 | DG32: 0.076404494 | DI32: 0.27041867 | DJ32: -0.2739726 | DK32: 0.62534007 | DL32: -0.00096711799 | DM32: 0.11452991 | DN32: -0.051383399 | DP32: -0.31697827 | DQ32: -0.37410714 | DR32: -0.23381295 | DS32: -0.011101373 | DU32: 0.11313394 | DW32: 0.51025641 | DY32: -0.29152542 | DZ32: -0.27631579 | EA32: -0.30213904 | EB32: -0.26276151 | EC32: -0.51572327 | ED32: -0.18181818 | EE32: -0.32996973 | EF32: -0.24705882 | EG32: -0.25510204 | EH32: -0.062992126 | EI32: -0.10784968 | EJ32: 0.71127451 | EK32: -0.28790297 | EL32: -0.065868263 | EM32: -0.43598096 | EN32: -0.052641912 | EO32: 0.14285714
A33: 2022 | B33: 10 | C33: 0.081275791 | D33: 0.0015897569 | E33: -0.0082592122 | F33: -0.15714286 | H33: 0.060747664 | I33: 0.26714032 | J33: 0.099644128 | K33: 0.089108911 | L33: -0.13928571 | M33: 0.20068451 | O33: -0.1703107 | P33: -0.25641026 | Q33: -0.16811594 | R33: 0.11732974 | S33: 0.0029585799 | T33: 0.13656388 | U33: 0.11447811 | V33: 0.31536926 | W33: 0.054481547 | X33: 0.011878082 | Y33: -0.11351351 | Z33: 0.028571429 | AB33: 0.098123812 | AC33: 0.051401869 | AD33: 0.095278605 | AE33: 0.0042735043 | AF33: -0.063157895 | AG33: 0.0093457944 | AH33: 0.0088495575 | AI33: -0.10614525 | AJ33: 0.13513514 | AK33: -0.28980527 | AL33: 0.11985019 | AM33: 0.11544462 | AN33: -0.037692308 | AO33: 0.020746888 | AP33: 0.084805654 | AR33: -0.10743802 | AT33: -0.03 | AU33: -0.085365854 | AV33: 0.12417848 | AW33: 0.062852538 | AX33: 0.94736842 | AY33: -0.19194313 | AZ33: 0.063354037 | BA33: 0.21343284 | BB33: 0.21428571 | BC33: -0.07486631 | BD33: -0.033536585 | BE33: 0.10485934 | BF33: -0.31731985 | BG33: -0.31273177 | BH33: -0.12392427 | BJ33: 0.054038005 | BK33: -0.35613682 | BL33: 0.17407993 | BM33: -0.0033140017 | BO33: 0.024576861 | BP33: -0.22535211 | BQ33: 0.16795866 | BR33: 0.16915423 | BS33: -0.018482699 | BT33: 0.043209877 | BV33: -0.10384615 | BW33: 0.078775602 | BX33: 0.064948334 | BZ33: 0.068292683 | CA33: -0.097959184 | CB33: 0.017884102 | CC33: 0.11980832 | CD33: -0.091111111 | CE33: -0.10110294 | CF33: -0.063872255 | CJ33: 0.17510378 | CK33: -0.036363636 | CL33: 0.175 | CN33: 0.094594595 | CO33: 0.19220056 | CP33: -0.017857143 | CQ33: -0.13012048 | CR33: 0.11880071 | CS33: 0.050793651 | CT33: -0.046448087 | CU33: 0.097222222 | CV33: 0.10533993 | CW33: 0.093317279 | CX33: -0.026884753 | CY33: -0.061946903 | CZ33: 0.063758258 | DA33: -0.0433213 | DB33: 0.19052178 | DC33: 0.12955643 | DD33: 0.068262411 | DE33: -0.058823529 | DF33: -0.036414566 | DG33: -0.36325678 | DI33: -0.8273906 | DJ33: 1.4654088 | DK33: -0.12864658 | DL33: 0.0087221684 | DM33: -0.1809816 | DN33: -0.0375 | DP33: -0.10776442 | DQ33: -0.50356633 | DR33: -0.0657277 | DS33: 0.012407681 | DU33: 0.075934579 | DW33: 0.17317487 | DY33: -0.36842105 | DZ33: 0.48 | EA33: 0.061302682 | EB33: -0.18274688 | EC33: 0.28571429 | ED33: -0.074074074 | EE33: -0.046686747 | EF33: 0.0625 | EG33: -0.14726027 | EH33: -0.10084034 | EI33: 0.18897256 | EJ33: -0.072758522 | EK33: 0.14567459 | EL33: 0.025641026 | EM33: 0.4660151 | EN33: 0.018983337 | EO33: -0.1025641
A34: 2022 | B34: 11 | C34: 0.055591284 | D34: 0.0031463204 | E34: -0.024983985 | F34: -0.085084746 | H34: -0.14317181 | I34: 0.07569386 | J34: -0.045631068 | K34: 0.16363636 | L34: -0.087136929 | M34: 0.087069189 | O34: -0.30859917 | P34: 0.066666667 | Q34: -0.14285714 | R34: -0.17441159 | S34: 0.0078662734 | T34: 0.20155039 | U34: -0.060422961 | V34: 0.39150228 | W34: -0.21833333 | X34: 0.60110742 | Y34: 0.25060976 | Z34: -0.027777778 | AB34: 0.036271504 | AC34: -0.11333333 | AD34: -0.3992233 | AE34: 0.25531915 | AF34: 0.97191011 | AG34: -0.080833333 | AH34: 0.061403509 | AI34: -0.36875 | AJ34: 0.095238095 | AK34: 0.10483871 | AL34: 0.21906355 | AM34: -0.11608392 | AN34: -0.035171863 | AO34: -0.077235772 | AP34: 0.35504886 | AR34: 0.083333333 | AT34: -0.082371134 | AU34: -0.2 | AV34: -0.354 | AW34: -0.024260804 | AX34: -0.040540541 | AY34: -0.15835777 | AZ34: -0.15420561 | BA34: -0.17589176 | BB34: 0.18431373 | BC34: -0.13294798 | BD34: -0.058885384 | BE34: -0.087962963 | BF34: -0.40740741 | BG34: 0.23201439 | BH34: 0.074656189 | BJ34: -0.3141784 | BK34: -0.27678571 | BL34: 0.14942308 | BM34: -0.073150457 | BO34: -0.16270649 | BP34: -0.18909091 | BQ34: -0.031710914 | BR34: 0.3106383 | BS34: 0.18721261 | BT34: -0.23076923 | BV34: -0.070100143 | BW34: 0.091244176 | BX34: 0.029735063 | BZ34: -0.45966514 | CA34: 0.33936652 | CB34: -0.16828294 | CC34: 0.027648724 | CD34: 0.100489 | CE34: 0.026584867 | CF34: -0.25159915 | CJ34: 0.088142519 | CK34: -0.43102426 | CL34: -0.25531915 | CN34: 0.77777778 | CO34: -0.08411215 | CP34: -0.13181818 | CQ34: -0.17728532 | CR34: 0.0051499896 | CS34: -0.35347432 | CT34: -0.49283668 | CU34: 0.18846695 | CV34: -0.15366695 | CW34: 0.12812041 | CX34: -0.067812983 | CY34: -0.10400943 | CZ34: 0.086155779 | DA34: -0.058490566 | DB34: -0.26095698 | DC34: -0.19985123 | DD34: -0.13941909 | DE34: -0.14354167 | DF34: 0.087209302 | DG34: 0.35737705 | DI34: -0.27230047 | DJ34: -0.06377551 | DK34: -0.044182217 | DL34: -0.56804637 | DM34: 0.37265918 | DN34: 0.021645022 | DP34: -0.0010934319 | DQ34: -0.16666667 | DR34: -0.14070352 | DS34: 0.0714911 | DU34: -0.087404995 | DW34: 0.12445731 | DX34: -0.1864831 | DY34: -0.09469697 | DZ34: -0.049140049 | EA34: -0.22743682 | EB34: 0.15972222 | EC34: -0.050505051 | ED34: -0.188 | EE34: -0.2764613 | EF34: -0.53594771 | EG34: 0.30522088 | EH34: -0.21495402 | EI34: 0.10064767 | EJ34: -0.10441767 | EK34: -0.089984351 | EL34: -0.0625 | EM34: -0.18181818 | EN34: 0.022284304 | EO34: -0.15
A35: 2022 | B35: 12 | C35: -0.05757577 | D35: 0.0036305257 | E35: 0.034822602 | F35: -0.20340867 | H35: -0.29562982 | I35: -0.037008079 | J35: -0.049847406 | K35: -0.22265625 | L35: 0.10168182 | M35: -0.041001192 | O35: -0.044132397 | P35: -0.027909483 | Q35: 0.17479675 | R35: -0.166423 | S35: 0.0048780488 | T35: 0.38709677 | U35: 0.019292605 | V35: -0.21919302 | W35: 0.025586354 | X35: 0.066952552 | Y35: -0.078498294 | Z35: -0.12704762 | AB35: -0.10376071 | AC35: -0.065162907 | AD35: -0.19198449 | AE35: -0.089830508 | AF35: -0.4017094 | AG35: 0.0073536819 | AH35: -0.074380165 | AI35: -0.20792079 | AJ35: -0.52775362 | AK35: -0.28832117 | AL35: 0.0608139 | AM35: -0.1965981 | AN35: -0.2054681 | AO35: -0.0088105727 | AP35: 0.014423077 | AR35: -0.32478632 | AT35: -0.067520503 | AU35: 0.066666667 | AV35: -0.17599428 | AW35: -0.050505051 | AX35: -0.039906103 | AY35: -0.27526132 | AZ35: 0.037292818 | BA35: -0.070149254 | BB35: -0.066225166 | BC35: 0.78666667 | BD35: -0.0011173184 | BE35: -0.17258883 | BF35: 0.09375 | BG35: 0.062773723 | BH35: -0.11151737 | BJ35: -0.17771084 | BK35: 0.92592593 | BL35: -0.078132843 | BM35: 0.32376682 | BO35: -0.14027027 | BP35: 0.19282511 | BQ35: 0.0091393755 | BR35: 0.1461039 | BS35: -0.023976392 | BT35: -0.35384615 | BV35: -0.33153846 | BW35: 0.015295392 | BX35: -0.0075841381 | BZ35: -0.033802817 | CA35: -0.16891892 | CB35: -0.083676269 | CC35: -0.014120986 | CD35: -0.1161964 | CE35: 0.2689243 | CF35: -0.10541311 | CJ35: 0.014131066 | CK35: -0.076223412 | CL35: -0.19285714 | CN35: -0.22916667 | CO35: -0.080408163 | CP35: 0.0052356021 | CQ35: -0.053872054 | CR35: 0.073405892 | CS35: 0.056074766 | CT35: 0.04519774 | CU35: 0.42366864 | CV35: 0.089355401 | CW35: 0.01854865 | CX35: -0.19979275 | CY35: -0.42090024 | CZ35: 0.022143211 | DA35: 0.1242485 | DB35: 0.051686616 | DC35: 0.066265633 | DD35: -0.071359691 | DE35: -0.43322793 | DF35: 0.037433155 | DG35: -0.28743961 | DI35: -0.24946237 | DJ35: 0.15803815 | DK35: -0.15188056 | DL35: -0.11353033 | DM35: -0.021828104 | DN35: -0.33898305 | DP35: -0.19825363 | DQ35: 0.065517241 | DR35: -0.34502924 | DS35: -0.028594771 | DU35: -0.12790006 | DW35: 0.31016731 | DX35: -0.77948718 | DY35: -0.054393305 | DZ35: -0.30490956 | EA35: -0.46261682 | EB35: -0.22670659 | EC35: 0.026595745 | ED35: -0.035591133 | EE35: 0.22052402 | EF35: -0.070422535 | EG35: -0.15384615 | EH35: -0.25916596 | EI35: 0.0090622024 | EJ35: 0.13107968 | EK35: -0.35511608 | EL35: -0.11333333 | EM35: -0.15925926 | EN35: -0.04924101 | EO35: -0.035714286
A36: 2023 | B36: 1 | C36: 0.062887306 | D36: 0.0028431053 | E36: 0.073015873 | F36: 1.2093023 | H36: 0.15328467 | I36: 0.060622463 | J36: 0.079942898 | K36: 0.10552764 | L36: 0.05211041 | M36: 0.11185682 | O36: 0.27597062 | P36: -0.013413147 | Q36: 0.11418685 | R36: -0.042092955 | S36: 0.0097087379 | T36: -0.044186047 | U36: 0.27444795 | V36: 0.050977654 | W36: -0.037422037 | X36: -0.027615714 | Y36: -0.12698413 | Z36: -0.072878027 | AB36: 0.017731358 | AC36: 0.10723861 | AD36: 0.3676 | AE36: 0.087523277 | AF36: -0.061904762 | AG36: -0.0393 | AH36: 0.25892857 | AI36: -0.079166667 | AJ36: 0.62651527 | AK36: 0.44615385 | AL36: 0.21034483 | AM36: 0.12555391 | AN36: 0.11574557 | AO36: 0.20444444 | AP36: 0.028436019 | AR36: 0.75949367 | AT36: 0.53012048 | AU36: 0.19276042 | AV36: 0.88150289 | AW36: 0.12356792 | AX36: 0.12958435 | AY36: 0.37980769 | AZ36: 0.38348868 | BA36: 0.020866774 | BB36: 0.23404255 | BC36: 0.50746269 | BD36: 0.1442953 | BE36: 0.44785276 | BF36: 0.33142857 | BG36: 0.73214286 | BH36: -0.085390947 | BJ36: 1.4302364 | BK36: -0.3525641 | BL36: -0.12577132 | BM36: 0.017615176 | BO36: 0.25746621 | BP36: 0.60150376 | BQ36: -0.045283019 | BR36: -0.016997167 | BS36: -0.094482237 | BT36: 0.6547619 | BV36: -0.30494822 | BW36: -0.016634235 | BX36: -0.074893883 | BZ36: 0.029154519 | CA36: 0.3049187 | CB36: 0.043413174 | CC36: -0.059288302 | CD36: 0.3323278 | CE36: 0.03610675 | CF36: -0.092356688 | CJ36: -0.031906418 | CK36: 0.27 | CL36: 0.20353982 | CN36: 0.054054054 | CO36: 0.012538837 | CP36: 0.28125 | CQ36: 0.39145907 | CR36: 0.078768435 | CS36: 0.28318584 | CT36: -0.032432432 | CU36: -0.83458022 | CV36: 0.14840314 | CW36: 0.050479233 | CX36: 0.017094017 | CY36: -0.22272727 | CZ36: -0.13018801 | DA36: 0.063279857 | DB36: 0.81272633 | DC36: 0.097683831 | DD36: -0.15057113 | DE36: 0.11587983 | DF36: 0.038659794 | DG36: -0.069491525 | DI36: 0.16332378 | DJ36: 0.12 | DK36: -0.052132701 | DL36: 0.97744361 | DM36: -0.13807531 | DN36: 0.17628205 | DP36: -0.0040802235 | DQ36: 0.2394822 | DR36: 0.48214286 | DS36: 0.14970563 | DU36: 0.075034106 | DW36: -0.10903733 | DX36: 0.01627907 | DY36: -0.11504425 | DZ36: 0.20446097 | EA36: 1.3478261 | EB36: 0.93588354 | EC36: 0.20725389 | ED36: 0.30251564 | EE36: -0.057245081 | EF36: 0.090909091 | EG36: 0.68 | EH36: 0.59055118 | EI36: 0.09254016 | EJ36: 0.28087832 | EK36: 0.73333333 | EL36: -0.067669173 | EM36: 0.51629956 | EN36: 0.13185412 | EO36: 0.18954248
A37: 2023 | B37: 2 | C37: -0.025142616 | D37: 0.0034568398 | E37: -0.26272189 | F37: -0.073684211 | H37: 0.016075949 | I37: -0.11150804 | J37: 0.052875083 | K37: -0.063636364 | L37: 0.20784314 | M37: -0.064609882 | O37: -0.072368421 | P37: -0.12078652 | Q37: -0.11024845 | R37: -0.064693317 | S37: 0.0028942308 | T37: 0.34549878 | U37: -0.23762376 | V37: 0.32225914 | W37: -0.23542117 | X37: -0.0908 | Y37: -0.19393939 | Z37: -0.12873617 | AB37: -0.050792659 | AC37: 0.1283293 | AD37: -0.19567125 | AE37: -0.13013699 | AF37: -0.18781726 | AG37: 0.86322473 | AH37: -0.12056738 | AI37: -0.16289593 | AJ37: -0.27358491 | AK37: -0.30851064 | AL37: -0.05519943 | AM37: -0.0888014 | AN37: -0.37009346 | AO37: -0.15129151 | AP37: -0.066820276 | AR37: -0.17266187 | AT37: -0.18110236 | AU37: -0.2707742 | AV37: -0.22273425 | AW37: -0.16460306 | AX37: 0.16558442 | AY37: -0.271777 | AZ37: -0.12704524 | BA37: -0.028301887 | BB37: 0.07183908 | BC37: -0.27970297 | BD37: -0.063538612 | BE37: 0.23305085 | BF37: -0.2832618 | BG37: -0.52101507 | BH37: 0.077615298 | BJ37: 0.19690326 | BK37: -0.42376238 | BL37: -0.085945609 | BM37: 0.1930759 | BO37: -0.05 | BP37: -0.058685446 | BQ37: -0.045849802 | BR37: -0.0057636888 | BS37: 0.023163606 | BT37: -0.17985612 | BV37: -0.57615894 | BW37: -0.10379165 | BX37: -0.05556375 | BZ37: 0.26062323 | CA37: -0.056104171 | CB37: 0.035007174 | CC37: -0.092744899 | CD37: -0.14849057 | CE37: 0.1469697 | CF37: -0.16491228 | CJ37: -0.010892466 | CK37: -0.071269937 | CL37: -0.49264706 | CN37: -0.12820513 | CO37: 0.093150685 | CP37: -0.21138211 | CQ37: 0.54475703 | CR37: -0.17829342 | CS37: 0.3 | CT37: 0.0055865922 | CU37: 0.055276382 | CV37: 0.027921486 | CW37: -0.083789538 | CX37: 0.084033613 | CY37: -0.21649123 | CZ37: -0.081296224 | DA37: -0.28248114 | DB37: -0.090753425 | DC37: 0.007215162 | DD37: -0.10635697 | DE37: -0.19230769 | DF37: -0.14399504 | DG37: 0.14754098 | DI37: -0.11330049 | DJ37: -0.014705882 | DK37: -0.11785714 | DL37: 0.096324461 | DM37: 0.21359223 | DN37: -0.1880109 | DP37: -0.065488009 | DQ37: -0.44908616 | DR37: -0.26506024 | DS37: -0.083394294 | DU37: -0.01713198 | DW37: 0.1168688 | DX37: -0.029748284 | DY37: -0.29 | DZ37: -0.12654321 | EA37: -0.29259259 | EB37: -0.3512 | EC37: 0.025751073 | ED37: -0.085882353 | EE37: -0.058823529 | EF37: -0.31336806 | EG37: 0.67748918 | EH37: -0.04738331 | EI37: -0.06249659 | EJ37: 0.029761905 | EK37: -0.28739316 | EL37: 0.11290323 | EM37: -0.2969204 | EN37: 0.0091244654 | EO37: 0.064102564
A38: 2023 | B38: 3 | C38: 0.037125014 | D38: 0.0039945258 | E38: -0.35072231 | F38: -0.20454545 | H38: -0.2898966 | I38: -0.15738082 | J38: 0.17702448 | K38: -0.32524272 | L38: -0.058441558 | M38: -0.050669216 | O38: -0.125 | P38: 0.45686901 | Q38: -0.19022688 | R38: -0.108646 | S38: 0.0067017574 | T38: 0.15189873 | U38: -0.18831169 | V38: -0.079396985 | W38: -0.053672316 | X38: -0.095468544 | Y38: -0.15793233 | Z38: -0.17612102 | AB38: 0.0050767364 | AC38: 0.32832618 | AD38: -0.35064935 | AE38: -0.51673228 | AF38: 0.2375 | AG38: -0.44972067 | AH38: -0.16129032 | AI38: -0.45945946 | AJ38: -0.26987013 | AK38: 0.020512821 | AL38: -0.095740671 | AM38: 0.039846375 | AN38: -0.42136499 | AO38: -0.15217391 | AP38: 0.022222222 | AR38: 0.017391304 | AS38: -0.29145729 | AT38: 0 | AU38: -0.05988024 | AV38: -0.10474308 | AW38: -0.18047079 | AX38: 0.016713092 | AY38: -0.20373206 | AZ38: -0.067254686 | BA38: -0.74271845 | BB38: 0.032171582 | BC38: -0.34707904 | BD38: -0.30375783 | BE38: 0.21305842 | BF38: -0.11976048 | BG38: -0.5281457 | BH38: -0.16597077 | BJ38: -0.11104751 | BK38: -0.29209622 | BL38: -0.25846014 | BM38: 0.18080357 | BO38: -0.10657895 | BP38: -0.13965087 | BQ38: -0.067937034 | BR38: 0.086956522 | BS38: 0.10442586 | BT38: -0.12289474 | BV38: -0.67317708 | BW38: 0.042236467 | BX38: 0.011353256 | BZ38: -0.2494382 | CA38: -0.10231023 | CB38: 0.019683948 | CC38: 0.10346375 | CD38: -0.29514735 | CE38: -0.087186262 | CF38: -0.15546218 | CJ38: 0.0082457816 | CK38: -0.26086957 | CL38: -0.49065217 | CN38: -0.35382353 | CO38: -0.17042607 | CP38: -0.1443299 | CQ38: -0.12748344 | CR38: -0.039607502 | CS38: 0.23342175 | CT38: 0.072222222 | CU38: 0.038095238 | CV38: -0.024826082 | CW38: 0.039502075 | CX38: -0.041343669 | CY38: -0.25347067 | CZ38: 0.0056699369 | DA38: -0.16588785 | DB38: -0.1650973 | DC38: -0.041141782 | DD38: 0.042407661 | DE38: -0.33571429 | DF38: -0.15354958 | DG38: -0.18095238 | DI38: -0.37222222 | DJ38: -0.10660981 | DK38: -0.023481781 | DL38: -0.052023121 | DM38: 0.20933333 | DN38: 1.0134228 | DP38: -0.16057397 | DQ38: -0.29383886 | DR38: -0.1997541 | DS38: -0.036179835 | DU38: -0.18850872 | DW38: 0.16880553 | DX38: -0.028301887 | DY38: -0.53661972 | DZ38: -0.10600707 | EA38: -0.09947644 | EB38: -0.099013564 | EC38: -0.22594142 | ED38: -0.10982411 | EE38: -0.24395161 | EF38: -0.70670038 | EG38: -0.16129032 | EH38: -0.16746209 | EI38: -0.14655532 | EJ38: -0.22543353 | EK38: -0.076461769 | EL38: 0.18115942 | EM38: -0.19421488 | EN38: -0.0033537149 | EO38: -0.053356282
A39: 2023 | B39: 4 | C39: 0.015974985 | D39: 0.0036297357 | E39: 0.098887515 | F39: -0.015714286 | H39: -0.18842105 | I39: -0.032038173 | J39: -0.046133333 | K39: 0.38848921 | L39: 0.0068965517 | M39: -0.050352467 | O39: -0.20466059 | P39: 0.1754386 | Q39: -0.29741379 | R39: -0.040629575 | S39: 0.0014285714 | T39: -0.13500785 | U39: 0.116 | V39: 0.1441048 | W39: -0.023880597 | X39: 0.1596952 | Y39: 0.04915398 | Z39: -0.032786885 | AB39: -0.028885202 | AC39: 0.04361874 | AD39: -0.226 | AE39: -0.14460285 | AF39: -0.1010101 | AG39: 0.096446701 | AH39: -0.028846154 | AI39: 0.51 | AJ39: 0.03361793 | AK39: 0.24623116 | AL39: -0.030012505 | AM39: 0.040166205 | AN39: -0.076923077 | AO39: -0.12307692 | AP39: 0.19323671 | AR39: 0.23931624 | AS39: -0.04964539 | AT39: -0.038461538 | AU39: 0.10191083 | AV39: -0.072847682 | AW39: 0.0074468085 | AX39: -0.13059361 | AY39: 0.10046869 | AZ39: 0.033096927 | BA39: -0.16981132 | BB39: -0.057142857 | BC39: -0.012526316 | BD39: 0.31484258 | BE39: 0.50708215 | BF39: 1.1360544 | BG39: -0.12280702 | BH39: 0.051314143 | BJ39: -0.10431423 | BK39: -0.16019417 | BL39: -0.012557427 | BM39: 0.19234405 | BO39: 0.016200295 | BP39: 0.5884058 | BQ39: 0.042666667 | BR39: 0.368 | BS39: 0.14773777 | BT39: 0.17011701 | BV39: -0.2050996 | BW39: -0.04004647 | BX39: 0.056129032 | BZ39: 0.32934132 | CA39: -0.23161765 | CB39: 0.037928222 | CC39: 0.15269943 | CD39: -0.18264697 | CE39: -0.02894356 | CF39: 0.19402985 | CJ39: 0.085345691 | CK39: -0.32352941 | CL39: 0.070280267 | CN39: -0.11819147 | CO39: 0.0060422961 | CP39: -0.030120482 | CQ39: 0.17647059 | CR39: 0.047191261 | CS39: 0.24731183 | CT39: -0.11398964 | CU39: 0.041284404 | CV39: 0.015663856 | CW39: -0.017563468 | CX39: 0.11026709 | CY39: 0.25974805 | CZ39: -0.046813232 | DA39: 0.49859944 | DB39: 0.062030075 | DC39: 0.036798915 | DD39: -0.015748031 | DE39: 2.0824373 | DF39: 0.0066438356 | DG39: -0.089147287 | DI39: 0.11504425 | DJ39: 0.63484487 | DK39: -0.037313433 | DL39: -0.11707317 | DM39: 0.087100331 | DN39: 0.05 | DP39: 0.013900327 | DQ39: -0.20805369 | DR39: -0.028679709 | DS39: 0.017388904 | DU39: 0.18695306 | DW39: 0.10219595 | DX39: 0.099514563 | DY39: 0.018237082 | DZ39: -0.071146245 | EA39: 0.052325581 | EB39: 0.57383331 | EC39: 0.85945946 | ED39: -0.06060241 | EE39: -0.056 | EF39: 0.094827586 | EG39: -0.050769231 | EH39: -0.094904459 | EI39: -0.030139446 | EJ39: 0.12238806 | EK39: 0.70779221 | EL39: 0.38650307 | EM39: -0.62621083 | EN39: 0.058387533 | EO39: -0.018181818
A40: 2023 | B40: 5 | C40: 0.0046161314 | D40: 0.0037532651 | E40: -0.060742407 | F40: -0.23657475 | H40: 0.28620839 | I40: -0.1306338 | J40: 0.24042494 | K40: 0.21243523 | L40: -0.2260274 | M40: 0.19671262 | O40: -0.28535032 | P40: 0.7238806 | Q40: 0.095705521 | R40: -0.16711179 | S40: -0.010936757 | T40: 0.14882033 | U40: -0.0071684588 | V40: 0.32156489 | W40: 0.22018349 | X40: 0.031455333 | Y40: -0.2893617 | Z40: -0.20338983 | AB40: -0.034895463 | AC40: -0.15325077 | AD40: 0.059431525 | AE40: -0.24285714 | AF40: 0.15168539 | AG40: -0.15740741 | AH40: 0.069306931 | AI40: 0.21854305 | AJ40: 0.49716056 | AK40: -0.12903226 | AL40: -0.051568543 | AM40: 0.042609854 | AN40: -0.054722222 | AO40: -0.058479532 | AP40: -0.026315789 | AR40: -0.2 | AS40: 0.059701493 | AT40: 0.01 | AU40: -0.30924855 | AV40: 0.46428571 | AW40: -0.13938754 | AX40: -0.038865546 | AY40: 1.2878672 | AZ40: 0.035469108 | BA40: 0.03030303 | BB40: 0.090909091 | BC40: -0.11523292 | BD40: 0.15393387 | BE40: -0.46616541 | BF40: -0.036624204 | BG40: 0.088 | BH40: 0.33333333 | BJ40: -0.30984903 | BK40: -0.080924855 | BL40: 0.072580645 | BM40: -0.25247721 | BO40: -0.15942029 | BP40: 0.1770073 | BQ40: 0.15004263 | BR40: -0.24756335 | BS40: -0.04456959 | BT40: -0.017094017 | BV40: 0.33079391 | BW40: -0.08763437 | BX40: -0.045593912 | BZ40: -0.52927928 | CA40: -0.6445933 | CB40: -0.082121807 | CC40: 0.087700488 | CD40: 0.047511312 | CE40: 0.21013413 | CF40: 0.070833333 | CJ40: -0.043820935 | CK40: -0.43486957 | CL40: -0.22889805 | CN40: 0.20440468 | CO40: -0.14744745 | CP40: 0.0062111801 | CQ40: 0.032258065 | CR40: -0.20218786 | CS40: 0.068965517 | CT40: -0.26900585 | CU40: 0.77973568 | CV40: -0.14524303 | CW40: -0.069884609 | CX40: -0.16067093 | CY40: -0.015873016 | CZ40: -0.011706142 | DA40: 0.099065421 | DB40: -0.23433628 | DC40: -0.14062799 | DD40: 0.26533333 | DE40: -0.45813953 | DF40: -0.07134109 | DG40: -0.13191489 | DI40: 0.12698413 | DJ40: -0.1080292 | DK40: -0.021963824 | DL40: -0.1781768 | DM40: 0.077079108 | DN40: -0.20634921 | DP40: 0.036929173 | DQ40: 0 | DR40: 0.022883054 | DS40: -0.10092241 | DU40: 0.12265416 | DW40: -0.18697318 | DX40: 0.057395143 | DY40: 0.48656716 | DZ40: -0.2893617 | EA40: -0.038674033 | EB40: 0.017391304 | EC40: -0.37209302 | ED40: -0.02013595 | EE40: 0.17231638 | EF40: -0.22047244 | EG40: -0.081037277 | EH40: 0.10471499 | EI40: -0.0065620642 | EJ40: -0.083244681 | EK40: 0.19581749 | EL40: 0.13274336 | EM40: -0.42073171 | EN40: -0.072647794 | EO40: -0.066666667
A41: 2023 | B41: 6 | C41: 0.064814273 | D41: 0.0046002928 | E41: 0.24191617 | F41: -0.20836502 | H41: -0.11764706 | I41: -0.12636695 | J41: 0.29524453 | K41: 0.32478632 | L41: 0.039823009 | M41: 0.19251218 | O41: 0.51515152 | P41: -0.28571429 | Q41: 0.11422172 | R41: 0.13696748 | S41: 0.0019230769 | T41: -0.14375987 | U41: 0.064981949 | V41: 0.1898917 | W41: -0.062656642 | X41: -0.026023313 | Y41: -0.041916168 | Z41: 0.10638298 | AB41: -0.0076046138 | AC41: 0.23583181 | AD41: -0.02195122 | AE41: -0.11006289 | AF41: -0.10731707 | AG41: 0.021978022 | AH41: 0.037037037 | AI41: 0.21195652 | AJ41: 0.83908046 | AK41: 0.10648148 | AL41: -0.026280018 | AM41: -0.052788421 | AN41: 0.0023508669 | AO41: -0.086956522 | AP41: -0.17567568 | AR41: 0.034482759 | AS41: 0.063380282 | AT41: -0.098910891 | AU41: 0.33054393 | AV41: -0.19512195 | AW41: 0.23435583 | AX41: 0.11530055 | AY41: -0.19570406 | AZ41: -0.19668508 | BA41: 0.022058824 | BB41: -0.11868687 | BC41: -0.0060240964 | BD41: -0.23418972 | BE41: -0.16549296 | BF41: 0.43801653 | BG41: 0.21323529 | BH41: 0.059375 | BJ41: 0.09375 | BK41: 0.88679245 | BL41: 0.017640254 | BM41: 0.0095440085 | BO41: 0.074482759 | BP41: 0.017054264 | BQ41: -0.056338028 | BR41: 0.12435233 | BS41: 0.066352307 | BT41: -0.069565217 | BV41: -0.22265743 | BW41: -0.032693508 | BX41: 0.06745784 | BZ41: -0.69239234 | CA41: -0.016828218 | CB41: 0.028824201 | CC41: 0.092022497 | CD41: 0.088552916 | CE41: -0.033251232 | CF41: 0.59922179 | CJ41: 0.052126204 | CK41: 0.15740883 | CL41: -0.0084468195 | CN41: -0.30928571 | CO41: 0.056710109 | CP41: 0.11111111 | CQ41: -0.19375 | CR41: 0.073236827 | CS41: -0.12258065 | CT41: -0.016 | CU41: -0.11386139 | CV41: 0.039174268 | CW41: 0.038441377 | CX41: 0.053641862 | CY41: -0.19758065 | CZ41: -0.035243585 | DA41: 0.21768707 | DB41: -0.16227462 | DC41: 0.071309703 | DD41: -0.23498419 | DE41: -0.12875536 | DF41: -0.018207129 | DG41: 0.0098039216 | DI41: -0.13380282 | DJ41: -0.04091653 | DK41: 0.079700572 | DL41: -0.063865546 | DM41: -0.040489642 | DN41: 0.18 | DP41: -0.099810849 | DQ41: -0.050847458 | DR41: 0.10309278 | DS41: -0.092939046 | DU41: 0.07880597 | DW41: -0.17530631 | DX41: 0.0041753653 | DY41: 0.11445783 | DZ41: -0.065868263 | EA41: -0.13793103 | EB41: 0.0085470085 | EC41: 0.10648148 | ED41: -0.15418848 | EE41: -0.0072289157 | EF41: 0.2020202 | EG41: 0.017636684 | EH41: 0.37597146 | EI41: 0.09071822 | EJ41: -0.048447926 | EK41: -0.3481717 | EL41: 0.0234375 | EM41: -0.26315789 | EN41: 0.05643805 | EO41: 0.011904762
A42: 2023 | B42: 7 | C42: 0.032733137 | D42: 0.0038564415 | E42: -0.048216008 | F42: 0.54178674 | H42: -0.1047619 | I42: 0.08715809 | J42: 0.056029233 | K42: 0.032258065 | L42: -0.080851064 | M42: -0.023778562 | O42: -0.044705882 | P42: 0.32727273 | Q42: -0.030150754 | R42: -0.0040290089 | S42: 0.0076775432 | T42: 0.049815498 | U42: -0.010169492 | V42: -0.14441748 | W42: -0.082887701 | X42: 0.091984414 | Y42: 0.13125 | Z42: 0.12884615 | AB42: -0.018783212 | AC42: 0.0088757396 | AD42: -0.12718204 | AE42: 0.17667845 | AF42: -0.092896175 | AG42: -0.43978495 | AH42: 0.044642857 | AI42: 0.013452915 | AJ42: -0.3125 | AK42: 0.11297071 | AL42: 0.059097255 | AM42: 0.14516854 | AN42: -0.054822633 | AO42: 0.034013605 | AP42: 0.1147541 | AR42: -0.17508333 | AS42: -0.43708609 | AT42: -0.17954071 | AU42: 0.21383648 | AV42: -0.30707071 | AW42: 0.19980119 | AX42: -0.072023518 | AY42: -0.18991098 | AZ42: 0.37826685 | BA42: 0.1294964 | BB42: -0.19197708 | BC42: -0.018181818 | BD42: -0.059354839 | BE42: -0.10126582 | BF42: 0.43678161 | BG42: 0.15757576 | BH42: 0.10830173 | BJ42: -0.24285714 | BK42: -0.13 | BL42: 0.0051150895 | BM42: 0.15966387 | BO42: 0.059050064 | BP42: -0.21493902 | BQ42: 0.064414768 | BR42: -0.0023041475 | BS42: -0.023373342 | BT42: -0.0093457944 | BV42: 0.25775194 | BW42: 0.052028717 | BX42: 0.012143337 | BZ42: -0.072950692 | CA42: 0.14131179 | CB42: -0.071705964 | CC42: -0.030768889 | CD42: -0.013888889 | CE42: -0.01656051 | CF42: -0.21654501 | CJ42: -0.0757428 | CK42: -0.068997607 | CL42: -0.068497914 | CN42: -0.19317477 | CO42: 0.3 | CP42: 0.027777778 | CQ42: -0.12015504 | CR42: 0.056223968 | CS42: -0.20036765 | CT42: -0.020325203 | CU42: -0.053072626 | CV42: 0.056938926 | CW42: 0.097257277 | CX42: -0.092837534 | CY42: -0.11557789 | CZ42: -0.0057694916 | DA42: 0.062150838 | DB42: -0.015452539 | DC42: 0.079235505 | DD42: 0.0027548209 | DE42: 0.97536946 | DF42: -0.01119403 | DG42: 0.038834951 | DI42: 0.06504065 | DJ42: -0.19112628 | DK42: -0.10358891 | DL42: -0.017953321 | DM42: -0.17271835 | DN42: 0 | DP42: 0.13662316 | DQ42: -0.16964286 | DR42: 0.0093457944 | DS42: 0.020958084 | DU42: 0.21804095 | DW42: -0.17485714 | DX42: 0.47401247 | DY42: -0.072072072 | DZ42: 0.62179487 | EA42: -0.033333333 | EB42: -0.11864407 | EC42: -0.0041841004 | ED42: -0.051377283 | EE42: -0.014563107 | EF42: 0.058823529 | EG42: 0.012131716 | EH42: -0.17592593 | EI42: 0.055109765 | EJ42: 0.12957317 | EK42: 0.13414634 | EL42: -0.0038167939 | EM42: 0.035714286 | EN42: 0.094599913 | EO42: -0.043137255
A43: 2023 | B43: 8 | C43: -0.016252093 | D43: 0.0049630877 | E43: -0.24214792 | F43: -0.45420561 | H43: -0.5 | I43: -0.080597015 | J43: -0.12160158 | K43: 0.278125 | L43: 0.29166667 | M43: 0.22530923 | O43: 0.85221675 | P43: -0.25114155 | Q43: -0.015544041 | R43: 0.14118123 | S43: 0.033809524 | T43: -0.42355009 | U43: -0.23630137 | V43: -0.041843972 | W43: -0.020408163 | X43: 0.029692876 | Y43: -0.060773481 | Z43: -0.26235094 | AB43: -0.008684014 | AC43: -0.27565982 | AD43: -0.12854286 | AE43: -0.22822823 | AF43: -0.06626506 | AG43: 0.23243762 | AH43: -0.22222222 | AI43: -0.24336283 | AJ43: -0.063636364 | AK43: 0.12781955 | AL43: 0.028998243 | AM43: 0.28453689 | AN43: -0.50372208 | AO43: 0.085526316 | AP43: -0.07918552 | AR43: -0.078492777 | AS43: -0.094117647 | AT43: -0.083567698 | AU43: 0.10880829 | AV43: -0.10787172 | AW43: 0.010770505 | AX43: -0.17529039 | AY43: -0.20879121 | AZ43: -0.012974052 | BA43: 0.01910828 | BB43: 0.59574468 | BC43: -0.23395062 | BD43: -0.14266118 | BE43: -0.11267606 | BF43: -0.2072 | BG43: 0.44764398 | BH43: -0.19163498 | BJ43: -0.062893082 | BK43: -0.16858238 | BL43: 0.024879842 | BM43: -0.3129529 | BO43: 0.047878788 | BP43: -0.099029126 | BQ43: -0.05904059 | BR43: -0.07852194 | BS43: -0.10219922 | BT43: -0.16981132 | BV43: -0.40677966 | BW43: 0.099217911 | BX43: -0.028011102 | BZ43: -0.16459732 | CA43: 0.25962807 | CB43: -0.01733154 | CC43: 0.22178852 | CD43: -0.20523139 | CE43: -0.11010363 | CF43: 0.080745342 | CJ43: 0.021847006 | CK43: -0.17920891 | CL43: 0.11048899 | CN43: -0.2435273 | CO43: -0.17692308 | CP43: -0.11351351 | CQ43: -0.16740088 | CR43: 0.011554434 | CS43: -0.2045977 | CT43: -0.012448133 | CU43: -0.032448378 | CV43: -0.036606421 | CW43: -0.10550529 | CX43: -0.028885832 | CY43: -0.28636364 | CZ43: -0.018858143 | DA43: -0.0539119 | DB43: -0.053811659 | DC43: -0.037309302 | DD43: -0.41208791 | DE43: -0.36408978 | DF43: -0.11320755 | DG43: -0.11214953 | DI43: 0.29007634 | DJ43: -0.17510549 | DK43: -0.045950864 | DL43: -0.47531993 | DM43: -0.088967972 | DN43: 0.19322034 | DP43: -0.20034733 | DQ43: -0.37849462 | DR43: -0.19212963 | DS43: 0.037471489 | DU43: -0.20445252 | DW43: -0.2700831 | DX43: -0.1438646 | DY43: 0 | DZ43: 0.16996047 | EA43: -0.3437931 | EB43: -0.24423077 | EC43: -0.071428571 | ED43: -0.16313214 | EE43: -0.066502463 | EF43: -0.17460317 | EG43: -0.22089041 | EH43: -0.033707865 | EI43: 0.0320296 | EJ43: -0.095816464 | EK43: -0.064516129 | EL43: -0.1302682 | EM43: -0.20682759 | EN43: 0.012866026 | EO43: 0.038934426
A44: 2023 | B44: 9 | C44: -0.047393126 | D44: 0.0039864487 | E44: -0.084224599 | F44: -0.36531963 | H44: -0.12340426 | I44: -0.15074212 | J44: -0.13731007 | K44: 0.031784841 | L44: 0.094982079 | M44: -0.098307191 | O44: 0.069148936 | P44: -0.067073171 | Q44: -0.23157895 | R44: -0.30379298 | S44: -0.0023030861 | T44: -0.2195122 | U44: -0.094170404 | V44: -0.23760178 | W44: -0.10714286 | X44: -0.13502475 | Y44: 0.58823529 | Z44: 0.012702079 | AB44: -0.058556004 | AC44: 0.036437247 | AD44: -0.12806138 | AE44: -0.3463035 | AF44: -0.070967742 | AG44: 0.10418938 | AH44: -0.044065934 | AI44: -0.33333333 | AJ44: 0.46601942 | AK44: -0.37666667 | AL44: -0.045687447 | AM44: -0.16758326 | AN44: -0.075 | AO44: 0.14545455 | AP44: -0.090909091 | AR44: -0.24972594 | AS44: -0.11675325 | AT44: -0.32514979 | AU44: 0.28037383 | AV44: -0.18627451 | AW44: -0.078688525 | AX44: -0.12548015 | AY44: 0.10185185 | AZ44: -0.075834176 | BA44: -0.3875 | BB44: -0.073333333 | BC44: 0.11200645 | BD44: -0.0832 | BE44: -0.12169312 | BF44: -0.19374369 | BG44: -0.19710669 | BH44: -0.054562559 | BJ44: -0.33020134 | BK44: -0.29940092 | BL44: -0.096 | BM44: -0.052735662 | BO44: 0.039039907 | BP44: -0.066810345 | BQ44: 0.018823529 | BR44: -0.160401 | BS44: -0.061779539 | BT44: -0.089772727 | BV44: -0.32467532 | BW44: -0.097098214 | BX44: -0.036677469 | BZ44: 0.14018879 | CA44: -0.047623583 | CB44: -0.088946328 | CC44: -0.030801059 | CD44: -0.24556962 | CE44: -0.077147016 | CF44: 0.12356322 | CJ44: -0.048959975 | CK44: -0.217119 | CL44: 0.0010084034 | CN44: -0.11894273 | CO44: -0.20560748 | CP44: -0.18292683 | CQ44: -0.16931217 | CR44: -0.20947225 | CS44: -0.15606936 | CT44: 0.033613445 | CU44: -0.20426829 | CV44: -0.076403067 | CW44: -0.019543974 | CX44: -0.13087819 | CY44: -0.20318471 | CZ44: -0.062463884 | DA44: -0.27936067 | DB44: 0.027251185 | DC44: -0.087144038 | DD44: 0.021028037 | DE44: -0.32160784 | DF44: -0.13617021 | DG44: -0.42763158 | DI44: -0.11242604 | DJ44: 0.24808184 | DK44: -0.20648546 | DL44: -0.51219512 | DM44: -0.072916667 | DN44: -0.35227273 | DP44: 0.14377788 | DQ44: -0.2733564 | DR44: -0.11530086 | DS44: -0.13410804 | DT44: -0.47139081 | DU44: 0.014848658 | DW44: -0.045540797 | DX44: 0.052718287 | DY44: -0.4368932 | DZ44: -0.19256757 | EA44: -0.37782449 | EB44: -0.094910941 | EC44: -0.013574661 | ED44: -0.076023392 | EE44: -0.20316623 | EF44: -0.30865385 | EG44: -0.14615385 | EH44: -0.069883721 | EI44: -0.082797867 | EJ44: 0.036716418 | EK44: -0.071264368 | EL44: -0.18061674 | EM44: -0.10007825 | EN44: -0.086767035 | EO44: -0.049309665
A45: 2023 | B45: 10 | C45: -0.021708729 | D45: 0.0043121661 | E45: -0.2729927 | F45: -0.30573042 | H45: -0.2223301 | I45: -0.10922993 | J45: -0.015655577 | K45: -0.082938389 | L45: -0.27986907 | M45: 0.063382708 | O45: -0.10323383 | P45: 0.026143791 | Q45: -0.15410959 | R45: -0.17922607 | S45: 0.0027700831 | T45: -0.16015625 | U45: -0.22772277 | V45: -0.042718447 | W45: 0.083333333 | X45: -0.10888539 | Y45: 0.011888889 | Z45: -0.4640821 | AB45: -0.10319344 | AC45: 0.041015625 | AD45: -0.17277684 | AE45: -0.23214286 | AF45: -0.22222222 | AG45: -0.39351199 | AH45: -0.16703069 | AI45: 0.81578947 | AJ45: -0.29801325 | AK45: -0.085561497 | AL45: -0.02639821 | AM45: 0.030647825 | AN45: -0.37702703 | AO45: 0.047619048 | AP45: -0.059459459 | AR45: 0.099649328 | AS45: -0.35156595 | AT45: -0.073191858 | AU45: 0.23722628 | AV45: 0.10441767 | AW45: -0.21619217 | AX45: -0.092972182 | AY45: -0.26470588 | AZ45: -0.16849015 | BA45: -0.15428571 | BB45: 0.011990408 | BC45: -0.15942029 | BD45: 0.11692845 | BE45: -0.21686747 | BF45: -0.2465582 | BG45: -0.18018018 | BH45: -0.27263682 | BJ45: -0.064128257 | BK45: -0.20081563 | BL45: -0.28166005 | BM45: -0.0024356298 | BO45: -0.16532146 | BP45: -0.069284065 | BQ45: -0.044649731 | BR45: -0.14925373 | BS45: -0.044730275 | BT45: -0.18414482 | BV45: 0.33076923 | BW45: -0.018695921 | BX45: -0.047575746 | BZ45: 0.039281311 | CA45: 0.38013801 | CB45: -0.12733645 | CC45: 0.031277393 | CD45: -0.1442953 | CE45: 0.02681388 | CF45: -0.24040921 | CI45: -0.5827957 | CJ45: -0.0024289068 | CK45: -0.21555556 | CL45: -0.21255876 | CN45: 0.25 | CO45: -0.11764706 | CP45: -0.28089552 | CQ45: -0.092356688 | CR45: -0.1480431 | CS45: -0.59246575 | CT45: -0.081300813 | CU45: -0.29885057 | CV45: -0.14487236 | CW45: 0.037943696 | CX45: -0.078878748 | CY45: 0.4028777 | CZ45: -0.078685682 | DA45: -0.10318226 | DB45: -0.15397924 | DC45: -0.13489758 | DD45: 0.004576659 | DE45: -0.17336262 | DF45: -0.068965517 | DG45: -0.098850575 | DI45: -0.0033333333 | DJ45: -0.038934426 | DK45: 0.2109375 | DL45: 0.33571429 | DM45: -0.24859551 | DN45: -0.17105263 | DP45: -0.028562679 | DQ45: -0.28571429 | DR45: -0.78883275 | DS45: -0.13492927 | DT45: -0.22567568 | DU45: -0.19864941 | DW45: 0.045725646 | DX45: 0.0015649452 | DY45: -0.10344828 | DZ45: -0.24686192 | EA45: -0.28209459 | EB45: -0.10036548 | EC45: -0.18348624 | ED45: -0.15506329 | EE45: -0.29470199 | EF45: 0.25577191 | EG45: -0.052767053 | EH45: -0.068633579 | EI45: -0.097353661 | EJ45: -0.58479701 | EK45: -0.2450495 | EL45: -0.016129032 | EM45: -0.42985507 | EN45: -0.095442141 | EO45: -0.070539419
A46: 2023 | B46: 11 | C46: 0.091343986 | D46: 0.0046781398 | E46: -0.82435743 | F46: 0.13471503 | H46: 0.31086142 | I46: -0.13182097 | J46: 0.24409101 | K46: 0.11369509 | L46: 0.036363636 | M46: -0.19322967 | O46: 0.2184466 | P46: 0.43312102 | Q46: 0.11740891 | R46: 0.36290323 | S46: 0 | T46: -0.5255814 | U46: -0.076923077 | V46: 0.1703854 | W46: -0.08 | X46: 0.083012203 | Y46: -0.16181692 | Z46: -0.28804255 | AB46: -0.041725139 | AC46: -0.063789869 | AD46: 0.88636364 | AE46: -0.25046512 | AF46: -0.0089285714 | AG46: -0.27093023 | AH46: 0.39387248 | AI46: 0.0048309179 | AJ46: -0.19811321 | AK46: 0.11111111 | AL46: 0.17784926 | AM46: -0.092948718 | AN46: 0.22668113 | AO46: -0.17171717 | AP46: -0.066091954 | AR46: 0.024315706 | AS46: 0.0430839 | AT46: -0.18224299 | AU46: 0.25958702 | AV46: -0.77454545 | AW46: 0.33711691 | AX46: -0.091202583 | AY46: -0.15428571 | AZ46: 0.24605263 | BA46: 0.60472973 | BB46: -0.16113744 | BC46: 0.11853448 | BD46: -0.05 | BE46: 0.092307692 | BF46: 0.03820598 | BG46: 0.31868132 | BH46: -0.14637483 | BJ46: -0.31049251 | BK46: -0.0781893 | BL46: 0.23449448 | BM46: -0.35612138 | BO46: 0.057019006 | BP46: -0.64019851 | BQ46: 0.11603546 | BR46: 0.070175439 | BS46: 0.23331994 | BT46: 1.8768171 | BV46: 0.022543353 | BW46: -0.069201701 | BX46: 0.050880864 | BZ46: -0.12322034 | CA46: 0.086956522 | CB46: 0.11512718 | CC46: 0.068967775 | CD46: -0.054901961 | CE46: 0.09984639 | CF46: 0.11447811 | CI46: 0.82989691 | CJ46: -0.0021421545 | CK46: -0.14929178 | CL46: 0.044776119 | CM46: 0.12179487 | CN46: 0.058461538 | CO46: 0.12444444 | CP46: 0.28684101 | CQ46: -0.12982456 | CR46: -0.21534344 | CS46: 0.84033613 | CT46: 0.10619469 | CU46: 0.21311475 | CV46: -0.1109175 | CW46: -0.033861186 | CX46: -0.03467799 | CY46: 0.82336182 | CZ46: 0.010829124 | DA46: -0.2483871 | DB46: -0.053169734 | DC46: 0.11190486 | DD46: 0.15489749 | DE46: 0.11888112 | DF46: 0.08994709 | DG46: 0.010204082 | DI46: -0.17391304 | DJ46: -0.18336887 | DK46: 0.033746898 | DL46: -0.3315508 | DM46: 0.01682243 | DN46: -0.11111111 | DP46: 0.064710704 | DQ46: -0.73333333 | DR46: 0.082208589 | DS46: 0.14255765 | DT46: 0.082024433 | DU46: 0.16081461 | DW46: -0.1539924 | DX46: 0.328125 | DY46: 0.41346154 | DZ46: 0.0055555556 | EA46: -0.34117647 | EB46: 0.0765625 | EC46: -0.36797753 | ED46: -0.1505618 | EE46: 0.21126761 | EF46: 0.057813711 | EG46: 0 | EH46: -0.4633557 | EI46: 0.044660101 | EJ46: -0.85020804 | EK46: 0.085245902 | EL46: 0.016393443 | EM46: 0.18607016 | EN46: 0.12528663 | EO46: 0.0625
A47: 2023 | B47: 12 | C47: 0.045662306 | D47: 0.0042783112 | E47: 0.20041157 | F47: -0.15068493 | H47: 0.32142857 | I47: 0.039548023 | J47: 0.09818892 | K47: 0.40835267 | L47: 0.061403509 | M47: 0.10700663 | O47: 0.16619237 | P47: -0.10222222 | Q47: 0.014492754 | R47: 0.87346381 | S47: 0.0027624309 | T47: 0.049019608 | U47: 0.6875 | V47: 0.22357019 | W47: 0.02006689 | X47: 0.17998517 | Y47: 0.24017467 | Z47: -0.17219533 | AB47: 0.039086239 | AC47: -0.01002004 | AD47: -0.31084337 | AE47: -0.23156479 | AF47: 0.66666667 | AG47: 0.22009569 | AH47: 0.15841584 | AI47: -0.38942308 | AJ47: 0.32941176 | AK47: -0.093578947 | AL47: 0.2009364 | AM47: 0.27522576 | AN47: 0.069849691 | AO47: 0.0925 | AP47: 0.15692308 | AR47: -0.018679466 | AS47: 0.60847826 | AT47: -0.11714286 | AU47: 0.34894614 | AV47: -0.048387097 | AW47: 0.26485569 | AX47: 0.22912966 | AY47: -0.12162162 | AZ47: 0.11193242 | BA47: 1.2481203 | BB47: 0.23728814 | BC47: -0.19052023 | BD47: 0.79934211 | BE47: 0.46478873 | BF47: 2.6976 | BG47: 0.40625 | BH47: -0.070512821 | BJ47: 0.0062111801 | BK47: 0.28571429 | BL47: 0.11149346 | BM47: 0.21343445 | BO47: -0.11640379 | BP47: 0.35862069 | BQ47: 0.15812274 | BR47: -0.013114754 | BS47: 0.16701972 | BT47: 0.04787234 | BV47: -0.57207462 | BW47: 0.04034509 | BX47: 0.013448964 | BZ47: 0.0098588827 | CA47: -0.16666667 | CB47: 0.22483279 | CC47: -0.013738363 | CD47: 0.15767635 | CE47: 0.6801676 | CF47: 0.58308157 | CI47: -0.70422535 | CJ47: 0.071553687 | CK47: -0.32067932 | CL47: 0.15306122 | CM47: 0.39183673 | CN47: 0.3372093 | CO47: -0.083003953 | CP47: 0.21774194 | CQ47: 0.7983871 | CR47: 0.27385048 | CS47: 0.49315068 | CT47: 0.032 | CU47: 0.040540541 | CV47: 0.20750145 | CW47: 0.067480384 | CX47: 0.23680352 | CY47: -0.4771875 | CZ47: -0.055136949 | DA47: 0.30615165 | DB47: 0.30381569 | DC47: 0.056465122 | DD47: -0.10848126 | DE47: -0.11875 | DF47: -0.097087379 | DG47: 0.67676768 | DI47: 0.67611336 | DJ47: 0.34464752 | DK47: 0.080652904 | DL47: 0.632 | DM47: 0.15257353 | DN47: 0.32738095 | DP47: 0.031306751 | DQ47: 0.32291667 | DR47: 0.022675737 | DS47: 0.062018349 | DT47: 0.64516129 | DU47: 0.22504537 | DW47: 0.45842697 | DX47: 0.29058824 | DY47: 0 | DZ47: 0.27071823 | EA47: -0.076071429 | EB47: 0.082148041 | EC47: 0.19111111 | ED47: 0.21252205 | EE47: -0.12790698 | EF47: -0.24615224 | EG47: 0.98913043 | EH47: -0.19934767 | EI47: 0.17974186 | EJ47: 0.14351852 | EK47: -0.29607251 | EL47: 0.26344086 | EM47: 0.48592656 | EN47: 0.1171681 | EO47: 0.37605042
A48: 2024 | B48: 1 | C48: 0.015926444 | D48: 0.0042681931 | E48: 0.1047619 | F48: -0.38704301 | H48: -0.039099099 | I48: 0.086956522 | J48: -0.13726758 | K48: -0.11861614 | L48: 0.064049587 | M48: 0.012332245 | O48: -0.058077111 | P48: 0.18316832 | Q48: 0 | R48: 0.008260447 | S48: 0.0018365473 | T48: -0.17514019 | U48: 0.30452675 | V48: 0.019121813 | W48: 0.36393443 | X48: 0.13117226 | Y48: -0.038732394 | Z48: -0.5198556 | AB48: -0.036572923 | AC48: -0.23279352 | AD48: 1.6013986 | AE48: -0.23876178 | AF48: 0.22702703 | AG48: -0.59477124 | AH48: 0.068376068 | AI48: -0.80472441 | AJ48: -0.097345133 | AK48: -0.076762281 | AL48: 0.070825211 | AM48: -0.35036946 | AN48: -0.23966942 | AO48: 0.16090863 | AP48: -0.21542553 | AR48: -0.17911434 | AS48: 1.4597919 | AT48: 0.051779935 | AU48: -0.15798611 | AV48: 0.37644068 | AW48: -0.010738255 | AX48: 0.13439306 | AY48: -0.42923077 | AZ48: 0.20512821 | BA48: -0.28428094 | BB48: 0.066210046 | BC48: -0.35256593 | BD48: 0.6297989 | BE48: -0.125 | BF48: 0.16529641 | BG48: 0.06962963 | BH48: 0.30862069 | BJ48: -0.41358025 | BK48: -0.055555556 | BL48: -0.023529412 | BM48: -0.14910714 | BO48: 0.03534452 | BP48: -0.31979695 | BQ48: 0.0099750623 | BR48: -0.12956811 | BS48: -0.059759844 | BT48: -0.21827411 | BU48: -0.25862069 | BV48: -0.31638045 | BW48: -0.0022764228 | BX48: 0.013780766 | BZ48: 0.057427259 | CA48: 0.192 | CB48: 0.023522823 | CC48: 0.10754472 | CD48: 0.39784946 | CE48: 0.06234414 | CF48: -0.13167939 | CI48: -0.1047619 | CJ48: 0.1078701 | CK48: -0.15882353 | CL48: -0.040176991 | CM48: -0.12609971 | CN48: -0.19565217 | CO48: 0.125 | CP48: 0.072847682 | CQ48: 0.089686099 | CR48: 0.1546459 | CS48: -0.0091743119 | CT48: -0.023255814 | CU48: 0.2965368 | CV48: -0.066493655 | CW48: 0.00522705 | CX48: -0.034084173 | CY48: -0.64734011 | CZ48: -0.045012211 | DA48: -0.26615553 | DB48: -0.010491441 | DC48: -0.0031059548 | DD48: 0.07300885 | DE48: -0.14184397 | DF48: -0.069892473 | DG48: 0.042168675 | DI48: -0.050724638 | DJ48: -0.24660194 | DK48: 0.063971568 | DL48: -0.19607843 | DM48: -0.2185008 | DN48: -0.076233184 | DP48: -0.12858401 | DQ48: -0.38188976 | DR48: 0.026053215 | DS48: -0.043538355 | DT48: -0.72509804 | DU48: 0.34518519 | DW48: -0.201849 | DX48: -0.20966272 | DY48: 0.41496599 | DZ48: -0.20434783 | EA48: -0.42017781 | EB48: -0.086641631 | EC48: 0.059701493 | ED48: -0.30181818 | EE48: 0.0044444444 | EF48: -0.32263889 | EG48: -0.22814208 | EH48: 0.030925259 | EI48: 0.086792747 | EJ48: -0.14574899 | EK48: -0.26609442 | EL48: 0.046808511 | EM48: -0.24442308 | EN48: -0.046279193 | EO48: -0.11603053
A49: 2024 | B49: 2 | C49: 0.052187033 | D49: 0.0044449673 | E49: 0.025862069 | F49: 0.78931673 | H49: 1.0438777 | I49: 0.178125 | J49: -0.12724888 | K49: 0.031775701 | L49: 0.05631068 | M49: 0.2122895 | O49: -0.84559585 | P49: 0.53556485 | Q49: 0.1 | R49: 0.10795181 | S49: 0.010082493 | T49: 0.0014729209 | U49: 0.21451104 | V49: -0.11188325 | W49: 0.036057692 | X49: -0.096079085 | Y49: 0.058608059 | Z49: -0.37015038 | AB49: 0.038468231 | AC49: 0.56992084 | AD49: -0.41129032 | AE49: 0.50318246 | AF49: -0.088105727 | AG49: -0.56612903 | AH49: 0.12 | AI49: 0.12096774 | AJ49: 0.11764706 | AK49: -0.10062893 | AL49: 0.11377427 | AM49: 0.11374408 | AN49: -0.20652174 | AO49: 0.024038462 | AP49: 0.2 | AR49: 0.23719807 | AS49: -0.61318681 | AT49: 0.76615385 | AU49: -0.18556701 | AV49: 0.23137545 | AW49: 0.078018996 | AX49: 0.017197452 | AY49: 0.9541779 | AZ49: 0.16863672 | BA49: 0.1728972 | BB49: -0.047109208 | BC49: -0.026617647 | BD49: -0.084127874 | BE49: 0.18956044 | BF49: 0.010397326 | BG49: 0.41412742 | BH49: 0.16996047 | BJ49: 0.56315789 | BK49: -0.095588235 | BL49: 0.017755231 | BM49: 0.13588667 | BO49: 0.18827586 | BP49: 0.067164179 | BQ49: -0.056790123 | BR49: -0.032442748 | BS49: 0.032373032 | BT49: -0.19480519 | BU49: 0.57848837 | BV49: -0.42995169 | BW49: -0.031127771 | BX49: 0.023327067 | BZ49: 0.21469949 | CA49: 1.3154362 | CB49: 0.085499316 | CC49: 0.16939598 | CD49: -0.023076923 | CE49: 0.10798122 | CF49: 0.15604396 | CI49: 0.069148936 | CJ49: 0.052741157 | CK49: -0.1486014 | CL49: 0.30923843 | CM49: 0.18322148 | CN49: -0.02972973 | CO49: -0.030651341 | CP49: 0.15432099 | CQ49: 1.0699588 | CR49: 0.061470697 | CS49: 0.38888889 | CT49: 0.41269841 | CU49: 0.098497496 | CV49: 0.19611177 | CW49: 0.13064673 | CX49: -0.088063823 | CY49: 0.042372881 | CZ49: -0.019203389 | DA49: 0.59701493 | DB49: -0.11439732 | DC49: -0.1814201 | DD49: -0.078350515 | DE49: 0.4214876 | DF49: 0.15028902 | DG49: 0.080924855 | DI49: 0.55852417 | DJ49: -0.018041237 | DK49: -0.040501044 | DL49: 0.38414634 | DM49: 0.22857143 | DN49: -0.21359223 | DP49: 0.067628712 | DQ49: 0.14585987 | DR49: -0.20583468 | DS49: 0.072976879 | DT49: -0.036019971 | DU49: 0.4030837 | DW49: 0.41312741 | DX49: 0.16955017 | DY49: 0.30769231 | DZ49: -0.054644809 | EA49: -0.23777778 | EB49: 0.15859031 | EC49: 1.056338 | ED49: 0.30208333 | EE49: 0.061946903 | EF49: 0.24072176 | EG49: -0.067256637 | EH49: -0.075151515 | EI49: 0.050978004 | EJ49: 2.3554502 | EK49: 0.30409357 | EL49: 0.25 | EM49: -0.14609315 | EN49: 0.056014138 | EO49: 0.16407599
A50: 2024 | B50: 3 | C50: 0.032723786 | D50: 0.0041014948 | E50: 0.042016807 | F50: -0.34803922 | H50: 1.412844 | I50: -0.84933687 | J50: -0.057118317 | K50: 0.097826087 | L50: 0.055147059 | M50: 0.021575292 | O50: 0.090604027 | P50: 0.16076294 | Q50: -0.038961039 | R50: -0.10221836 | S50: -0.00045372051 | T50: 0.085303767 | U50: -0.28831169 | V50: 0.32159624 | W50: -0.062645012 | X50: -0.01941509 | Y50: 0.051903114 | Z50: 0.83836696 | AB50: 0.068571783 | AC50: -0.025210084 | AD50: -0.050228311 | AE50: 0.070336391 | AF50: -0.12077295 | AG50: -0.18215613 | AH50: 0.092857143 | AI50: 0.30215827 | AJ50: 0.21052632 | AK50: -0.020979021 | AL50: 0.057477527 | AM50: 0.071914894 | AN50: 0.016712329 | AO50: -0.21126761 | AP50: 0.19774011 | AR50: 0.16790316 | AS50: -0.13352273 | AT50: -0.14599303 | AU50: -0.06835443 | AV50: 0.21 | AW50: 0.024543738 | AX50: 0.1014402 | AY50: -0.31034483 | AZ50: -0.055967633 | BA50: 0.067729084 | BB50: -0.15730337 | BC50: -0.078410636 | BD50: 0.11696265 | BE50: -0.54457275 | BF50: -0.24035281 | BG50: -0.075416259 | BH50: 0.20045045 | BJ50: -0.16161616 | BK50: 0.23577236 | BL50: 0.046105919 | BM50: 0.2221709 | BO50: 0.16076611 | BP50: -0.006993007 | BQ50: -0.002617801 | BR50: -0.20710059 | BS50: -0.0046029919 | BT50: 0.24193548 | BU50: -0.3388582 | BV50: 0.52372881 | BW50: 0.012783852 | BX50: -0.019766732 | BZ50: 0.052160954 | CA50: 0.052173913 | CB50: -0.078764965 | CC50: 0.032215228 | CD50: 0.3648294 | CE50: 0.041666667 | CF50: 0.18250951 | CI50: 0.094527363 | CJ50: 0.044380957 | CK50: -0.28338711 | CL50: 0.31577465 | CM50: -0.22007941 | CN50: 0.31448468 | CO50: 0.78656126 | CP50: 0.94652406 | CQ50: -0.095427435 | CR50: 0.079840136 | CS50: -0.23333333 | CT50: -0.17977528 | CU50: -0.11246201 | CV50: 0.009073265 | CW50: 0.042828399 | CX50: -0.016823688 | CY50: -0.038617886 | CZ50: 0.044805426 | DA50: -0.0074766355 | DB50: -0.061121613 | DC50: 0.23721224 | DD50: 0.44742729 | DE50: -0.13953488 | DF50: -0.12060302 | DG50: -0.1684492 | DI50: -0.24081633 | DJ50: -0.0078740157 | DK50: -0.11705831 | DL50: -0.29955947 | DM50: -0.16611296 | DN50: -0.092592593 | DP50: 0.76106322 | DQ50: -0.24124514 | DR50: 0.13129252 | DS50: 0.14848485 | DT50: -0.034406215 | DU50: -0.048927263 | DW50: -0.10382514 | DX50: -0.069033531 | DY50: -0.24264706 | DZ50: 0.42774566 | EA50: -0.303207 | EB50: 0.28010139 | EC50: 0.18150685 | ED50: -0.045333333 | EE50: -0.045833333 | EF50: 0.15699884 | EG50: 0.12333966 | EH50: 0.39619921 | EI50: -0.025309336 | EJ50: -0.22316384 | EK50: 0.37668161 | EL50: -0.28130081 | EM50: 0.38599106 | EN50: -0.14682636 | EO50: -0.13946588
A51: 2024 | B51: 4 | C51: -0.040319558 | D51: 0.0043180243 | E51: -0.024193548 | F51: 0.27819549 | H51: 0.38022814 | I51: -0.36267606 | J51: -0.060578456 | K51: -0.001650165 | L51: 0.010452962 | M51: -0.045277014 | N51: 0.010423453 | O51: -0.26153846 | P51: -0.21126761 | Q51: -0.070608108 | R51: -0.23037791 | S51: 0.012256015 | T51: -0.077348066 | U51: -0.2810219 | V51: 0.075192422 | W51: -0.084158416 | X51: -0.075689223 | Y51: -0.075657895 | Z51: 0.19480519 | AB51: -0.18028785 | AC51: -0.05 | AD51: 0.37740385 | AE51: -0.17373626 | AF51: 0.049450549 | AG51: -0.16622727 | AH51: -0.17647059 | AI51: -0.41616022 | AJ51: -0.025797101 | AK51: 0.10714286 | AL51: -0.048686244 | AM51: -0.074235808 | AN51: -0.17272972 | AO51: -0.047619048 | AP51: 0.23938679 | AR51: -0.16828263 | AS51: -0.27868852 | AT51: -0.37270502 | AU51: 0.0027173913 | AV51: -0.20694215 | AW51: -0.19164619 | AX51: -0.011370097 | AY51: -0.06 | AZ51: -0.15928571 | BA51: -0.26492537 | BB51: -0.066666667 | BC51: -0.26229508 | BD51: -0.016447368 | BE51: -0.23833671 | BF51: -0.14852443 | BG51: -0.24470339 | BH51: 0.028142589 | BJ51: -0.45180723 | BK51: -0.20065789 | BL51: -0.079511614 | BM51: -0.2297808 | BO51: 0.355 | BP51: -0.070422535 | BQ51: -0.0085301837 | BR51: -0.21144279 | BS51: 0.037716763 | BT51: -0.0064935065 | BU51: -0.19498607 | BV51: 1.3882091 | BW51: -0.080302275 | BX51: -0.085972812 | BZ51: -0.28810198 | CA51: -0.14876033 | CB51: -0.043912449 | CC51: 0.0040362404 | CD51: -0.11153846 | CE51: -0.12881356 | CF51: -0.17041801 | CI51: -0.22736364 | CJ51: -0.020689623 | CK51: -0.22825019 | CL51: 0.56283451 | CM51: -0.33890909 | CN51: -0.453274 | CO51: -0.23451327 | CP51: -0.17857143 | CQ51: -0.47912088 | CR51: -0.010105762 | CS51: -0.086956522 | CT51: -0.43767123 | CU51: -0.20547945 | CV51: 0.29157267 | CW51: -0.011025358 | CX51: -0.10164271 | CY51: -0.078224101 | CZ51: -0.076757903 | DA51: -0.14971751 | DB51: -0.20671141 | DC51: 0.014599908 | DD51: -0.28748068 | DE51: -0.54324324 | DF51: 0.085771429 | DG51: 1.0514469 | DI51: -0.2172043 | DJ51: -0.19047619 | DK51: 0.091670774 | DL51: -0.46339623 | DM51: -0.10956175 | DN51: 0.14965986 | DP51: 0.025700935 | DQ51: 0.11326007 | DR51: -0.044497895 | DS51: -0.11756083 | DT51: -0.11954023 | DU51: -0.13535076 | DV51: 0.28543689 | DW51: -0.23018293 | DX51: 0.18008475 | DY51: 0 | DZ51: 0 | EA51: 0.28870293 | EB51: -0.34653465 | EC51: -0.15072464 | ED51: -0.063547486 | EE51: -0.1790393 | EF51: 0.92829596 | EG51: 0.17652027 | EH51: -0.37810945 | EI51: -0.030993723 | EJ51: -0.32 | EK51: -0.17915309 | EL51: -0.2081448 | EM51: 0.1827957 | EN51: -0.056265369 | EO51: -0.21034483
A52: 2024 | B52: 5 | C52: 0.050579598 | D52: 0.0045670367 | E52: -0.14876033 | F52: -0.14705882 | H52: -0.15151515 | I52: -0.049723757 | J52: 0.026181818 | K52: 0.10413223 | L52: -0.29310345 | M52: -0.016666667 | N52: -0.22888459 | O52: -0.17083333 | P52: -0.14285714 | Q52: -0.003998546 | R52: 0.043122443 | S52: 0.0089686099 | T52: 0.1239408 | U52: 0.32994924 | V52: -0.12169604 | W52: -0.0081081081 | X52: -0.0044739696 | Y52: 0.12099644 | Z52: -0.44021739 | AB52: -0.064862286 | AC52: 0.20871143 | AD52: -0.0087260035 | AE52: -0.13632132 | AF52: 0.020942408 | AG52: -0.23567573 | AH52: 0.11111111 | AI52: 0.022947717 | AJ52: 0.47277596 | AK52: 0.4516129 | AL52: -0.10262659 | AM52: 0.29373928 | AN52: -0.036156352 | AO52: -0.075 | AP52: 0.0028544244 | AR52: -0.065389254 | AS52: 0.071136364 | AT52: 0.33333333 | AU52: 0.056910569 | AV52: 0.7819925 | AW52: 0.34346505 | AX52: 0.29787234 | AY52: -0.17021277 | AZ52: 0.09855565 | BA52: 0.096446701 | BB52: 0.014285714 | BC52: 0.055555556 | BD52: -0.045150502 | BE52: 0.075898802 | BF52: -0.39147727 | BG52: 0.10098177 | BH52: 0.28558394 | BJ52: -0.076923077 | BK52: -0.037037037 | BL52: -0.048851504 | BM52: 0.76153091 | BO52: -0.10147601 | BP52: 0.34090909 | BQ52: 0.045003309 | BR52: 0.059936909 | BS52: -0.063640162 | BT52: -0.019607843 | BU52: -0.020761246 | BV52: -0.67241112 | BW52: -0.0496614 | BX52: 0.022701005 | BZ52: -0.019100676 | CA52: 0.25889968 | CB52: 0.21691229 | CC52: 0.051971656 | CD52: 0.4978355 | CE52: 0.0015564202 | CF52: -0.93643411 | CI52: -0.037298506 | CJ52: -0.028478098 | CK52: 0.21640736 | CL52: -0.13013699 | CM52: 0.089108911 | CN52: 0.47674419 | CO52: 0.57514451 | CP52: 0.036789298 | CQ52: 0.20253165 | CR52: 0.16187711 | CS52: 0.066666667 | CT52: 0.31546894 | CU52: -0.060344828 | CV52: 0.055688337 | CW52: -0.10381828 | CX52: 0.15542857 | CY52: -0.32110092 | CZ52: 0.13533077 | DA52: 0.043189369 | DB52: 0.026226734 | DC52: -0.14862153 | DD52: 0.11713666 | DE52: -0.091420118 | DF52: -0.015841272 | DG52: -0.13793103 | DI52: -0.17582418 | DJ52: -0.55228758 | DK52: -0.0054176072 | DL52: 0.26582278 | DM52: -0.12527964 | DN52: 0.42899408 | DP52: -0.14806378 | DQ52: -0.013687813 | DR52: 0.28823159 | DS52: -0.099003322 | DT52: 0.27067015 | DU52: 0.048679605 | DV52: -0.086102719 | DW52: 0.19009901 | DX52: 0.19479354 | DY52: 0 | DZ52: -0.27125506 | EA52: -0.3961039 | EB52: -0.13030303 | EC52: -0.12286689 | ED52: -0.029052946 | EE52: 0.18085106 | EF52: -0.25185185 | EG52: 0.2218234 | EH52: -0.73584906 | EI52: -0.073389694 | EJ52: 0.27807487 | EK52: 0.0079365079 | EL52: 0.28857143 | EM52: -0.39636364 | EN52: 0.064807794 | EO52: 0.015283843
A53: 2024 | B53: 6 | C53: 0.035284796 | D53: 0.0039931494 | E53: 0.067961165 | F53: -0.20689655 | H53: -0.27272727 | I53: 0.10465116 | J53: -0.055043704 | K53: -0.049401198 | L53: 0.33170732 | M53: -0.018798151 | N53: -0.10618729 | O53: 0.08040201 | P53: -0.097222222 | Q53: -0.02189781 | R53: -0.1967411 | S53: 0.0017777778 | T53: 0.2464817 | U53: 0.011450382 | V53: -0.1184953 | W53: -0.098092643 | X53: 0.096282173 | Y53: -0.073015873 | Z53: -0.12815534 | AB53: 0.010707476 | AC53: 0.12162162 | AD53: -0.3028169 | AE53: -0.60271019 | AF53: -0.14871795 | AG53: -0.54350927 | AH53: -0.071428571 | AI53: -0.85383904 | AJ53: 0.012626263 | AK53: 0.035555556 | AL53: -0.028364514 | AM53: 0.07689758 | AN53: -0.16018925 | AO53: 0.033783784 | AP53: -0.17836812 | AQ53: 0.14947781 | AR53: -0.16315412 | AS53: -0.002758328 | AT53: -0.1802439 | AU53: 0.44615385 | AV53: -0.24561404 | AW53: -0.18382353 | AX53: 0.035445281 | AY53: -0.19717949 | AZ53: -0.1608662 | BA53: 0.027777778 | BB53: -0.073239437 | BC53: 0.11368421 | BD53: 0.051371862 | BE53: -0.26472772 | BF53: -0.18767507 | BG53: -0.21019108 | BH53: -0.17246274 | BJ53: -0.19039683 | BK53: -0.22282051 | BL53: 0.026190476 | BM53: 0.1637883 | BO53: -0.10924025 | BP53: -0.06779661 | BQ53: 0.038632046 | BR53: -0.089285714 | BS53: 0.018590125 | BT53: -0.23666667 | BU53: 0.038869258 | BV53: -0.15165877 | BW53: 0.014061758 | BX53: -0.0034776563 | BZ53: -0.053414469 | CA53: -0.28534704 | CB53: -0.0092886537 | CC53: 0.10366427 | CD53: 0.19075145 | CE53: -0.067599068 | CF53: -0.15640244 | CI53: -0.22146175 | CJ53: -0.0079047332 | CK53: -0.35755814 | CL53: -0.023622047 | CM53: -0.0070707071 | CN53: -0.35958005 | CO53: -0.0091743119 | CP53: -0.058064516 | CQ53: 0.2 | CR53: -0.029538298 | CS53: 0.20833333 | CT53: -0.037037037 | CU53: 0.17889908 | CV53: -0.042185495 | CW53: 0.070595553 | CX53: -0.056709529 | CY53: 0.51351351 | CZ53: -0.023728145 | DA53: 0.093418259 | DB53: -0.11376752 | DC53: -0.067199383 | DD53: -0.18834951 | DE53: -0.25512862 | DF53: 0.032085561 | DG53: -0.30909091 | DI53: 0 | DJ53: -0.065693431 | DK53: -0.43940082 | DL53: 0.78703704 | DM53: 0.11253197 | DN53: -0.17184265 | DP53: 0.014705882 | DQ53: -0.23138511 | DR53: 0.036638984 | DS53: -0.013643068 | DT53: -0.13390411 | DU53: -0.17536408 | DV53: -0.20495868 | DW53: 0.13311148 | DX53: -0.023290759 | DY53: -0.13592233 | DZ53: -0.077777778 | EA53: -0.010752688 | EB53: -0.221777 | EC53: 0.15953307 | ED53: -0.14441953 | EE53: -0.27477477 | EF53: -0.1670297 | EG53: -0.14336075 | EH53: -0.261 | EI53: 0.002823786 | EJ53: -0.5167364 | EK53: -0.22440945 | EL53: -0.0022172949 | EM53: -0.11144578 | EN53: 0.022411116 | EO53: 0.053763441
A54: 2024 | B54: 7 | C54: 0.012109035 | D54: 0.0045089999 | E54: 0.21818182 | F54: -0.095652174 | H54: -0.26339286 | I54: 0.084210526 | J54: 0.088 | K54: 0.15433071 | L54: -0.12087912 | M54: 0.032035176 | N54: 0.0084190833 | O54: 0.18604651 | P54: 0.47692308 | Q54: 0.0073880597 | R54: 0.033433509 | S54: -0.0017657498 | T54: 0.12096774 | U54: 0.20377358 | V54: 0.16216216 | W54: 0.15407855 | X54: 0.084596273 | Y54: -0.092465753 | Z54: 0.33619154 | AB54: 0.16252108 | AC54: 0.061579652 | AD54: 0.17929293 | AE54: 0.34922481 | AF54: -0.39759036 | AG54: 0.1034375 | AH54: -0.12307692 | AI54: -0.79949367 | AJ54: 0.077306733 | AK54: -0.18025751 | AL54: 0.19782609 | AM54: 0.19021237 | AN54: -0.21126761 | AO54: -0.065359477 | AP54: 0.057736721 | AQ54: 0.1391255 | AR54: 0.550454 | AS54: -0.076382979 | AT54: -0.15079837 | AU54: -0.015957447 | AV54: 0.26356589 | AW54: -0.096327096 | AX54: 0.1287976 | AY54: -0.24960077 | AZ54: 0.14470046 | BA54: 0.040540541 | BB54: 0.094224924 | BC54: -0.2436673 | BD54: -0.054414214 | BE54: 1.1040229 | BF54: 0.13563218 | BG54: 0.49677419 | BH54: 0.063464837 | BJ54: -0.23262425 | BK54: -0.24425382 | BL54: 0.12230693 | BM54: 0.23408329 | BO54: 0.051636699 | BP54: 0.018181818 | BQ54: 0.14878049 | BR54: 0.30065359 | BS54: 0.14936487 | BT54: 0.043668122 | BU54: -0.35034014 | BV54: -0.65642458 | BW54: 0.032980418 | BX54: 0.079980835 | BZ54: 0.10238095 | CA54: 0.47122302 | CB54: 0.29349632 | CC54: -0.11167683 | CD54: -0.36771845 | CE54: -0.0058333333 | CF54: 0.17600289 | CI54: 2.2967033 | CJ54: -0.086187557 | CK54: -0.72773756 | CL54: 0.080645161 | CM54: 0.30824008 | CN54: -0.06147541 | CO54: 0.11296296 | CP54: 0.31164384 | CQ54: 0.23684211 | CR54: 0.056040502 | CS54: 0.32758621 | CT54: 0.0096153846 | CU54: -0.0077821012 | CV54: 0.12582123 | CW54: 0.028467683 | CX54: -0.2782244 | CY54: -0.0625 | CZ54: 0.10639452 | DA54: 0.14757282 | DB54: 0.33116279 | DC54: 0.10085584 | DD54: -0.26794258 | DE54: -0.11256831 | DF54: 0.12435233 | DG54: -0.25526316 | DI54: 0.22 | DJ54: -0.0859375 | DK54: 0.79919028 | DL54: -0.1761658 | DM54: 0.15632184 | DN54: 0.065 | DP54: 0.31488801 | DQ54: -0.20052083 | DR54: 0.7200754 | DS54: 0.11476636 | DT54: -0.41676552 | DU54: -0.10632818 | DV54: -0.24948025 | DW54: 0.13803231 | DX54: -0.066153846 | DY54: 0.11247191 | DZ54: 0.22289157 | EA54: 0.10326087 | EB54: -0.11327513 | EC54: 0.067114094 | ED54: 0.046678636 | EE54: 0.086956522 | EF54: 0.11280162 | EG54: -0.096021948 | EH54: 1.3583994 | EI54: 0.13452893 | EJ54: 0.0043290043 | EK54: -0.035532995 | EL54: 0.10222222 | EM54: -0.017118644 | EN54: 0.041035876 | EO54: 0.3244898
A55: 2024 | B55: 8 | C55: 0.02336552 | D55: 0.0046191297 | E55: -0.11940299 | F55: -0.056730769 | G55: 0.032520325 | H55: 0.46060606 | I55: 0.077669903 | J55: 0.11994485 | K55: 0.18144611 | L55: -0.2 | M55: -0.029975654 | N55: 0.18831169 | O55: -0.55686275 | P55: 0.1796875 | Q55: -0.036965701 | R55: -0.049073064 | S55: -0.0017866508 | T55: -0.15107914 | U55: -0.031347962 | V55: -0.071603427 | W55: 0.0078534031 | X55: 0.017752835 | Y55: -0.056603774 | Z55: -0.091590966 | AB55: 0.050252542 | AC55: -0.20807062 | AD55: -0.10706638 | AE55: 0.034185579 | AF55: -0.2886 | AG55: 0.86207873 | AH55: -0.11403509 | AI55: -0.50378788 | AJ55: 0.13888889 | AK55: -0.057591623 | AL55: -0.0028519575 | AM55: -0.08714766 | AN55: 0.030102041 | AO55: -0.055944056 | AP55: 0.36244541 | AQ55: -0.028414756 | AR55: -0.37016575 | AS55: 0.1694694 | AT55: 0.045255474 | AU55: -0.1027027 | AV55: -0.09202454 | AW55: 0.18634969 | AX55: -0.17058378 | AY55: 0.079804214 | AZ55: 0.27938808 | BA55: -0.20779221 | BB55: 0.27777778 | BC55: -0.10647338 | BD55: 0.10099824 | BE55: -0.55992 | BF55: -0.094129555 | BG55: -0.078663793 | BH55: -0.15322581 | BJ55: 0.070516096 | BK55: 0.009749709 | BL55: 0.06261075 | BM55: 0.56943367 | BO55: -0.21174923 | BP55: 0.017857143 | BQ55: 0.02866242 | BR55: -0.37688442 | BS55: -0.069105691 | BT55: -0.012552301 | BU55: -0.078534031 | BV55: -0.073170732 | BW55: 0.051972789 | BX55: 0.058740203 | BZ55: -0.20086393 | CA55: -0.04400978 | CB55: -0.02926874 | CC55: 0.19531956 | CD55: -0.29558541 | CE55: -0.20284996 | CF55: -0.011370621 | CI55: -0.080952381 | CJ55: 0.047025258 | CK55: -0.19112515 | CL55: -0.044776119 | CM55: -0.10575428 | CN55: -0.18340611 | CO55: -0.32113145 | CP55: -0.15926893 | CQ55: 0.042553191 | CR55: 0.0364821 | CS55: -0.21892393 | CT55: -0.0095238095 | CU55: -0.062745098 | CV55: 0.11228709 | CW55: 0.054088406 | CX55: -0.2464891 | CY55: -0.34285714 | CZ55: -0.050098209 | DA55: 0.39763113 | DB55: -0.071278826 | DC55: 0.039122895 | DD55: -0.12091503 | DE55: -0.18054187 | DF55: -0.046082949 | DG55: 0.13074205 | DH55: -0.042693662 | DI55: -0.23497268 | DJ55: -0.042735043 | DK55: 0.29207921 | DL55: -0.27672956 | DM55: 0.011928429 | DN55: -0.31455399 | DP55: -0.095190381 | DQ55: -0.31596091 | DR55: -0.54794521 | DS55: 0.17907445 | DT55: -0.24293785 | DU55: 0.11609716 | DV55: 0.45152355 | DW55: -0.016774194 | DX55: -0.048599671 | DY55: 0.05039895 | DZ55: -0.15763547 | EA55: -0.16748768 | EB55: -0.064630144 | EC55: -0.0062893082 | ED55: 0.051457976 | EE55: 0.077142857 | EF55: -0.12582781 | EG55: -0.64339909 | EH55: -0.33180328 | EI55: 0.011879087 | EJ55: -0.038793103 | EK55: -0.042105263 | EL55: 0.13306452 | EM55: -0.061907225 | EN55: 0.019162168 | EO55: 0.17873652
A56: 2024 | B56: 9 | C56: 0.021009193 | D56: 0.0042208867 | E56: -0.025423729 | F56: 0.018348624 | G56: -0.15905512 | H56: -0.26556017 | I56: 0.45945946 | J56: -0.0043085761 | K56: -0.03926097 | L56: 0.0052083333 | M56: -0.064156863 | N56: -0.1069477 | O56: -0.053097345 | P56: 0.099337748 | Q56: -0.13830769 | R56: -0.058486239 | S56: 0.087266251 | T56: 0 | U56: -0.85566343 | V56: -0.13546473 | W56: -0.12987013 | X56: 0.011366194 | Y56: -0.06 | Z56: 0.22018349 | AB56: 0.035837438 | AC56: -0.11146497 | AD56: 0.06235012 | AE56: -0.14444444 | AF56: -0.34129885 | AG56: -0.36121673 | AH56: 0.25742574 | AI56: -0.16984733 | AJ56: -0.20325203 | AK56: -0.022222222 | AL56: 0.0046801872 | AM56: 0.31104816 | AN56: 0.17038138 | AO56: -0.051851852 | AP56: 0.29487179 | AQ56: -0.017957927 | AR56: -0.12175439 | AS56: 0.79251477 | AT56: -0.094972067 | AU56: 0.13453815 | AV56: -0.094594595 | AW56: -0.050420168 | AX56: 0.16727605 | AY56: -0.065825778 | AZ56: 0.019509125 | BA56: -0.098360656 | BB56: 0.30434783 | BC56: 0.10955711 | BD56: 0.42346667 | BE56: -0.060898019 | BF56: -0.10726257 | BG56: -0.58245614 | BH56: -0.36285714 | BJ56: -0.20047733 | BK56: 0.26819426 | BL56: 0.11172874 | BM56: 0.11122096 | BO56: 0.18715239 | BP56: 0.011695906 | BQ56: -0.0036119711 | BR56: 0.056451613 | BS56: -0.0015010917 | BT56: -0.076271186 | BU56: 0.13068182 | BV56: 0.18421053 | BW56: -0.039403345 | BX56: -0.022910724 | BZ56: -0.010810811 | CA56: -0.21994885 | CB56: -0.053969754 | CC56: -0.077165051 | CD56: 0.22343324 | CE56: 0.051524711 | CF56: -0.20111906 | CI56: -0.32642487 | CJ56: -0.035024454 | CK56: 0.41586193 | CL56: 0.015625 | CM56: 0.14869565 | CN56: -0.096256684 | CO56: 0.48284314 | CP56: -0.28881988 | CQ56: -0.013605442 | CR56: -0.14407196 | CS56: -0.057007126 | CT56: -0.35576923 | CU56: 0.020920502 | CV56: 0.078929792 | CW56: -0.034030011 | CX56: -0.03277635 | CY56: -0.0072463768 | CZ56: -0.0024129831 | DA56: 0.094430993 | DB56: -0.15650865 | DC56: -0.098624633 | DD56: -0.10037175 | DE56: 0.073038774 | DF56: 0.033816425 | DG56: -0.325 | DH56: -0.058390805 | DI56: 0.15714286 | DJ56: 0.28571429 | DK56: 0.02507837 | DL56: -0.196 | DM56: -0.10412574 | DN56: 0.020547945 | DP56: -0.25249169 | DQ56: -0.18095238 | DR56: -0.06969697 | DS56: -0.11319681 | DT56: -0.067164179 | DU56: 0.21320546 | DV56: 0.22519084 | DW56: 0.094488189 | DX56: 0.17316017 | DY56: -0.17634615 | DZ56: 0.029239766 | EA56: -0.041420118 | EB56: -0.36518219 | EC56: 0.056962025 | ED56: -0.14029364 | EE56: -0.1193634 | EF56: -0.060361681 | EG56: -0.38297872 | EH56: -0.14818449 | EI56: -0.038906557 | EJ56: -0.022421525 | EK56: 0.032967033 | EL56: 0.014234875 | EM56: -0.13602941 | EN56: 0.064798935 | EO56: -0.092810458
A57: 2024 | B57: 10 | C57: -0.0089235273 | D57: 0.0039502663 | E57: 0.57391304 | F57: 0.001001001 | G57: 0.059925094 | H57: 0.40112994 | I57: 0.66666667 | J57: 0.041211622 | K57: 0.018028846 | L57: -0.025906736 | M57: -0.040479383 | N57: -0.65996503 | O57: 0.0093457944 | P57: 0.10240964 | Q57: 0.030083914 | R57: 0.073081608 | S57: -0.063063063 | T57: -0.12711864 | U57: -0.040134529 | V57: 0.17956538 | W57: -0.032835821 | X57: -0.0093468343 | Y57: -0.18297872 | Z57: -0.07518797 | AB57: 0.08987421 | AC57: -0.086021505 | AD57: -0.16478555 | AE57: 0.0077922078 | AF57: 0.0074690568 | AG57: -0.1984127 | AH57: -0.19685039 | AI57: -0.14482759 | AJ57: 0.1122449 | AK57: 0.0056818182 | AL57: -0.11645963 | AM57: 0.05812446 | AN57: 0.093948371 | AO57: -0.125 | AP57: 0.24443069 | AQ57: -0.12434692 | AR57: -0.25549341 | AS57: 0.24249084 | AT57: 0.30555556 | AU57: 0.017699115 | AV57: -0.014925373 | AW57: -0.13955071 | AX57: 0.090446359 | AY57: 0.053164557 | AZ57: 0.0074074074 | BA57: 0.23636364 | BB57: 0.41166667 | BC57: 0.2289916 | BD57: 0.25777445 | BE57: -0.050716221 | BF57: 0.4718398 | BG57: -0.11484594 | BH57: 0.21076233 | BJ57: -0.016343284 | BK57: -0.034090909 | BL57: -0.19675 | BM57: 0.0022241993 | BO57: -0.086671352 | BP57: -0.011560694 | BQ57: 0.01294666 | BR57: -0.083969466 | BS57: 0.15826158 | BT57: 0.18348624 | BU57: 0.14070352 | BV57: -0.22222222 | BW57: -0.01238668 | BX57: -0.013575449 | BZ57: -0.010928962 | CA57: -0.29508197 | CB57: 0.056049555 | CC57: -0.063435379 | CD57: 0.23385301 | CE57: 0.085 | CF57: 0.069649805 | CI57: 0.68461538 | CJ57: -0.098978725 | CK57: 0.039036424 | CL57: -0.084615385 | CM57: -0.1332324 | CN57: -0.18934911 | CO57: 0.023140496 | CP57: -0.034934498 | CQ57: 0.21034483 | CR57: -0.018298401 | CS57: 0.017632242 | CT57: 0.029850746 | CU57: -0.024590164 | CV57: 0.026646091 | CW57: 0.022884882 | CX57: 0.10299003 | CY57: -0.15693431 | CZ57: -0.022115433 | DA57: -0.051438053 | DB57: 0.25512935 | DC57: -0.02287419 | DD57: -0.053719008 | DE57: 0.036414566 | DF57: 0.028037383 | DG57: 0.060185185 | DH57: 0.19775391 | DI57: 0.074074074 | DJ57: -0.22222222 | DK57: -0.12317363 | DL57: 0.038611291 | DM57: -0.089912281 | DN57: -0.087248322 | DP57: 0.06962963 | DQ57: 0.085271318 | DR57: -0.12703583 | DS57: 0.09268762 | DT57: -0.3832 | DU57: 0.35269079 | DV57: -0.36760125 | DW57: -0.17745803 | DX57: 0.017712177 | DY57: 0.095727294 | DZ57: -0.068181818 | EA57: -0.12345679 | EB57: -0.14285714 | EC57: -0.11826347 | ED57: -0.24288425 | EE57: -0.06626506 | EF57: -0.017815345 | EG57: -0.034482759 | EH57: 0.055587558 | EI57: -0.00086243312 | EJ57: -0.0091743119 | EK57: 0.44680851 | EL57: 0.12982456 | EM57: 0.085106383 | EN57: -0.082751416 | EO57: 0.17435159
A58: 2024 | B58: 11 | C58: 0.059633474 | D58: 0.0037005926 | E58: 1.2486188 | F58: 0 | G58: -0.1819788 | H58: -0.068548387 | I58: 0.025925926 | J58: -0.10567979 | K58: -0.023612751 | L58: -0.23404255 | M58: -0.00026203162 | N58: 0.13367609 | O58: 0.5462963 | P58: -0.072859745 | Q58: -0.090042465 | R58: 0.01097238 | S58: 0.0048076923 | T58: -0.029126214 | U58: 0.53001635 | V58: -0.28506787 | W58: 0.055555556 | X58: 0.10322363 | Y58: -0.16145833 | Z58: -0.26829268 | AA58: -0.20338983 | AB58: 0.061861239 | AC58: 0.29607843 | AD58: -0.067567568 | AE58: -0.020618557 | AF58: -0.14848549 | AG58: 0.079207921 | AH58: 0.029411765 | AI58: 0.0035842294 | AJ58: -0.30275229 | AK58: 0.16949153 | AL58: -0.1066198 | AM58: 0.177864 | AN58: -0.22630561 | AO58: 0.25 | AP58: -0.019393337 | AQ58: -0.11038186 | AR58: -0.64368124 | AS58: -0.10436321 | AT58: -0.19030733 | AU58: 0.0052173913 | AV58: -0.33333333 | AW58: 0.045094937 | AX58: -0.12459605 | AY58: -0.33894231 | AZ58: -0.16115196 | BA58: 0.37254902 | BB58: 0.5974026 | BC58: -0.24273504 | BD58: -0.016979446 | BE58: -0.79812398 | BF58: -0.24744898 | BG58: 0.21835443 | BH58: 0.10246914 | BJ58: 0.013580153 | BK58: -0.011764706 | BL58: 0.079053844 | BM58: -0.069906791 | BN58: 0.29777778 | BO58: -0.051038728 | BP58: 0.011695906 | BQ58: -0.029141104 | BR58: -0.075 | BS58: 0.010619469 | BT58: 0.56589147 | BU58: -0.21585903 | BV58: -0.0095238095 | BW58: 0.10506226 | BX58: -0.022557246 | BZ58: -0.099447514 | CA58: -0.03255814 | CB58: 0.14919584 | CC58: -0.039776834 | CD58: -0.18050542 | CE58: 0.064516129 | CF58: -0.24699891 | CH58: -0.11179039 | CI58: -0.4109589 | CJ58: -0.0066455747 | CK58: -0.16201117 | CL58: -0.042016807 | CM58: -0.13187773 | CN58: -0.04379562 | CO58: -0.22455574 | CP58: 0.31221719 | CQ58: -0.060778727 | CR58: -0.13976292 | CS58: 1.8094059 | CT58: -0.27536232 | CU58: -0.0042016807 | CV58: 0.015952845 | CW58: 0.14942373 | CX58: 0.018674699 | CY58: 0.00086580087 | CZ58: -0.059295228 | DA58: -0.48279883 | DB58: -0.019189765 | DC58: 0.12430489 | DD58: -0.66375546 | DE58: -0.25945946 | DF58: 2.0181818 | DG58: -0.11790393 | DH58: -0.06889523 | DI58: -0.13218391 | DJ58: 0.10714286 | DK58: -0.85119163 | DL58: -0.32937624 | DM58: -0.12771084 | DN58: 0.0073529412 | DP58: 0.0083102493 | DQ58: -0.19642857 | DR58: 0.041044776 | DS58: 0.073378339 | DT58: 0.37483787 | DU58: 0.17891661 | DV58: -0.019704433 | DW58: -0.090379009 | DX58: -0.074691806 | DY58: -0.24355423 | DZ58: -0.18292683 | EA58: -0.20422535 | EB58: -0.091269841 | EC58: -0.022071307 | ED58: -0.052631579 | EE58: -0.083870968 | EF58: -0.059976168 | EG58: -0.085714286 | EH58: -0.37107776 | EI58: 0.13857523 | EJ58: 0.24074074 | EK58: 0.088235294 | EL58: 0.01863354 | EM58: -0.033333333 | EN58: -0.019744962 | EO58: 0.14478528
A59: 2024 | B59: 12 | C59: -0.02409975 | D59: 0.0040230304 | E59: -0.39066339 | F59: 0.01 | G59: -0.1511879 | H59: 1.012987 | I59: -0.31768953 | J59: -0.17835804 | K59: -0.042321644 | L59: 0.16666667 | M59: -0.034073039 | N59: -0.040816327 | O59: -0.17365269 | P59: -0.30058939 | Q59: 0.0095238095 | R59: -0.28255988 | S59: 0.00043497173 | T59: -0.1289 | U59: -0.10427481 | V59: -0.049728752 | W59: -0.020467836 | X59: -0.13856648 | Y59: 0.055900621 | Z59: 0.21111111 | AA59: -0.69202128 | AB59: -0.044917887 | AC59: -0.06505295 | AD59: 0.026086957 | AE59: 0.67763158 | AF59: 0.74452736 | AG59: 0.13073394 | AH59: -0.095238095 | AI59: 0.075 | AJ59: -0.30921053 | AK59: -0.024154589 | AL59: -0.060655738 | AM59: -0.12638696 | AN59: 0.1625 | AO59: 0.69285714 | AP59: -0.17849899 | AQ59: -0.017437961 | AR59: 0.20481928 | AS59: -0.046082949 | AT59: -0.089051095 | AU59: -0.32352941 | AV59: -0.14772727 | AW59: -0.08327025 | AX59: -0.077112387 | AY59: 0.086060606 | AZ59: -0.19357195 | BA59: -0.21428571 | BB59: -0.015521064 | BC59: -0.0022573363 | BD59: -0.19090909 | BE59: 0.47474747 | BF59: -0.15819209 | BG59: 0.22077922 | BH59: -0.21612542 | BI59: 0.11309524 | BJ59: -0.29625749 | BK59: -0.10940476 | BL59: -0.0074992789 | BM59: -0.19947507 | BN59: -0.50342466 | BO59: -0.091891892 | BP59: -0.052023121 | BQ59: -0.086361243 | BR59: 0.072072072 | BS59: -0.024868651 | BT59: -0.12376238 | BU59: 0.19101124 | BV59: -0.028846154 | BW59: 0.012830002 | BX59: -0.067028353 | BZ59: 0.012269939 | CA59: 0.0096153846 | CB59: -0.11788919 | CC59: -0.02935816 | CD59: 0.074889868 | CE59: 0.018181818 | CF59: -0.0028985507 | CH59: -0.093903638 | CI59: -0.11627907 | CJ59: -0.013329052 | CK59: 0.0016666667 | CL59: -0.18421053 | CM59: 0.06639839 | CN59: 0.67938931 | CO59: -0.01875 | CP59: -0.082758621 | CQ59: -0.13650152 | CR59: -0.059862522 | CS59: -0.12951542 | CT59: -0.10933333 | CU59: 0.021097046 | CV59: -0.10140938 | CW59: -0.078801463 | CX59: 0.11413365 | CY59: -0.23546713 | CZ59: 0.012208648 | DA59: -0.084554679 | DB59: -0.045652174 | DC59: -0.099157724 | DD59: -0.016753247 | DE59: 0.43759124 | DF59: 0.051204819 | DG59: -0.32178218 | DH59: -0.22329247 | DI59: -0.82781457 | DJ59: 0.45967742 | DK59: -0.38541667 | DL59: -0.3378882 | DM59: -0.022099448 | DN59: -0.11678832 | DO59: -0.094503756 | DP59: -0.17445055 | DQ59: 0.47111111 | DR59: -0.035842294 | DS59: -0.011211375 | DT59: 0.21698113 | DU59: 0.055672069 | DV59: 0.035175879 | DW59: -0.11217949 | DX59: -0.19357367 | DY59: -0.26183099 | DZ59: -0.0074626866 | EA59: 0.017699115 | EB59: 0.93886463 | EC59: 0.43055556 | ED59: -0.13756614 | EE59: -0.3943662 | EF59: -0.083802817 | EG59: -0.453125 | EH59: -0.17592191 | EI59: -0.048891055 | EJ59: -0.18283582 | EK59: 0.13175676 | EL59: 0.033536585 | EM59: -0.23935091 | EN59: -0.07029935 | EO59: -0.10610932
A60: 2025 | B60: 1 | C60: 0.026856365 | D60: 0.0034993025 | E60: 0 | F60: -0.17821782 | G60: -0.048346056 | H60: 0.41935484 | I60: -0.034391534 | J60: -0.060867223 | K60: 0.042929293 | L60: -0.085892857 | M60: 0.060781476 | N60: 0.014184397 | O60: -0.17391304 | P60: -0.15168539 | Q60: 0.13207547 | R60: -0.081377152 | S60: 0.12521739 | T60: -0.078636207 | U60: -0.10465314 | V60: -0.24833492 | W60: -0.086567164 | X60: 0.25824371 | Y60: -0.020588235 | Z60: 0.036697248 | AA60: -0.20725389 | AB60: 0.053679567 | AC60: -0.1763754 | AD60: -0.27683616 | AE60: -0.20915033 | AF60: 0.030942535 | AG60: -0.077079108 | AH60: -0.021052632 | AI60: -0.21013289 | AJ60: -0.13019048 | AK60: -0.014851485 | AL60: 0.12111693 | AM60: 0.32804128 | AN60: -0.061075269 | AO60: -0.046413502 | AP60: 0.26790123 | AQ60: -0.33174061 | AR60: -0.3275 | AS60: 0.36438923 | AT60: 0.041666667 | AU60: 0.16368286 | AV60: 0.02 | AW60: -0.0066061107 | AX60: -0.028444444 | AY60: -0.61123512 | AZ60: 0.26539855 | BA60: -0.18636364 | BB60: 0.32732733 | BC60: 0.12441176 | BD60: 0.049438202 | BE60: -0.7630137 | BF60: 0.026845638 | BG60: -0.15744681 | BH60: 0.51428571 | BI60: -0.11764706 | BJ60: -0.61816635 | BK60: 0.68426681 | BL60: 0.12670735 | BM60: -0.084351714 | BN60: 0.20682759 | BO60: -0.048214286 | BP60: -0.097560976 | BQ60: 0.074351585 | BR60: -0.067226891 | BS60: 0.52155172 | BT60: -0.096045198 | BU60: -0.21226415 | BV60: -0.12435644 | BW60: 0.0099066179 | BX60: 0.052067963 | BZ60: 0.22121212 | CA60: -0.15714286 | CB60: 0.087727485 | CC60: 0.050621776 | CD60: -0.1147541 | CE60: 0.21003401 | CF60: -0.11434109 | CH60: -0.45686381 | CI60: 0.052631579 | CJ60: -0.0066344205 | CK60: 0.10732113 | CL60: -0.11043011 | CM60: -0.81792453 | CN60: 0.37272727 | CO60: 0.76008493 | CP60: -0.13157895 | CQ60: -0.098360656 | CR60: 0.042900055 | CS60: -0.12753036 | CT60: -0.11377246 | CU60: -0.074380165 | CV60: 0.038567203 | CW60: -0.016903573 | CX60: 0.39755839 | CY60: -0.26453949 | CZ60: 0.01609974 | DA60: -0.26231527 | DB60: -0.18375095 | DC60: -0.031115146 | DD60: -0.6522256 | DE60: -0.2899213 | DF60: 0.10315186 | DG60: 0.01459854 | DH60: -0.074971815 | DI60: -0.32884615 | DJ60: 0.044198895 | DK60: 0.0084745763 | DL60: -0.034005629 | DM60: -0.062146893 | DN60: -0.11570248 | DO60: -0.26157205 | DP60: -0.0049916805 | DQ60: -0.14501511 | DR60: 0 | DS60: 0.061117257 | DT60: -0.43697674 | DU60: -0.029077118 | DV60: 0.17961165 | DW60: -0.19494585 | DX60: -0.4888241 | DY60: 0.21160084 | DZ60: -0.21052632 | EA60: -0.23469565 | EB60: -0.18018018 | EC60: -0.04368932 | ED60: -0.0030674847 | EE60: 0.25581395 | EF60: -0.14573405 | EG60: -0.074857143 | EH60: -0.17846802 | EI60: -0.093975453 | EJ60: -0.082191781 | EK60: -0.29850746 | EL60: 0.050147493 | EM60: 0.52533333 | EN60: 0.05204709 | EO60: -0.059952038
A61: 2025 | B61: 2 | C61: -0.012694826 | D61: 0.0032347297 | E61: -0.19758065 | F61: -0.054216867 | G61: -0.37834225 | H61: -0.083333333 | I61: -0.10136986 | J61: -0.18468598 | K61: 0.049636804 | L61: -0.24464414 | M61: 0.05542292 | N61: -0.34731935 | O61: 0 | P61: -0.072847682 | Q61: -0.10833333 | R61: 0.0051107325 | S61: -0.88408037 | T61: -0.033266883 | U61: -0.21816105 | V61: 0.0012658228 | W61: -0.0098039216 | X61: 0.19800864 | Y61: -0.22522523 | Z61: -0.13690265 | AA61: 0.0087145969 | AB61: 0.011365564 | AC61: -0.14145383 | AD61: -0.1328125 | AE61: -0.012396694 | AF61: -0.37081604 | AG61: -0.094505495 | AH61: -0.075591398 | AI61: -0.48895899 | AJ61: -0.028139713 | AK61: -0.13065327 | AL61: -0.095579078 | AM61: -0.094739988 | AN61: -0.038479157 | AO61: 1.1504425 | AP61: 0.0087633885 | AQ61: -0.28089888 | AR61: -0.3866171 | AS61: -0.038947901 | AT61: -0.033846154 | AU61: 0.23736264 | AV61: 0.043137255 | AW61: -0.071487947 | AX61: -0.047118024 | AY61: 0.33971292 | AZ61: 0.044380816 | BA61: -0.05027933 | BB61: -0.11199095 | BC61: -0.062355379 | BD61: -0.066024268 | BE61: -0.38945087 | BF61: -0.18039216 | BG61: -0.093434343 | BH61: -0.044339623 | BI61: -0.081818182 | BJ61: -0.29805014 | BK61: -0.2731746 | BL61: -0.12690224 | BM61: -0.0859375 | BN61: -0.097091262 | BO61: -0.09318324 | BP61: -0.094594595 | BQ61: -0.038626609 | BR61: -0.072072072 | BS61: 0.0088133459 | BT61: -0.128125 | BU61: -0.23952096 | BV61: -0.30257802 | BW61: 0.15405644 | BX61: 0.093264716 | BY61: -0.36796117 | BZ61: -0.19354839 | CA61: -0.16949153 | CB61: 0.048734449 | CC61: 0.13708351 | CD61: -0.28935185 | CE61: 0.088545327 | CF61: 0.17067834 | CH61: -0.040959041 | CI61: -0.16666667 | CJ61: -0.066484185 | CK61: -0.090909091 | CL61: 0.015351142 | CM61: -0.19170984 | CN61: -0.24834437 | CO61: -0.12303981 | CP61: -0.14718615 | CQ61: -0.072727273 | CR61: -0.023984708 | CS61: -0.024361949 | CT61: -0.018581081 | CU61: -0.066964286 | CV61: 0.042642125 | CW61: 0.10394685 | CX61: -0.08659324 | CY61: -0.15538462 | CZ61: -0.0033936652 | DA61: -0.078464107 | DB61: -0.68 | DC61: 0.16419024 | DD61: 0.70451956 | DE61: -0.65033965 | DF61: 0.049350649 | DG61: 0.10071942 | DH61: -0.38878732 | DI61: -0.25501433 | DJ61: -0.23809524 | DK61: 0.0084033613 | DL61: -0.4270454 | DM61: -0.012048193 | DN61: -0.037383178 | DO61: -0.61738616 | DP61: -0.081939799 | DQ61: 0.024734982 | DR61: -0.15613383 | DS61: -0.16445139 | DT61: -0.50158337 | DU61: -0.17261905 | DV61: -0.17695473 | DW61: -0.17264574 | DX61: -0.34410646 | DY61: -0.11889764 | DZ61: -0.3 | EA61: -0.52494035 | EB61: -0.54532967 | EC61: 0.14720812 | ED61: 0.22461538 | EE61: -0.13888889 | EF61: -0.064783156 | EG61: 0.0023162446 | EH61: -0.2310157 | EI61: -0.18173494 | EJ61: -0.21393035 | EK61: 0.072340426 | EL61: 0.075842697 | EM61: -0.30454545 | EN61: -0.021416033 | EO61: 0.021683673

Sheet Excess Returns and Beta
A1: YEAR | B1: MONTH | C1: SPY | D1: TBILL | E1: ACRS | F1: ADIL | G1: ALMS | H1: ALTS | I1: AMLX | J1: AMPH | K1: AMRX | L1: ANEB | M1: ANIP | N1: ANRO | O1: ANTX | P1: AQST | Q1: ARTL | R1: ARVN | S1: ASBP | T1: ASRT | U1: ATHA | V1: AVDL | W1: AVIR | X1: AXSM | Y1: AYTU | Z1: BFRI | AA1: BIOA | AB1: BMY | AC1: BTMD | AD1: CALC | AE1: CARA | AF1: CGTX | AG1: CING | AH1: CLSD | AI1: CNSP | AJ1: CNTX | AK1: COCP | AL1: COLL | AM1: CORT | AN1: CPHI | AO1: CPIX | AP1: CRMD | AQ1: CTNM | AR1: CTXR | AS1: CVKD | AT1: DARE | AU1: DERM | AV1: DRRX | AW1: ELAN | AX1: ELVN | AY1: ENVB | AZ1: EOLS | BA1: ESPR | BB1: ETON | BC1: EVOK | BD1: EWTX | BE1: EYEN | BF1: EYPT | BG1: FULC | BH1: GHRS | BI1: GRCE | BJ1: HEPA | BK1: HOTH | BL1: HRMY | BM1: HROW | BN1: IBO | BO1: IGC | BP1: IKNA | BQ1: INVA | BR1: IRD | BS1: ITCI | BT1: ITRM | BU1: IXHL | BV1: JAGX | BW1: JAZZ | BX1: JNJ | BY1: JUNS | BZ1: KPRX | CA1: LEXX | CB1: LGND | CC1: LLY | CD1: LPCN | CE1: LQDA | CF1: LYRA | CG1: MAZE | CH1: MBX | CI1: MIRA | CJ1: MRK | CK1: NBY | CL1: NKTR | CM1: NMRA | CN1: NRXP | CO1: NTRB | CP1: NUVB | CQ1: OCUL | CR1: OGN | CS1: OMER | CT1: OPTN | CU1: ORMP | CV1: PAHC | CW1: PBH | CX1: PCRX | CY1: PCSA | CZ1: PFE | DA1: PHAT | DB1: PLRX | DC1: PRGO | DD1: PRPH | DE1: PTPI | DF1: PULM | DG1: RANI | DH1: RAPP | DI1: RLMD | DJ1: RVPH | DK1: SAVA | DL1: SCLX | DM1: SCPH | DN1: SCYX | DO1: SEPN | DP1: SIGA | DQ1: SNES | DR1: SNOA | DS1: SUPN | DT1: SXTP | DU1: TARS | DV1: TELO | DW1: TERN | DX1: THRD | DY1: TLPH | DZ1: TLRY | EA1: TNFA | EB1: TRAW | EC1: TRVI | ED1: TTNP | EE1: TXMD | EF1: VERU | EG1: VRCA | EH1: VRPX | EI1: VTRS | EJ1: VTYX | EK1: VYNE | EL1: XERS | EM1: YCBD | EN1: ZTS | EO1: ZVRA
A2: 2020 | B2: 3 | C2: -0.12464237 | D2: 0.0020473632 | E2: -0.087719298 | F2: -0.097222222 | H2: -0.36 | J2: -0.035737492 | K2: -0.096103896 | M2: -0.15142679 | P2: -0.41286863 | Q2: -0.10280374 | R2: -0.14491831 | T2: -0.39814815 | V2: -0.20520521 | X2: -0.24576923 | Y2: 1.8301887 | AB2: -0.056215219 | AE2: -0.12109115 | AH2: -0.24107143 | AI2: -0.43548387 | AK2: -0.46616541 | AL2: -0.31242105 | AM2: -0.057844691 | AN2: -0.12280702 | AO2: -0.099255583 | AP2: -0.30961538 | AR2: -0.15730337 | AT2: -0.22018349 | AV2: -0.12429379 | AW2: -0.18284672 | AY2: -0.163034 | AZ2: -0.51688009 | BA2: -0.3755199 | BB2: -0.24074074 | BC2: -0.056910569 | BE2: -0.41025641 | BF2: -0.20930233 | BG2: -0.36892178 | BJ2: -0.50558659 | BK2: -0.27021226 | BM2: -0.30797101 | BO2: 0.11363636 | BQ2: -0.12694878 | BR2: -0.22746781 | BS2: -0.27156398 | BT2: 0.12916667 | BV2: -0.15789474 | BW2: -0.1295165 | BX2: -0.024910801 | BZ2: -0.095652174 | CA2: -0.12121212 | CB2: -0.22307692 | CC2: 0.099818252 | CD2: -0.034205231 | CE2: 0.14043584 | CJ2: 0.012951052 | CK2: 0.052631579 | CL2: -0.14223931 | CN2: 0.011267606 | CO2: 0.50000583 | CQ2: 0.052072264 | CS2: 0.12258606 | CT2: -0.25785124 | CU2: -0.25490196 | CV2: -0.038269983 | CW2: -0.018201285 | CX2: -0.22706316 | CY2: 0.025641026 | CZ2: -0.023339184 | DA2: -0.28516058 | DC2: -0.051291715 | DD2: -0.025728383 | DF2: -0.36875 | DI2: -0.30073801 | DJ2: -0.0037878788 | DK2: -0.26737968 | DM2: -0.16384181 | DN2: -0.1673774 | DP2: -0.04400049 | DQ2: -0.37650602 | DR2: -0.070208729 | DS2: 0 | DY2: -0.10606061 | DZ2: -0.52321552 | EA2: -0.23201439 | EB2: -0.30232558 | EC2: -0.36608863 | ED2: -0.11538462 | EE2: -0.37278107 | EF2: -0.20823245 | EG2: -0.079191238 | EK2: -0.091525424 | EL2: -0.45224719 | EM2: -0.088235294 | EN2: -0.11664052 | EO2: -0.25742574
A3: 2020 | B3: 4 | C3: 0.12698322 | D3: -0.00019324052 | E3: 0.27884615 | F3: 0.13846154 | H3: 0.16517857 | J3: 0.14218329 | K3: 0.043103448 | M3: -0.017918508 | P3: 0.96803653 | Q3: 0.22916667 | R3: 0.30272953 | T3: 0.35384615 | V3: 0.30730479 | X3: 0.61533231 | Y3: 0.093333333 | AB3: 0.099850495 | AE3: 0.12187737 | AH3: 0.16470588 | AI3: 0.36666667 | AK3: 0.32394366 | AL3: 0.26638089 | AM3: 0.064760303 | AN3: -0.04 | AO3: 0.090909091 | AP3: 0.15598886 | AR3: 0.53166667 | AT3: 0.30588235 | AV3: 0.37419355 | AW3: 0.10361769 | AY3: -0.052083333 | AZ3: 0.0024096386 | BA3: 0.25594672 | BB3: 0.26341463 | BC3: 0.14655172 | BE3: 0.59130435 | BF3: -0.049019608 | BG3: 0.056951424 | BJ3: 0.056497175 | BK3: 0.16013072 | BM3: 0.17539267 | BO3: 0.10204082 | BQ3: 0.20578231 | BR3: 0.055555556 | BS3: 0.14964216 | BT3: 0.29151292 | BV3: -0.05 | BW3: 0.10537397 | BX3: 0.14420735 | BZ3: 0.0019230769 | CA3: 0 | CB3: 0.35547305 | CC3: 0.11476347 | CD3: 0.15416667 | CE3: 0.057324841 | CJ3: 0.031192157 | CK3: 0.53333333 | CL3: 0.075630252 | CN3: 0.10027855 | CO3: -0.2 | CQ3: 0.16363636 | CS3: 0.24308153 | CT3: -0.10022272 | CU3: 0.016447368 | CV3: 0.10508994 | CW3: 0.10932388 | CX3: 0.23143454 | CY3: -0.25 | CZ3: 0.1752481 | DA3: 0.31061193 | DC3: 0.10833905 | DD3: -0.11642349 | DF3: 0.36633663 | DI3: 0.23013779 | DJ3: 0.0085551331 | DK3: 0.85766423 | DM3: 0.27567568 | DN3: 0.23559539 | DP3: 0.23641026 | DQ3: 0.038647343 | DR3: 0.036734694 | DS3: 0.30072262 | DY3: 0.36440678 | DZ3: 0.17005814 | EA3: 0.6206089 | EB3: 0.033333333 | EC3: -0.12765957 | ED3: 0.13043478 | EE3: 0.49056604 | EF3: -0.012232416 | EG3: 0.10430009 | EK3: -0.32089552 | EL3: 0.38461538 | EM3: 0.035483871 | EN3: 0.10045752 | EO3: 0.33333333
A4: 2020 | B4: 5 | C4: 0.047645592 | D4: -0.00017111862 | E4: 0.060150376 | F4: 0.094594595 | H4: 0.21072797 | J4: 0.099705015 | K4: 0.3415978 | M4: -0.22369408 | P4: 0.12993039 | Q4: 0.084745763 | R4: -0.36628571 | T4: 0.125 | V4: -0.22157996 | X4: -0.18994002 | Y4: -0.091463415 | AB4: -0.017923128 | AE4: 0.070850202 | AH4: -0.060606061 | AI4: -0.073170732 | AK4: 0.031914894 | AL4: 0.066247582 | AM4: 0.19589258 | AN4: -0.0625 | AO4: -0.16414141 | AP4: 0.065060241 | AR4: -0.055495103 | AT4: -0.054054054 | AV4: 0.098591549 | AW4: -0.13354917 | AX4: 0.91371429 | AY4: 0.45054945 | AZ4: 0.098557692 | BA4: 0.069949495 | BB4: -0.11196911 | BC4: 0.85714286 | BE4: -0.21038251 | BF4: -0.11340206 | BG4: 0.57765452 | BJ4: -0.010695187 | BK4: -0.18591549 | BM4: 0.20489978 | BO4: 0.074074074 | BQ4: -0.014809591 | BR4: 0.32105263 | BS4: 0.18166384 | BT4: 0.20285714 | BV4: 0.059210526 | BW4: 0.082267574 | BX4: -0.0016618646 | BZ4: -0.021113244 | CA4: 0.034482759 | CB4: 0.030435224 | CC4: -0.0063077818 | CD4: 0.64981949 | CE4: 0.85542169 | CJ4: 0.017394236 | CK4: -0.076086957 | CL4: 0.13020833 | CN4: -0.065654008 | CO4: -0.14583738 | CQ4: 0.22222222 | CS4: -0.10469314 | CT4: 0.069306931 | CU4: 0.01618123 | CV4: -0.0190965 | CW4: 0.037109855 | CX4: 0.064422378 | CY4: 0.066666667 | CZ4: 0.0058041867 | DA4: 0.24940898 | DC4: 0.031779238 | DD4: -0.04790174 | DF4: 0.2173913 | DI4: 0.14895138 | DJ4: -0.0065975495 | DK4: -0.71971185 | DM4: -0.11758475 | DN4: -0.21865285 | DP4: 0.013542099 | DQ4: -0.11162791 | DR4: 0.90944882 | DS4: 0.030769231 | DY4: -0.13664596 | DZ4: 0.22360248 | EA4: -0.01734104 | EB4: 0.35483871 | EC4: -0.045296167 | ED4: 0.076923077 | EE4: -0.28481013 | EF4: 0.15479876 | EG4: -0.048881524 | EK4: 0.31318681 | EL4: 0.9037037 | EM4: 0.52647975 | EN4: 0.077952343 | EO4: -0.37333333
A5: 2020 | B5: 6 | C5: 0.017760594 | D5: 0 | E5: 0.14893617 | F5: -0.14197531 | H5: 0.012658228 | J5: 0.20493562 | K5: -0.022587269 | M5: 0.04121056 | P5: -0.0020533881 | Q5: -0.0546875 | R5: 0.0081154193 | T5: -0.13131313 | V5: 0 | X5: 0.068849052 | Y5: -0.046979866 | AB5: -0.015406399 | AE5: 0.077504726 | AH5: 0.010752688 | AI5: -0.19548872 | AK5: 0.56701031 | AL5: -0.20634921 | AM5: 0.11096433 | AN5: 0.48888889 | AO5: 0.0060422961 | AP5: 0.42533937 | AR5: 0.30184332 | AT5: -0.058095238 | AV5: -0.0085470085 | AW5: 0.0018682858 | AX5: -0.17497761 | AY5: 0.17424242 | AZ5: 0.15973742 | BA5: 0.21099835 | BB5: 0.18478261 | BC5: 0.43319838 | BE5: -0.017301038 | BF5: -0.11627907 | BG5: -0.081366148 | BJ5: 0.54594595 | BK5: -0.10726644 | BM5: -0.036968577 | BO5: 0.034482759 | BQ5: 0.00071581961 | BR5: 0.1314741 | BS5: 0.22940613 | BT5: -0.71733967 | BV5: 0.0041407867 | BW5: -0.075259806 | BX5: -0.054587914 | BZ5: -0.056862745 | CA5: -0.015666667 | CB5: 0.10121099 | CC5: 0.073422731 | CD5: 0.3785558 | CE5: -0.088744589 | CJ5: -0.034337446 | CK5: 0.35294118 | CL5: 0.067281106 | CN5: -0.05166185 | CO5: 0 | CQ5: 0.18323864 | CS5: -0.010752688 | CT5: 0.72222222 | CU5: 0.12420382 | CV5: 0.0073585706 | CW5: -0.10995261 | CX5: 0.19385666 | CY5: 0.125 | CZ5: -0.14375603 | DA5: -0.22161779 | DC5: 0.0091291706 | DD5: -0.094316634 | DF5: 0.023809524 | DI5: -0.071769342 | DJ5: 0.019924099 | DK5: 0.43925234 | DM5: -0.11644658 | DN5: -0.0039787798 | DP5: -0.013361161 | DQ5: 0.047120419 | DR5: -0.26597938 | DS5: -0.015339967 | DY5: -0.1294964 | DZ5: -0.27817259 | EA5: 0.023529412 | EB5: 0.35714286 | EC5: 1.4014599 | ED5: 0.10714286 | EE5: 0.10619469 | EF5: -0.10455764 | EG5: -0.040940767 | EK5: -0.27615063 | EL5: -0.48249027 | EM5: 0.29931973 | EN5: -0.016858777 | EO5: 0.52659574
A6: 2020 | B6: 7 | C6: 0.05889233 | D6: 0.00010958391 | E6: 0.32716049 | F6: 0.15827338 | H6: 0.23125 | J6: -0.10863758 | K6: -0.090336134 | M6: -0.084415584 | P6: 0.082304527 | Q6: -0.049586777 | R6: -0.060822898 | T6: 0.047209302 | V6: -0.030940594 | X6: -0.13308216 | Y6: -0.021126761 | AB6: 0.0052111106 | AE6: -0.038596491 | AH6: -0.12765957 | AI6: -0.13084112 | AK6: 0.11184211 | AL6: -0.098285714 | AM6: -0.11117717 | AN6: -0.28358209 | AO6: 0 | AP6: -0.29365079 | AR6: 0.14159292 | AT6: 0.1223458 | AV6: -0.15517241 | AW6: 0.1016317 | AX6: -0.26927253 | AY6: 0.19354839 | AZ6: -0.38490566 | BA6: -0.26661469 | BB6: 0.22568807 | BC6: 0.042372881 | BE6: 0.23943662 | BF6: -0.065789474 | BG6: -0.13231274 | BJ6: 0.41258741 | BK6: 0.058139535 | BM6: 0.051823417 | BO6: 0.016666667 | BQ6: -0.03111588 | BR6: -0.063380282 | BS6: -0.2276977 | BT6: -0.12605042 | BV6: 0.34804124 | BW6: -0.018941454 | BX6: 0.03647841 | BZ6: -0.15176715 | CA6: 0.34050119 | CB6: 0.047653107 | CC6: -0.084602135 | CD6: 0.22222222 | CE6: -0.3432304 | CF6: 0.18165785 | CJ6: 0.037629918 | CK6: 0.069565217 | CL6: -0.043177893 | CN6: 0.020952381 | CO6: -0.12194706 | CQ6: -0.058823529 | CS6: -0.12839674 | CT6: -0.31518817 | CU6: 0.039660057 | CV6: -0.1170508 | CW6: -0.0098509052 | CX6: 0.0026681913 | CY6: -0.055555556 | CZ6: 0.18830114 | DA6: 0.010635065 | DC6: -0.040707536 | DD6: 0.18746538 | DF6: -0.23255814 | DI6: -0.18726257 | DJ6: -0.0046511628 | DK6: 0.029220779 | DM6: 0.019021739 | DN6: -0.13715047 | DP6: 0.086291995 | DQ6: -0.1 | DR6: 0.28932584 | DS6: -0.062526316 | DY6: -0.099173554 | DZ6: 0.037974684 | EA6: 0.49137931 | EB6: 1.0175439 | EC6: -0.24468085 | ED6: -0.061290323 | EE6: 0.48 | EF6: -0.15269461 | EG6: -0.40417802 | EK6: -0.069364162 | EL6: 0.07518797 | EM6: 0.72774869 | EN6: 0.10837896 | EO6: 0.44947735
A7: 2020 | B7: 8 | C7: 0.069796715 | D7: 0 | E7: 0.14418605 | F7: -0.14285714 | H7: 0.7715736 | J7: 0.017982018 | K7: -0.050808314 | M7: 0.059101655 | P7: 0.49429658 | Q7: -0.16521739 | R7: -0.17619048 | T7: -0.1005996 | V7: -0.066411239 | X7: 0.027758306 | Y7: -0.23741007 | AB7: 0.06034649 | AE7: -0.057177616 | AH7: 0.048780488 | AI7: 0.15591398 | AK7: -0.37278107 | AL7: 0.20785805 | AM7: -0.15050167 | AN7: -0.18708333 | AO7: -0.033033033 | AP7: 0.049438202 | AR7: -0.27906977 | AT7: -0.027027027 | AV7: -0.11479592 | AW7: 0.22979264 | AX7: 0.15106488 | AY7: -0.31345946 | AZ7: 0.18404908 | BA7: -0.040659049 | BB7: 0.17365269 | BC7: 0.21138211 | BE7: -0.0028409091 | BF7: -0.24633803 | BG7: -0.54190296 | BJ7: -0.18069307 | BK7: -0.029304029 | BM7: 0.25729927 | BO7: 0.96721311 | BQ7: -0.13547434 | BR7: -0.14285714 | BS7: -0.080958386 | BT7: -0.25 | BV7: -0.38819211 | BW7: 0.24147806 | BX7: 0.059470549 | BZ7: -0.0049019608 | CA7: -0.12625153 | CB7: -0.12954429 | CC7: -0.0077861482 | CD7: -0.038961039 | CE7: -0.074141049 | CF7: -0.024626866 | CJ7: 0.062687631 | CK7: -0.26317073 | CL7: -0.12725632 | CN7: -0.0018656716 | CO7: 0.11110679 | CQ7: 0.10969388 | CS7: -0.068589244 | CT7: -0.10696762 | CU7: -0.049046322 | CV7: -0.07480313 | CW7: -0.020435601 | CX7: 0.18836723 | CY7: -0.076470588 | CZ7: -0.017932638 | DA7: 0.10523151 | DB7: 0.079862602 | DC7: -0.0093434772 | DD7: 0.60822338 | DF7: -0.18939394 | DI7: -0.01897168 | DJ7: -0.0046728972 | DK7: -0.0094637224 | DM7: 0.14133333 | DN7: -0.12808642 | DP7: 0.082549016 | DQ7: -0.20555556 | DR7: -0.19716776 | DS7: -0.012351224 | DY7: 0.14678899 | DZ7: -0.090785908 | EA7: -0.51445087 | EB7: -0.79069565 | EC7: -0.18913481 | ED7: -0.20687285 | EE7: -0.21081081 | EF7: -0.021201413 | EG7: 0.40091463 | EK7: -0.049689441 | EL7: 0.6451049 | EM7: -0.25151515 | EN7: 0.055510982 | EO7: 0.75456731
A8: 2020 | B8: 9 | C8: -0.037398487 | D8: -0.00021914381 | E8: 0.044715447 | F8: 0.61594203 | H8: -0.32091691 | J8: -0.079980373 | K8: -0.055961071 | M8: -0.10044643 | P8: -0.38231552 | Q8: 0.033958333 | R8: -0.09017341 | T8: -0.17814815 | V8: -0.31053352 | X8: -0.02809985 | Y8: 0.12264151 | AB8: -0.030706317 | AE8: -0.17903226 | AH8: -0.10465116 | AI8: -0.18139535 | AK8: -0.12301887 | AL8: 0.092339979 | AM8: 0.37047244 | AN8: -0.065094823 | AO8: -0.0031055901 | AP8: 0.29122056 | AR8: 0.11827957 | AT8: -0.075277778 | AV8: -0.014409222 | AW8: -0.038885065 | AX8: -0.12478485 | AY8: 0.08652862 | AZ8: 0.012953368 | BA8: 0.029639889 | BB8: 0.0076530612 | BC8: 0.049217002 | BE8: -0.11111111 | BF8: -0.031769763 | BG8: 0.090784044 | BJ8: -0.060422961 | BK8: -0.25660377 | BM8: -0.18867925 | BO8: -0.13333333 | BQ8: -0.10760034 | BR8: -0.087719298 | BS8: 0.40834248 | BT8: 0.34615385 | BV8: -0.27625 | BW8: 0.061016445 | BX8: -0.029529 | BZ8: -0.034482759 | CA8: -0.22659548 | CB8: -0.065490196 | CC8: -0.0024932063 | CD8: -0.047297297 | CE8: -0.0390625 | CF8: -0.14460597 | CJ8: -0.020157279 | CK8: -0.1945272 | CL8: -0.14219235 | CN8: 0.0028037383 | CO8: -0.39499551 | CQ8: -0.12528736 | CS8: -0.15439331 | CT8: -0.14285714 | CU8: -0.252149 | CV8: -0.18446669 | CW8: -0.00027449904 | CX8: -0.038387716 | CY8: 0.2611465 | CZ8: -0.028841595 | DA8: -0.0024483134 | DB8: -0.099403579 | DC8: -0.12218051 | DD8: 0.25815274 | DF8: 0.11214953 | DI8: 0.054372197 | DJ8: 0.0093896714 | DK8: 2.6656051 | DM8: -0.1296729 | DN8: -0.21946903 | DP8: -0.011515739 | DQ8: 0.31468531 | DR8: 0.13568521 | DS8: -0.052296498 | DY8: 0.136 | DZ8: -0.27719821 | EA8: -0.10714286 | EB8: 0.16327378 | EC8: 0 | ED8: -0.28336222 | EE8: 0.082191781 | EF8: -0.054151625 | EG8: -0.1577802 | EK8: 0.08496732 | EL8: 0.26036132 | EM8: -0.1902834 | EN8: 0.032917484 | EO8: -0.22660638
A9: 2020 | B9: 10 | C9: -0.024933396 | D9: 0.00010959592 | E9: 0.49416342 | F9: -0.21973094 | H9: -0.2278481 | J9: 0.0448 | K9: 0.072164948 | M9: -0.096419709 | P9: -0.0030895984 | Q9: -0.53878702 | R9: -0.11435832 | T9: -0.068649542 | V9: 0 | X9: -0.069333333 | Y9: -0.20142857 | AB9: -0.023227534 | AE9: 0.042043222 | AH9: -0.12337662 | AI9: -0.044545455 | AK9: -0.10251721 | AL9: -0.14361191 | AM9: -0.035909221 | AN9: 0.06441886 | AO9: -0.080996885 | AP9: -0.16252073 | AR9: -0.057211538 | AT9: -0.036647642 | AV9: 0.055555556 | AW9: 0.11027569 | AX9: -0.22271386 | AY9: -0.15217391 | AZ9: -0.22506394 | BA9: -0.1937046 | BB9: -0.07721519 | BC9: -0.18550107 | BE9: 0.057692308 | BF9: -0.27793862 | BG9: 0.24337957 | BJ9: -0.13504823 | BK9: -0.15228426 | BL9: 0.14749263 | BM9: -0.14847943 | BO9: 0.057692308 | BQ9: 0.034449761 | BR9: 0.033653846 | BS9: -0.03858145 | BT9: -0.54857143 | BV9: -0.31295337 | BW9: 0.010589803 | BX9: -0.079056739 | BZ9: -0.10204082 | CA9: -0.32990654 | CB9: -0.13501888 | CC9: -0.11863259 | CD9: -0.14893617 | CE9: -0.06097561 | CF9: -0.04293381 | CJ9: -0.0933098 | CK9: -0.16767123 | CL9: -0.045207957 | CN9: 0.0050046598 | CO9: 1.2313874 | CP9: -0.09894624 | CQ9: 0.24835742 | CS9: 0.0034636319 | CT9: -0.17948718 | CU9: -0.030651341 | CV9: -0.055175651 | CW9: -0.093080725 | CX9: -0.13007319 | CY9: -0.58484848 | CZ9: -0.033242243 | DA9: 0.073356968 | DB9: -0.045474614 | DC9: -0.044435496 | DD9: 1.092481 | DF9: -0.058823529 | DI9: -0.17783094 | DJ9: 0.0093023256 | DK9: -0.28670721 | DM9: 0.15704698 | DN9: -0.0090702948 | DP9: -0.069863698 | DQ9: -0.25 | DR9: -0.11469534 | DS9: -0.11900192 | DY9: 0.20422535 | DZ9: 0.17731959 | EA9: -0.17777778 | EB9: -0.071428571 | EC9: -0.20099256 | ED9: -0.15175333 | EE9: -0.2278481 | EF9: -0.038167939 | EG9: -0.042635659 | EK9: -0.036144578 | EL9: -0.20236088 | EM9: 0.025 | EN9: -0.040040544 | EO9: 0.0097431355
A10: 2020 | B10: 11 | C10: 0.10877691 | D10: -0.00010958391 | E10: -0.13020833 | F10: 0.33908046 | H10: 0.16666667 | J10: -0.093415008 | K10: -0.050480769 | M10: 0.15967046 | P10: 0.45867769 | Q10: 0.34185234 | R10: 0.15734099 | T10: -0.32258065 | U10: 0.37873754 | V10: 0.42460317 | X10: 0.093198613 | Y10: -0.069977902 | AB10: 0.067578819 | AD10: 0.96732523 | AE10: 0.10633484 | AH10: 0.48888889 | AI10: 0.3320647 | AK10: 1.5889968 | AL10: 0.037016265 | AM10: 0.34922527 | AN10: 0.11898017 | AO10: 0.0033898305 | AP10: 0.78217822 | AR10: 0.050484447 | AT10: 0.53830163 | AV10: 0.024930748 | AW10: -0.013544018 | AX10: 0.61353574 | AY10: 0.35897436 | AZ10: 0.2310231 | BA10: -0.055055055 | BB10: 0.089163237 | BC10: -0.18324607 | BE10: 0.063636364 | BF10: 0.45682972 | BG10: 0.15922921 | BJ10: -0.37918216 | BK10: 0.02994012 | BL10: 0.11182519 | BM10: 0.20798319 | BO10: 1.0818182 | BQ10: -0.032839963 | BR10: -0.28372093 | BS10: -0.041751115 | BT10: 0.54388186 | BV10: 0.75917547 | BW10: -0.02352533 | BX10: 0.062618388 | BZ10: -0.059659091 | CA10: 0.16317992 | CB10: 0.023286841 | CC10: 0.12229168 | CD10: 0.33333333 | CE10: -0.3961039 | CF10: 0.16074766 | CJ10: 0.068874952 | CK10: 0.020408163 | CL10: 0.034722222 | CN10: 0.0080028191 | CO10: -0.20666782 | CP10: -0.0049554014 | CQ10: 0.84210526 | CS10: 0.14299803 | CT10: 0.265625 | CU10: 0.68379447 | CV10: 0.15606781 | CW10: 0.076899788 | CX10: 0.1585086 | CY10: 0.54501217 | CZ10: 0.1499524 | DA10: 0.087906504 | DB10: 0.27289547 | DC10: 0.10431831 | DD10: 0.44752416 | DF10: 0.23214286 | DI10: 0.14969285 | DJ10: 0.010138249 | DK10: -0.059683313 | DM10: 0.069605568 | DN10: 0.52173913 | DP10: 0.084509744 | DQ10: 0.14184397 | DR10: -0.090418354 | DS10: 0.16013072 | DY10: -0.12280702 | DZ10: 0.58318739 | EA10: 0.1027027 | EB10: 0.11538462 | EC10: -0.052795031 | ED10: 0.21168924 | EE10: 0.098360656 | EF10: 0.20634921 | EG10: 0.23481781 | EK10: 0.0625 | EL10: -0.078224101 | EM10: 0.46829268 | EN10: 0.011542146 | EO10: 0.77192982
A11: 2020 | B11: 12 | C11: 0.037065957 | D11: 3.5711031e-05 | E11: 0.93712575 | F11: -0.27038627 | H11: 0.14519906 | J11: 0.13231982 | K11: 0.15696203 | M11: -0.01759134 | P11: -0.24220963 | Q11: 0.18834446 | R11: 2.5095041 | T11: -0.14857143 | U11: 0.37550201 | V11: -0.069637883 | W11: 0.25390156 | X11: 0.12387916 | Y11: -0.32337633 | AB11: 0.0019235528 | AD11: 0.1208961 | AE11: 0.03135651 | AH11: 0.36318408 | AI11: -0.20535714 | AK11: -0.37037037 | AL11: 0.083288264 | AM11: 0.15547703 | AN11: 0.026006904 | AO11: -0.0033783784 | AP11: -0.17444444 | AR11: -0.0097087379 | AT11: -0.094594595 | AV11: 0.11891892 | AW11: 0.0026152337 | AX11: -0.13563309 | AY11: -0.06918239 | AZ11: -0.09919571 | BA11: -0.081920904 | BB11: 0.023929471 | BC11: -0.17307692 | BE11: 0.72649573 | BF11: 0.20733945 | BG11: 0.024496938 | BJ11: 0.31137725 | BK11: 0.37790698 | BL11: -0.16416185 | BM11: 0.19304348 | BO11: -0.31877729 | BQ11: 0.18507891 | BR11: 0.053571429 | BS11: 0.34517766 | BT11: 0.35146215 | BV11: 1.3292369 | BW11: 0.17297989 | BX11: 0.087780205 | BZ11: 0.48942598 | CA11: 0.19568345 | CB11: 0.17873652 | CC11: 0.1592175 | CD11: -0.15 | CE11: 0.05734767 | CF11: -0.082125604 | CJ11: 0.02577325 | CK11: 0.12419355 | CL11: 0.037217816 | CN11: 1.2447102 | CO11: 0.40056831 | CP11: 0.16533865 | CQ11: 0.18285714 | CS11: 0.23252804 | CT11: 0.022222222 | CU11: -0.0046948357 | CV11: 0.028056124 | CW11: -0.019679505 | CX11: -0.01237828 | CY11: 0.038582677 | CZ11: -0.039152496 | DA11: -0.2241943 | DB11: -0.1744186 | DC11: -0.072585844 | DD11: -0.12404449 | DF11: -0.13768116 | DI11: -0.098143982 | DJ11: -0.20209854 | DK11: -0.11658031 | DM11: -0.42624729 | DN11: 0.15037594 | DP11: 0.049060875 | DQ11: 0.071428571 | DR11: 0.077151335 | DS11: 0.18122066 | DU11: 0.70997104 | DY11: -0.17333333 | DZ11: -0.086283186 | EA11: -0.024509804 | EB11: 0.6062069 | EC11: -0.20655738 | ED11: -0.35490196 | EE11: -0.097014925 | EF11: 1.8453947 | EG11: 0.2579235 | EK11: -0.070588235 | EL11: 0.12844037 | EM11: -0.019933555 | EN11: 0.031924199 | EO11: -0.30693069
A12: 2021 | B12: 1 | C12: -0.010190496 | D12: 0 | E12: 2.2071097 | F12: 0.26470588 | H12: 0.84253579 | J12: -0.095972153 | K12: 0.052516411 | M12: -0.017217631 | P12: -0.011214953 | Q12: 0.31178082 | R12: -0.11173908 | T12: 0.76314318 | U12: -0.37751825 | V12: 0.092814371 | W12: 0.74724749 | X12: -0.16423223 | Y12: 0.19397993 | AB12: -0.0096722765 | AD12: 0.05616816 | AE12: 0.23595506 | AH12: 0.14233577 | AI12: -0.033707865 | AK12: 0.26470588 | AL12: 0.20519221 | AM12: 0.080275229 | AN12: 0.59376402 | AO12: 0.074576271 | AP12: 0.17765814 | AR12: 0.19607843 | AT12: 0.68656716 | AV12: -0.0048309179 | AW12: -0.053472449 | AX12: -0.40952381 | AY12: 1.5 | AZ12: 1.0119048 | BA12: 0.21115385 | BB12: 0.097170972 | BC12: 0 | BE12: -0.0082508251 | BF12: 0.70212766 | BG12: -0.055508113 | BJ12: -0.059360731 | BK12: -0.10970464 | BL12: -0.00802213 | BM12: 0.31195335 | BO12: 0.019230769 | BQ12: -0.030669895 | BR12: 0.798151 | BS12: 0.011006289 | BT12: 0.42568251 | BV12: 2.4601227 | BW12: -0.057861254 | BX12: 0.036535806 | BZ12: 0.27991886 | CA12: -0.38093328 | CB12: 0.86375063 | CC12: 0.2317583 | CD12: 0.30147059 | CE12: -0.071186441 | CF12: -0.072807018 | CJ12: -0.057824221 | CK12: 0.276901 | CL12: 0.15882353 | CN12: 1.407377 | CO12: 0.2 | CP12: -0.12393162 | CQ12: -0.12318841 | CS12: 0.36226811 | CT12: -0.038647343 | CU12: 0.71226415 | CV12: 0.067973621 | CW12: 0.14711787 | CX12: 0.10427807 | CY12: -0.044730857 | CZ12: -0.014116417 | DA12: 0.1589404 | DB12: 0.08318662 | DC12: -0.045169715 | DD12: 0.102397 | DF12: 0.18487395 | DI12: 0.019020892 | DJ12: -0.071469411 | DK12: 1.9061584 | DM12: 0.19848771 | DN12: -0.023529412 | DP12: -0.11142019 | DQ12: 0.031884058 | DR12: 0.12672176 | DS12: 0.16812401 | DU12: -0.087829664 | DY12: 0.77419355 | DZ12: 1.1912833 | EA12: 0.32663317 | EB12: 0.43838557 | EC12: 0.23140496 | ED12: -0.039513678 | EE12: 0.36363636 | EF12: 0.019653179 | EG12: 0.020851434 | EI12: -0.093385924 | EK12: 0.25316456 | EL12: 0.032520325 | EM12: 0.18644068 | EN12: -0.066542347 | EO12: -0.46160714
A13: 2021 | B13: 2 | C13: 0.02780559 | D13: -0.00010959201 | E13: 0.07373494 | F13: 0.16744186 | H13: -0.061043285 | J13: -0.035753575 | K13: 0.12058212 | M13: 0.019621584 | P13: -0.1342155 | Q13: 0.92147034 | R13: 0.037910923 | T13: 0.35289453 | U13: 0.034709193 | V13: 0.10136986 | W13: 0.032328767 | X13: -0.010721104 | Y13: 0.074229692 | AB13: -0.0016287353 | AD13: -0.34486134 | AE13: -0.018716578 | AH13: 0.057507987 | AI13: 0.52906977 | AK13: -0.087209302 | AL13: -0.022783761 | AM13: -0.11004954 | AN13: 0.24883885 | AO13: 0.072555205 | AP13: 0.71428571 | AR13: 0.66393443 | AT13: -0.17256637 | AV13: 0.077669903 | AW13: 0.13193248 | AX13: -0.033026114 | AY13: -0.075675676 | AZ13: 0.79142012 | BA13: -0.13020006 | BB13: -0.1132287 | BC13: 0.14341085 | BE13: -0.013311148 | BF13: -0.034821429 | BG13: 0.14014467 | BJ13: -0.087378641 | BK13: 0.11374408 | BL13: -0.010875627 | BM13: -0.14777778 | BO13: 0.10691824 | BQ13: -0.048293089 | BR13: -0.090831191 | BS13: 0.10202177 | BT13: 0.16312057 | BV13: -0.25531915 | BW13: 0.080643087 | BX13: -0.022566288 | BZ13: -0.12202853 | CA13: 0.29157667 | CB13: -0.20032371 | CC13: -0.010676379 | CD13: -0.10169492 | CE13: 0.02189781 | CF13: 0.4115421 | CJ13: -0.057739027 | CK13: 0.26966292 | CL13: 0.15177665 | CN13: -0.34439905 | CO13: 0.72222006 | CP13: -0.021463415 | CQ13: 0.01046832 | CS13: 0.024665982 | CT13: -0.025125628 | CU13: 0.22727273 | CV13: 0.040018047 | CW13: 0.04275 | CX13: 0.11228814 | CY13: 0.81269841 | CZ13: -0.067130054 | DA13: 0.14415584 | DB13: 0.34457538 | DC13: -0.054800643 | DD13: -0.24308621 | DE13: -0.0089285714 | DF13: 0.092198582 | DI13: 0.020195838 | DJ13: 0.13423645 | DK13: 1.4510595 | DM13: 0.16403785 | DN13: 0.041499331 | DP13: -0.021666951 | DQ13: 0.0056179775 | DR13: -0.015892421 | DS13: -0.08574345 | DU13: -0.038461538 | DY13: -0.14545455 | DZ13: 0.34585635 | EA13: 0.26136364 | EB13: 0.86567164 | EC13: -0.053691275 | ED13: 0.047468354 | EE13: -0.078787879 | EF13: 0.56689342 | EG13: 0.16680851 | EI13: -0.12595841 | EK13: -0.058080808 | EL13: 0.072834646 | EM13: 0.068571429 | EN13: 0.0064180878 | EO13: 0.5721393
A14: 2021 | B14: 3 | C14: 0.045404985 | D14: -0.00010837252 | E14: 0.13105925 | F14: -0.035856574 | H14: -0.0047281324 | J14: 0.045065602 | K14: 0.24860853 | M14: 0.2419244 | P14: 0.13537118 | Q14: -0.11413043 | R14: -0.15581098 | T14: -0.19988277 | U14: -0.16591115 | V14: 0.12437811 | W14: -0.18059979 | X14: -0.15944181 | Y14: -0.0091264668 | AB14: 0.037340338 | AD14: -0.72360558 | AE14: 0.18310627 | AH14: -0.25377644 | AI14: -0.091254753 | AK14: -0.11464968 | AL14: 0.0046629928 | AM14: -0.054075547 | AN14: -0.053307788 | AO14: -0.10882353 | AP14: -0.334 | AR14: -0.12315271 | AT14: -0.096256684 | AV14: -0.10810811 | AW14: -0.10377358 | AX14: -0.32962669 | AY14: -0.10233918 | AZ14: 0.072667217 | BA14: 0.024096386 | BB14: -0.074589128 | BC14: -0.37966102 | BE14: -0.13827993 | BF14: -0.06012951 | BG14: -0.065820777 | BJ14: -0.021276596 | BK14: -0.16170213 | BL14: -0.068508599 | BM14: -0.11994785 | BO14: 0.017045455 | BQ14: 0.045494313 | BR14: -0.45240339 | BS14: -0.042337003 | BT14: -0.1402439 | BV14: -0.14285714 | BW14: -0.021840038 | BX14: 0.037170256 | BZ14: -0.10108303 | CA14: -0.06187291 | CB14: 0.028538659 | CC14: -0.088193811 | CD14: -0.050314465 | CE14: -0.039285714 | CF14: -0.22319035 | CJ14: 0.070803077 | CK14: -0.19469027 | CL14: -0.11855443 | CN14: -0.080238899 | CO14: -0.27258092 | CP14: 0.041874377 | CQ14: -0.10523446 | CS14: -0.10732197 | CT14: -0.048969072 | CU14: 0.14029181 | CV14: 0.13732889 | CW14: 0.056820906 | CX14: -0.046394558 | CY14: -0.045534151 | CZ14: 0.081814411 | DA14: -0.14733258 | DB14: 0.18857661 | DC14: 0.0085458953 | DD14: -0.03458792 | DE14: 0.12012012 | DF14: -0.13636364 | DI14: 0.056088782 | DJ14: -0.37676439 | DK14: -0.074722108 | DM14: -0.098915989 | DN14: 0.020565553 | DP14: 0.028488316 | DQ14: -0.072625698 | DR14: -0.077018634 | DS14: -0.025679196 | DU14: -0.11089655 | DY14: -0.095744681 | DZ14: -0.066912972 | EA14: -0.033033033 | EB14: -0.20088 | EC14: -0.039007092 | ED14: -0.099697885 | EE14: -0.11842105 | EF14: -0.22033285 | EG14: 0.10503282 | EI14: -0.059254084 | EK14: -0.082439678 | EL14: -0.17247706 | EM14: 0.10695187 | EN14: 0.014429012 | EO14: -0.029535865
